Workbook

Sheet Matrix
B1: Not enough data
B2: Data as of July 3, 2024 | D2: Client
E3: Communication | H3: Decision | K3: Drive | N3: Emotion | Q3: Environment | T3: Preference | W3: Priority | Z3: TOTAL
B4: XP | E4: Synchronous | F4: Asynchronous | H4: Data-Driven | I4: Intuition | K4: Small tangible goals | L4: Towards visionary ideas | N4: Investment | O4: Separation | Q4: Flexibility | R4: Structure | T4: One goal in mind | U4: With detailed instructions | W4: Speed of execution | X4: Accuracy of decisions
B5: Communication | C5: Synchronous | D5: # | E5: {=COUNTIFS( rawv3!$F:$F, "<>Ongoing", INDIRECT("rawv3!" & ADDRESS(1, MATCH($D$2 & " " & E$3, rawv3!$1:$1, 0), 4) & ":" & ADDRESS(1048576, MATCH($D$2 & " " & E$3, rawv3!$1:$1, 0), 4)), E$4, INDIRECT("rawv3!" & ADDRESS(1, MATCH($B$4 & " " & $B5, rawv3!$1:$1, 0), 4) & ":" & ADDRESS(1048576, MATCH($B$4 & " " & $B5, rawv3!$1:$1, 0), 4)), $C5 )} -> 595 | F5: {=COUNTIFS( rawv3!$F:$F, "<>Ongoing", INDIRECT("rawv3!" & ADDRESS(1, MATCH($D$2 & " " & E$3, rawv3!$1:$1, 0), 4) & ":" & ADDRESS(1048576, MATCH($D$2 & " " & E$3, rawv3!$1:$1, 0), 4)), F$4, INDIRECT("rawv3!" & ADDRESS(1, MATCH($B$4 & " " & $B5, rawv3!$1:$1, 0), 4) & ":" & ADDRESS(1048576, MATCH($B$4 & " " & $B5, rawv3!$1:$1, 0), 4)), $C5 )} -> 379 | H5: {=COUNTIFS( rawv3!$F:$F, "<>Ongoing", INDIRECT("rawv3!" & ADDRESS(1, MATCH($D$2 & " " & H$3, rawv3!$1:$1, 0), 4) & ":" & ADDRESS(1048576, MATCH($D$2 & " " & H$3, rawv3!$1:$1, 0), 4)), H$4, INDIRECT("rawv3!" & ADDRESS(1, MATCH($B$4 & " " & $B5, rawv3!$1:$1, 0), 4) & ":" & ADDRESS(1048576, MATCH($B$4 & " " & $B5, rawv3!$1:$1, 0), 4)), $C5 )} -> 591 | I5: {=COUNTIFS( rawv3!$F:$F, "<>Ongoing", INDIRECT("rawv3!" & ADDRESS(1, MATCH($D$2 & " " & H$3, rawv3!$1:$1, 0), 4) & ":" & ADDRESS(1048576, MATCH($D$2 & " " & H$3, rawv3!$1:$1, 0), 4)), I$4, INDIRECT("rawv3!" & ADDRESS(1, MATCH($B$4 & " " & $B5, rawv3!$1:$1, 0), 4) & ":" & ADDRESS(1048576, MATCH($B$4 & " " & $B5, rawv3!$1:$1, 0), 4)), $C5 )} -> 385 | K5: {=COUNTIFS( rawv3!$F:$F, "<>Ongoing", INDIRECT("rawv3!" & ADDRESS(1, MATCH($D$2 & " " & K$3, rawv3!$1:$1, 0), 4) & ":" & ADDRESS(1048576, MATCH($D$2 & " " & K$3, rawv3!$1:$1, 0), 4)), K$4, INDIRECT("rawv3!" & ADDRESS(1, MATCH($B$4 & " " & $B5, rawv3!$1:$1, 0), 4) & ":" & ADDRESS(1048576, MATCH($B$4 & " " & $B5, rawv3!$1:$1, 0), 4)), $C5 )} -> 445 | L5: {=COUNTIFS( rawv3!$F:$F, "<>Ongoing", INDIRECT("rawv3!" & ADDRESS(1, MATCH($D$2 & " " & K$3, rawv3!$1:$1, 0), 4) & ":" & ADDRESS(1048576, MATCH($D$2 & " " & K$3, rawv3!$1:$1, 0), 4)), L$4, INDIRECT("rawv3!" & ADDRESS(1, MATCH($B$4 & " " & $B5, rawv3!$1:$1, 0), 4) & ":" & ADDRESS(1048576, MATCH($B$4 & " " & $B5, rawv3!$1:$1, 0), 4)), $C5 )} -> 530 | N5: {=COUNTIFS( rawv3!$F:$F, "<>Ongoing", INDIRECT("rawv3!" & ADDRESS(1, MATCH($D$2 & " " & N$3, rawv3!$1:$1, 0), 4) & ":" & ADDRESS(1048576, MATCH($D$2 & " " & N$3, rawv3!$1:$1, 0), 4)), N$4, INDIRECT("rawv3!" & ADDRESS(1, MATCH($B$4 & " " & $B5, rawv3!$1:$1, 0), 4) & ":" & ADDRESS(1048576, MATCH($B$4 & " " & $B5, rawv3!$1:$1, 0), 4)), $C5 )} -> 595 | O5: {=COUNTIFS( rawv3!$F:$F, "<>Ongoing", INDIRECT("rawv3!" & ADDRESS(1, MATCH($D$2 & " " & N$3, rawv3!$1:$1, 0), 4) & ":" & ADDRESS(1048576, MATCH($D$2 & " " & N$3, rawv3!$1:$1, 0), 4)), O$4, INDIRECT("rawv3!" & ADDRESS(1, MATCH($B$4 & " " & $B5, rawv3!$1:$1, 0), 4) & ":" & ADDRESS(1048576, MATCH($B$4 & " " & $B5, rawv3!$1:$1, 0), 4)), $C5 )} -> 381 | Q5: {=COUNTIFS( rawv3!$F:$F, "<>Ongoing", INDIRECT("rawv3!" & ADDRESS(1, MATCH($D$2 & " " & Q$3, rawv3!$1:$1, 0), 4) & ":" & ADDRESS(1048576, MATCH($D$2 & " " & Q$3, rawv3!$1:$1, 0), 4)), Q$4, INDIRECT("rawv3!" & ADDRESS(1, MATCH($B$4 & " " & $B5, rawv3!$1:$1, 0), 4) & ":" & ADDRESS(1048576, MATCH($B$4 & " " & $B5, rawv3!$1:$1, 0), 4)), $C5 )} -> 690 | R5: {=COUNTIFS( rawv3!$F:$F, "<>Ongoing", INDIRECT("rawv3!" & ADDRESS(1, MATCH($D$2 & " " & Q$3, rawv3!$1:$1, 0), 4) & ":" & ADDRESS(1048576, MATCH($D$2 & " " & Q$3, rawv3!$1:$1, 0), 4)), R$4, INDIRECT("rawv3!" & ADDRESS(1, MATCH($B$4 & " " & $B5, rawv3!$1:$1, 0), 4) & ":" & ADDRESS(1048576, MATCH($B$4 & " " & $B5, rawv3!$1:$1, 0), 4)), $C5 )} -> 285 | T5: {=COUNTIFS( rawv3!$F:$F, "<>Ongoing", INDIRECT("rawv3!" & ADDRESS(1, MATCH($D$2 & " " & T$3, rawv3!$1:$1, 0), 4) & ":" & ADDRESS(1048576, MATCH($D$2 & " " & T$3, rawv3!$1:$1, 0), 4)), T$4, INDIRECT("rawv3!" & ADDRESS(1, MATCH($B$4 & " " & $B5, rawv3!$1:$1, 0), 4) & ":" & ADDRESS(1048576, MATCH($B$4 & " " & $B5, rawv3!$1:$1, 0), 4)), $C5 )} -> 743 | U5: {=COUNTIFS( rawv3!$F:$F, "<>Ongoing", INDIRECT("rawv3!" & ADDRESS(1, MATCH($D$2 & " " & T$3, rawv3!$1:$1, 0), 4) & ":" & ADDRESS(1048576, MATCH($D$2 & " " & T$3, rawv3!$1:$1, 0), 4)), U$4, INDIRECT("rawv3!" & ADDRESS(1, MATCH($B$4 & " " & $B5, rawv3!$1:$1, 0), 4) & ":" & ADDRESS(1048576, MATCH($B$4 & " " & $B5, rawv3!$1:$1, 0), 4)), $C5 )} -> 232 | W5: {=COUNTIFS( rawv3!$F:$F, "<>Ongoing", INDIRECT("rawv3!" & ADDRESS(1, MATCH($D$2 & " " & W$3, rawv3!$1:$1, 0), 4) & ":" & ADDRESS(1048576, MATCH($D$2 & " " & W$3, rawv3!$1:$1, 0), 4)), W$4, INDIRECT("rawv3!" & ADDRESS(1, MATCH($B$4 & " " & $B5, rawv3!$1:$1, 0), 4) & ":" & ADDRESS(1048576, MATCH($B$4 & " " & $B5, rawv3!$1:$1, 0), 4)), $C5 )} -> 436 | X5: {=COUNTIFS( rawv3!$F:$F, "<>Ongoing", INDIRECT("rawv3!" & ADDRESS(1, MATCH($D$2 & " " & W$3, rawv3!$1:$1, 0), 4) & ":" & ADDRESS(1048576, MATCH($D$2 & " " & W$3, rawv3!$1:$1, 0), 4)), X$4, INDIRECT("rawv3!" & ADDRESS(1, MATCH($B$4 & " " & $B5, rawv3!$1:$1, 0), 4) & ":" & ADDRESS(1048576, MATCH($B$4 & " " & $B5, rawv3!$1:$1, 0), 4)), $C5 )} -> 540 | Z5: {=COUNTIFS( rawv3!$F:$F, "<>Ongoing", INDIRECT("rawv3!" & ADDRESS(1, MATCH($B$4 & " " & $B5, rawv3!$1:$1, 0), 4) & ":" & ADDRESS(1048576, MATCH($B$4 & " " & $B5, rawv3!$1:$1, 0), 4)), $C5)} -> 976
D6: F90D % | E6: {=COUNTIFS( rawv3!$F:$F, "Success", INDIRECT("rawv3!" & ADDRESS(1, MATCH($D$2 & " " & E$3, rawv3!$1:$1, 0), 4) & ":" & ADDRESS(1048576, MATCH($D$2 & " " & E$3, rawv3!$1:$1, 0), 4)), E$4, INDIRECT("rawv3!" & ADDRESS(1, MATCH($B$4 & " " & $B5, rawv3!$1:$1, 0), 4) & ":" & ADDRESS(1048576, MATCH($B$4 & " " & $B5, rawv3!$1:$1, 0), 4)), $C5 )/E5} -> 0.77142857 | F6: {=COUNTIFS( rawv3!$F:$F, "Success", INDIRECT("rawv3!" & ADDRESS(1, MATCH($D$2 & " " & E$3, rawv3!$1:$1, 0), 4) & ":" & ADDRESS(1048576, MATCH($D$2 & " " & E$3, rawv3!$1:$1, 0), 4)), F$4, INDIRECT("rawv3!" & ADDRESS(1, MATCH($B$4 & " " & $B5, rawv3!$1:$1, 0), 4) & ":" & ADDRESS(1048576, MATCH($B$4 & " " & $B5, rawv3!$1:$1, 0), 4)), $C5 )/F5} -> 0.77308707 | H6: {=COUNTIFS( rawv3!$F:$F, "Success", INDIRECT("rawv3!" & ADDRESS(1, MATCH($D$2 & " " & H$3, rawv3!$1:$1, 0), 4) & ":" & ADDRESS(1048576, MATCH($D$2 & " " & H$3, rawv3!$1:$1, 0), 4)), H$4, INDIRECT("rawv3!" & ADDRESS(1, MATCH($B$4 & " " & $B5, rawv3!$1:$1, 0), 4) & ":" & ADDRESS(1048576, MATCH($B$4 & " " & $B5, rawv3!$1:$1, 0), 4)), $C5 )/H5} -> 0.77834179 | I6: {=COUNTIFS( rawv3!$F:$F, "Success", INDIRECT("rawv3!" & ADDRESS(1, MATCH($D$2 & " " & H$3, rawv3!$1:$1, 0), 4) & ":" & ADDRESS(1048576, MATCH($D$2 & " " & H$3, rawv3!$1:$1, 0), 4)), I$4, INDIRECT("rawv3!" & ADDRESS(1, MATCH($B$4 & " " & $B5, rawv3!$1:$1, 0), 4) & ":" & ADDRESS(1048576, MATCH($B$4 & " " & $B5, rawv3!$1:$1, 0), 4)), $C5 )/I5} -> 0.76363636 | K6: {=COUNTIFS( rawv3!$F:$F, "Success", INDIRECT("rawv3!" & ADDRESS(1, MATCH($D$2 & " " & K$3, rawv3!$1:$1, 0), 4) & ":" & ADDRESS(1048576, MATCH($D$2 & " " & K$3, rawv3!$1:$1, 0), 4)), K$4, INDIRECT("rawv3!" & ADDRESS(1, MATCH($B$4 & " " & $B5, rawv3!$1:$1, 0), 4) & ":" & ADDRESS(1048576, MATCH($B$4 & " " & $B5, rawv3!$1:$1, 0), 4)), $C5 )/K5} -> 0.74157303 | L6: {=COUNTIFS( rawv3!$F:$F, "Success", INDIRECT("rawv3!" & ADDRESS(1, MATCH($D$2 & " " & K$3, rawv3!$1:$1, 0), 4) & ":" & ADDRESS(1048576, MATCH($D$2 & " " & K$3, rawv3!$1:$1, 0), 4)), L$4, INDIRECT("rawv3!" & ADDRESS(1, MATCH($B$4 & " " & $B5, rawv3!$1:$1, 0), 4) & ":" & ADDRESS(1048576, MATCH($B$4 & " " & $B5, rawv3!$1:$1, 0), 4)), $C5 )/L5} -> 0.8 | N6: {=COUNTIFS( rawv3!$F:$F, "Success", INDIRECT("rawv3!" & ADDRESS(1, MATCH($D$2 & " " & N$3, rawv3!$1:$1, 0), 4) & ":" & ADDRESS(1048576, MATCH($D$2 & " " & N$3, rawv3!$1:$1, 0), 4)), N$4, INDIRECT("rawv3!" & ADDRESS(1, MATCH($B$4 & " " & $B5, rawv3!$1:$1, 0), 4) & ":" & ADDRESS(1048576, MATCH($B$4 & " " & $B5, rawv3!$1:$1, 0), 4)), $C5 )/N5} -> 0.77310924 | O6: {=COUNTIFS( rawv3!$F:$F, "Success", INDIRECT("rawv3!" & ADDRESS(1, MATCH($D$2 & " " & N$3, rawv3!$1:$1, 0), 4) & ":" & ADDRESS(1048576, MATCH($D$2 & " " & N$3, rawv3!$1:$1, 0), 4)), O$4, INDIRECT("rawv3!" & ADDRESS(1, MATCH($B$4 & " " & $B5, rawv3!$1:$1, 0), 4) & ":" & ADDRESS(1048576, MATCH($B$4 & " " & $B5, rawv3!$1:$1, 0), 4)), $C5 )/O5} -> 0.77165354 | Q6: {=COUNTIFS( rawv3!$F:$F, "Success", INDIRECT("rawv3!" & ADDRESS(1, MATCH($D$2 & " " & Q$3, rawv3!$1:$1, 0), 4) & ":" & ADDRESS(1048576, MATCH($D$2 & " " & Q$3, rawv3!$1:$1, 0), 4)), Q$4, INDIRECT("rawv3!" & ADDRESS(1, MATCH($B$4 & " " & $B5, rawv3!$1:$1, 0), 4) & ":" & ADDRESS(1048576, MATCH($B$4 & " " & $B5, rawv3!$1:$1, 0), 4)), $C5 )/Q5} -> 0.77681159 | R6: {=COUNTIFS( rawv3!$F:$F, "Success", INDIRECT("rawv3!" & ADDRESS(1, MATCH($D$2 & " " & Q$3, rawv3!$1:$1, 0), 4) & ":" & ADDRESS(1048576, MATCH($D$2 & " " & Q$3, rawv3!$1:$1, 0), 4)), R$4, INDIRECT("rawv3!" & ADDRESS(1, MATCH($B$4 & " " & $B5, rawv3!$1:$1, 0), 4) & ":" & ADDRESS(1048576, MATCH($B$4 & " " & $B5, rawv3!$1:$1, 0), 4)), $C5 )/R5} -> 0.76491228 | T6: {=COUNTIFS( rawv3!$F:$F, "Success", INDIRECT("rawv3!" & ADDRESS(1, MATCH($D$2 & " " & T$3, rawv3!$1:$1, 0), 4) & ":" & ADDRESS(1048576, MATCH($D$2 & " " & T$3, rawv3!$1:$1, 0), 4)), T$4, INDIRECT("rawv3!" & ADDRESS(1, MATCH($B$4 & " " & $B5, rawv3!$1:$1, 0), 4) & ":" & ADDRESS(1048576, MATCH($B$4 & " " & $B5, rawv3!$1:$1, 0), 4)), $C5 )/T5} -> 0.7846568 | U6: {=COUNTIFS( rawv3!$F:$F, "Success", INDIRECT("rawv3!" & ADDRESS(1, MATCH($D$2 & " " & T$3, rawv3!$1:$1, 0), 4) & ":" & ADDRESS(1048576, MATCH($D$2 & " " & T$3, rawv3!$1:$1, 0), 4)), U$4, INDIRECT("rawv3!" & ADDRESS(1, MATCH($B$4 & " " & $B5, rawv3!$1:$1, 0), 4) & ":" & ADDRESS(1048576, MATCH($B$4 & " " & $B5, rawv3!$1:$1, 0), 4)), $C5 )/U5} -> 0.73275862 | W6: {=COUNTIFS( rawv3!$F:$F, "Success", INDIRECT("rawv3!" & ADDRESS(1, MATCH($D$2 & " " & W$3, rawv3!$1:$1, 0), 4) & ":" & ADDRESS(1048576, MATCH($D$2 & " " & W$3, rawv3!$1:$1, 0), 4)), W$4, INDIRECT("rawv3!" & ADDRESS(1, MATCH($B$4 & " " & $B5, rawv3!$1:$1, 0), 4) & ":" & ADDRESS(1048576, MATCH($B$4 & " " & $B5, rawv3!$1:$1, 0), 4)), $C5 )/W5} -> 0.76146789 | X6: {=COUNTIFS( rawv3!$F:$F, "Success", INDIRECT("rawv3!" & ADDRESS(1, MATCH($D$2 & " " & W$3, rawv3!$1:$1, 0), 4) & ":" & ADDRESS(1048576, MATCH($D$2 & " " & W$3, rawv3!$1:$1, 0), 4)), X$4, INDIRECT("rawv3!" & ADDRESS(1, MATCH($B$4 & " " & $B5, rawv3!$1:$1, 0), 4) & ":" & ADDRESS(1048576, MATCH($B$4 & " " & $B5, rawv3!$1:$1, 0), 4)), $C5 )/X5} -> 0.78148148 | Z6: {=COUNTIFS( rawv3!$F:$F, "Success", INDIRECT("rawv3!" & ADDRESS(1, MATCH($B$4 & " " & $B5, rawv3!$1:$1, 0), 4) & ":" & ADDRESS(1048576, MATCH($B$4 & " " & $B5, rawv3!$1:$1, 0), 4)), $C5)/Z5} -> 0.77254098 | AA6: {=COUNTIFS( rawv3!$F:$F, "Success", INDIRECT("rawv3!" & ADDRESS(1, MATCH($B$4 & " " & $B5, rawv3!$1:$1, 0), 4) & ":" & ADDRESS(1048576, MATCH($B$4 & " " & $B5, rawv3!$1:$1, 0), 4)), $C5)} -> 754
C7: Asynchronous | D7: # | E7: {=COUNTIFS( rawv3!$F:$F, "<>Ongoing", INDIRECT("rawv3!" & ADDRESS(1, MATCH($D$2 & " " & E$3, rawv3!$1:$1, 0), 4) & ":" & ADDRESS(1048576, MATCH($D$2 & " " & E$3, rawv3!$1:$1, 0), 4)), E$4, INDIRECT("rawv3!" & ADDRESS(1, MATCH($B$4 & " " & $B5, rawv3!$1:$1, 0), 4) & ":" & ADDRESS(1048576, MATCH($B$4 & " " & $B5, rawv3!$1:$1, 0), 4)), $C7 )} -> 688 | F7: {=COUNTIFS( rawv3!$F:$F, "<>Ongoing", INDIRECT("rawv3!" & ADDRESS(1, MATCH($D$2 & " " & E$3, rawv3!$1:$1, 0), 4) & ":" & ADDRESS(1048576, MATCH($D$2 & " " & E$3, rawv3!$1:$1, 0), 4)), F$4, INDIRECT("rawv3!" & ADDRESS(1, MATCH($B$4 & " " & $B5, rawv3!$1:$1, 0), 4) & ":" & ADDRESS(1048576, MATCH($B$4 & " " & $B5, rawv3!$1:$1, 0), 4)), $C7 )} -> 871 | H7: {=COUNTIFS( rawv3!$F:$F, "<>Ongoing", INDIRECT("rawv3!" & ADDRESS(1, MATCH($D$2 & " " & H$3, rawv3!$1:$1, 0), 4) & ":" & ADDRESS(1048576, MATCH($D$2 & " " & H$3, rawv3!$1:$1, 0), 4)), H$4, INDIRECT("rawv3!" & ADDRESS(1, MATCH($B$4 & " " & $B5, rawv3!$1:$1, 0), 4) & ":" & ADDRESS(1048576, MATCH($B$4 & " " & $B5, rawv3!$1:$1, 0), 4)), $C7 )} -> 953 | I7: {=COUNTIFS( rawv3!$F:$F, "<>Ongoing", INDIRECT("rawv3!" & ADDRESS(1, MATCH($D$2 & " " & H$3, rawv3!$1:$1, 0), 4) & ":" & ADDRESS(1048576, MATCH($D$2 & " " & H$3, rawv3!$1:$1, 0), 4)), I$4, INDIRECT("rawv3!" & ADDRESS(1, MATCH($B$4 & " " & $B5, rawv3!$1:$1, 0), 4) & ":" & ADDRESS(1048576, MATCH($B$4 & " " & $B5, rawv3!$1:$1, 0), 4)), $C7 )} -> 609 | K7: {=COUNTIFS( rawv3!$F:$F, "<>Ongoing", INDIRECT("rawv3!" & ADDRESS(1, MATCH($D$2 & " " & K$3, rawv3!$1:$1, 0), 4) & ":" & ADDRESS(1048576, MATCH($D$2 & " " & K$3, rawv3!$1:$1, 0), 4)), K$4, INDIRECT("rawv3!" & ADDRESS(1, MATCH($B$4 & " " & $B5, rawv3!$1:$1, 0), 4) & ":" & ADDRESS(1048576, MATCH($B$4 & " " & $B5, rawv3!$1:$1, 0), 4)), $C7 )} -> 777 | L7: {=COUNTIFS( rawv3!$F:$F, "<>Ongoing", INDIRECT("rawv3!" & ADDRESS(1, MATCH($D$2 & " " & K$3, rawv3!$1:$1, 0), 4) & ":" & ADDRESS(1048576, MATCH($D$2 & " " & K$3, rawv3!$1:$1, 0), 4)), L$4, INDIRECT("rawv3!" & ADDRESS(1, MATCH($B$4 & " " & $B5, rawv3!$1:$1, 0), 4) & ":" & ADDRESS(1048576, MATCH($B$4 & " " & $B5, rawv3!$1:$1, 0), 4)), $C7 )} -> 785 | N7: {=COUNTIFS( rawv3!$F:$F, "<>Ongoing", INDIRECT("rawv3!" & ADDRESS(1, MATCH($D$2 & " " & N$3, rawv3!$1:$1, 0), 4) & ":" & ADDRESS(1048576, MATCH($D$2 & " " & N$3, rawv3!$1:$1, 0), 4)), N$4, INDIRECT("rawv3!" & ADDRESS(1, MATCH($B$4 & " " & $B5, rawv3!$1:$1, 0), 4) & ":" & ADDRESS(1048576, MATCH($B$4 & " " & $B5, rawv3!$1:$1, 0), 4)), $C7 )} -> 926 | O7: {=COUNTIFS( rawv3!$F:$F, "<>Ongoing", INDIRECT("rawv3!" & ADDRESS(1, MATCH($D$2 & " " & N$3, rawv3!$1:$1, 0), 4) & ":" & ADDRESS(1048576, MATCH($D$2 & " " & N$3, rawv3!$1:$1, 0), 4)), O$4, INDIRECT("rawv3!" & ADDRESS(1, MATCH($B$4 & " " & $B5, rawv3!$1:$1, 0), 4) & ":" & ADDRESS(1048576, MATCH($B$4 & " " & $B5, rawv3!$1:$1, 0), 4)), $C7 )} -> 636 | Q7: {=COUNTIFS( rawv3!$F:$F, "<>Ongoing", INDIRECT("rawv3!" & ADDRESS(1, MATCH($D$2 & " " & Q$3, rawv3!$1:$1, 0), 4) & ":" & ADDRESS(1048576, MATCH($D$2 & " " & Q$3, rawv3!$1:$1, 0), 4)), Q$4, INDIRECT("rawv3!" & ADDRESS(1, MATCH($B$4 & " " & $B5, rawv3!$1:$1, 0), 4) & ":" & ADDRESS(1048576, MATCH($B$4 & " " & $B5, rawv3!$1:$1, 0), 4)), $C7 )} -> 1150 | R7: {=COUNTIFS( rawv3!$F:$F, "<>Ongoing", INDIRECT("rawv3!" & ADDRESS(1, MATCH($D$2 & " " & Q$3, rawv3!$1:$1, 0), 4) & ":" & ADDRESS(1048576, MATCH($D$2 & " " & Q$3, rawv3!$1:$1, 0), 4)), R$4, INDIRECT("rawv3!" & ADDRESS(1, MATCH($B$4 & " " & $B5, rawv3!$1:$1, 0), 4) & ":" & ADDRESS(1048576, MATCH($B$4 & " " & $B5, rawv3!$1:$1, 0), 4)), $C7 )} -> 411 | T7: {=COUNTIFS( rawv3!$F:$F, "<>Ongoing", INDIRECT("rawv3!" & ADDRESS(1, MATCH($D$2 & " " & T$3, rawv3!$1:$1, 0), 4) & ":" & ADDRESS(1048576, MATCH($D$2 & " " & T$3, rawv3!$1:$1, 0), 4)), T$4, INDIRECT("rawv3!" & ADDRESS(1, MATCH($B$4 & " " & $B5, rawv3!$1:$1, 0), 4) & ":" & ADDRESS(1048576, MATCH($B$4 & " " & $B5, rawv3!$1:$1, 0), 4)), $C7 )} -> 1178 | U7: {=COUNTIFS( rawv3!$F:$F, "<>Ongoing", INDIRECT("rawv3!" & ADDRESS(1, MATCH($D$2 & " " & T$3, rawv3!$1:$1, 0), 4) & ":" & ADDRESS(1048576, MATCH($D$2 & " " & T$3, rawv3!$1:$1, 0), 4)), U$4, INDIRECT("rawv3!" & ADDRESS(1, MATCH($B$4 & " " & $B5, rawv3!$1:$1, 0), 4) & ":" & ADDRESS(1048576, MATCH($B$4 & " " & $B5, rawv3!$1:$1, 0), 4)), $C7 )} -> 384 | W7: {=COUNTIFS( rawv3!$F:$F, "<>Ongoing", INDIRECT("rawv3!" & ADDRESS(1, MATCH($D$2 & " " & W$3, rawv3!$1:$1, 0), 4) & ":" & ADDRESS(1048576, MATCH($D$2 & " " & W$3, rawv3!$1:$1, 0), 4)), W$4, INDIRECT("rawv3!" & ADDRESS(1, MATCH($B$4 & " " & $B5, rawv3!$1:$1, 0), 4) & ":" & ADDRESS(1048576, MATCH($B$4 & " " & $B5, rawv3!$1:$1, 0), 4)), $C7 )} -> 691 | X7: {=COUNTIFS( rawv3!$F:$F, "<>Ongoing", INDIRECT("rawv3!" & ADDRESS(1, MATCH($D$2 & " " & W$3, rawv3!$1:$1, 0), 4) & ":" & ADDRESS(1048576, MATCH($D$2 & " " & W$3, rawv3!$1:$1, 0), 4)), X$4, INDIRECT("rawv3!" & ADDRESS(1, MATCH($B$4 & " " & $B5, rawv3!$1:$1, 0), 4) & ":" & ADDRESS(1048576, MATCH($B$4 & " " & $B5, rawv3!$1:$1, 0), 4)), $C7 )} -> 871 | Z7: {=COUNTIFS( rawv3!$F:$F, "<>Ongoing", INDIRECT("rawv3!" & ADDRESS(1, MATCH($B$4 & " " & $B5, rawv3!$1:$1, 0), 4) & ":" & ADDRESS(1048576, MATCH($B$4 & " " & $B5, rawv3!$1:$1, 0), 4)), $C7)} -> 1562
D8: F90D % | E8: {=COUNTIFS( rawv3!$F:$F, "Success", INDIRECT("rawv3!" & ADDRESS(1, MATCH($D$2 & " " & E$3, rawv3!$1:$1, 0), 4) & ":" & ADDRESS(1048576, MATCH($D$2 & " " & E$3, rawv3!$1:$1, 0), 4)), E$4, INDIRECT("rawv3!" & ADDRESS(1, MATCH($B$4 & " " & $B5, rawv3!$1:$1, 0), 4) & ":" & ADDRESS(1048576, MATCH($B$4 & " " & $B5, rawv3!$1:$1, 0), 4)), $C7 )/E7} -> 0.78633721 | F8: {=COUNTIFS( rawv3!$F:$F, "Success", INDIRECT("rawv3!" & ADDRESS(1, MATCH($D$2 & " " & E$3, rawv3!$1:$1, 0), 4) & ":" & ADDRESS(1048576, MATCH($D$2 & " " & E$3, rawv3!$1:$1, 0), 4)), F$4, INDIRECT("rawv3!" & ADDRESS(1, MATCH($B$4 & " " & $B5, rawv3!$1:$1, 0), 4) & ":" & ADDRESS(1048576, MATCH($B$4 & " " & $B5, rawv3!$1:$1, 0), 4)), $C7 )/F7} -> 0.80941447 | H8: {=COUNTIFS( rawv3!$F:$F, "Success", INDIRECT("rawv3!" & ADDRESS(1, MATCH($D$2 & " " & H$3, rawv3!$1:$1, 0), 4) & ":" & ADDRESS(1048576, MATCH($D$2 & " " & H$3, rawv3!$1:$1, 0), 4)), H$4, INDIRECT("rawv3!" & ADDRESS(1, MATCH($B$4 & " " & $B5, rawv3!$1:$1, 0), 4) & ":" & ADDRESS(1048576, MATCH($B$4 & " " & $B5, rawv3!$1:$1, 0), 4)), $C7 )/H7} -> 0.8069255 | I8: {=COUNTIFS( rawv3!$F:$F, "Success", INDIRECT("rawv3!" & ADDRESS(1, MATCH($D$2 & " " & H$3, rawv3!$1:$1, 0), 4) & ":" & ADDRESS(1048576, MATCH($D$2 & " " & H$3, rawv3!$1:$1, 0), 4)), I$4, INDIRECT("rawv3!" & ADDRESS(1, MATCH($B$4 & " " & $B5, rawv3!$1:$1, 0), 4) & ":" & ADDRESS(1048576, MATCH($B$4 & " " & $B5, rawv3!$1:$1, 0), 4)), $C7 )/I7} -> 0.78817734 | K8: {=COUNTIFS( rawv3!$F:$F, "Success", INDIRECT("rawv3!" & ADDRESS(1, MATCH($D$2 & " " & K$3, rawv3!$1:$1, 0), 4) & ":" & ADDRESS(1048576, MATCH($D$2 & " " & K$3, rawv3!$1:$1, 0), 4)), K$4, INDIRECT("rawv3!" & ADDRESS(1, MATCH($B$4 & " " & $B5, rawv3!$1:$1, 0), 4) & ":" & ADDRESS(1048576, MATCH($B$4 & " " & $B5, rawv3!$1:$1, 0), 4)), $C7 )/K7} -> 0.81338481 | L8: {=COUNTIFS( rawv3!$F:$F, "Success", INDIRECT("rawv3!" & ADDRESS(1, MATCH($D$2 & " " & K$3, rawv3!$1:$1, 0), 4) & ":" & ADDRESS(1048576, MATCH($D$2 & " " & K$3, rawv3!$1:$1, 0), 4)), L$4, INDIRECT("rawv3!" & ADDRESS(1, MATCH($B$4 & " " & $B5, rawv3!$1:$1, 0), 4) & ":" & ADDRESS(1048576, MATCH($B$4 & " " & $B5, rawv3!$1:$1, 0), 4)), $C7 )/L7} -> 0.78598726 | N8: {=COUNTIFS( rawv3!$F:$F, "Success", INDIRECT("rawv3!" & ADDRESS(1, MATCH($D$2 & " " & N$3, rawv3!$1:$1, 0), 4) & ":" & ADDRESS(1048576, MATCH($D$2 & " " & N$3, rawv3!$1:$1, 0), 4)), N$4, INDIRECT("rawv3!" & ADDRESS(1, MATCH($B$4 & " " & $B5, rawv3!$1:$1, 0), 4) & ":" & ADDRESS(1048576, MATCH($B$4 & " " & $B5, rawv3!$1:$1, 0), 4)), $C7 )/N7} -> 0.80669546 | O8: {=COUNTIFS( rawv3!$F:$F, "Success", INDIRECT("rawv3!" & ADDRESS(1, MATCH($D$2 & " " & N$3, rawv3!$1:$1, 0), 4) & ":" & ADDRESS(1048576, MATCH($D$2 & " " & N$3, rawv3!$1:$1, 0), 4)), O$4, INDIRECT("rawv3!" & ADDRESS(1, MATCH($B$4 & " " & $B5, rawv3!$1:$1, 0), 4) & ":" & ADDRESS(1048576, MATCH($B$4 & " " & $B5, rawv3!$1:$1, 0), 4)), $C7 )/O7} -> 0.78930818 | Q8: {=COUNTIFS( rawv3!$F:$F, "Success", INDIRECT("rawv3!" & ADDRESS(1, MATCH($D$2 & " " & Q$3, rawv3!$1:$1, 0), 4) & ":" & ADDRESS(1048576, MATCH($D$2 & " " & Q$3, rawv3!$1:$1, 0), 4)), Q$4, INDIRECT("rawv3!" & ADDRESS(1, MATCH($B$4 & " " & $B5, rawv3!$1:$1, 0), 4) & ":" & ADDRESS(1048576, MATCH($B$4 & " " & $B5, rawv3!$1:$1, 0), 4)), $C7 )/Q7} -> 0.80608696 | R8: {=COUNTIFS( rawv3!$F:$F, "Success", INDIRECT("rawv3!" & ADDRESS(1, MATCH($D$2 & " " & Q$3, rawv3!$1:$1, 0), 4) & ":" & ADDRESS(1048576, MATCH($D$2 & " " & Q$3, rawv3!$1:$1, 0), 4)), R$4, INDIRECT("rawv3!" & ADDRESS(1, MATCH($B$4 & " " & $B5, rawv3!$1:$1, 0), 4) & ":" & ADDRESS(1048576, MATCH($B$4 & " " & $B5, rawv3!$1:$1, 0), 4)), $C7 )/R7} -> 0.7810219 | T8: {=COUNTIFS( rawv3!$F:$F, "Success", INDIRECT("rawv3!" & ADDRESS(1, MATCH($D$2 & " " & T$3, rawv3!$1:$1, 0), 4) & ":" & ADDRESS(1048576, MATCH($D$2 & " " & T$3, rawv3!$1:$1, 0), 4)), T$4, INDIRECT("rawv3!" & ADDRESS(1, MATCH($B$4 & " " & $B5, rawv3!$1:$1, 0), 4) & ":" & ADDRESS(1048576, MATCH($B$4 & " " & $B5, rawv3!$1:$1, 0), 4)), $C7 )/T7} -> 0.79541596 | U8: {=COUNTIFS( rawv3!$F:$F, "Success", INDIRECT("rawv3!" & ADDRESS(1, MATCH($D$2 & " " & T$3, rawv3!$1:$1, 0), 4) & ":" & ADDRESS(1048576, MATCH($D$2 & " " & T$3, rawv3!$1:$1, 0), 4)), U$4, INDIRECT("rawv3!" & ADDRESS(1, MATCH($B$4 & " " & $B5, rawv3!$1:$1, 0), 4) & ":" & ADDRESS(1048576, MATCH($B$4 & " " & $B5, rawv3!$1:$1, 0), 4)), $C7 )/U7} -> 0.8125 | W8: {=COUNTIFS( rawv3!$F:$F, "Success", INDIRECT("rawv3!" & ADDRESS(1, MATCH($D$2 & " " & W$3, rawv3!$1:$1, 0), 4) & ":" & ADDRESS(1048576, MATCH($D$2 & " " & W$3, rawv3!$1:$1, 0), 4)), W$4, INDIRECT("rawv3!" & ADDRESS(1, MATCH($B$4 & " " & $B5, rawv3!$1:$1, 0), 4) & ":" & ADDRESS(1048576, MATCH($B$4 & " " & $B5, rawv3!$1:$1, 0), 4)), $C7 )/W7} -> 0.79015919 | X8: {=COUNTIFS( rawv3!$F:$F, "Success", INDIRECT("rawv3!" & ADDRESS(1, MATCH($D$2 & " " & W$3, rawv3!$1:$1, 0), 4) & ":" & ADDRESS(1048576, MATCH($D$2 & " " & W$3, rawv3!$1:$1, 0), 4)), X$4, INDIRECT("rawv3!" & ADDRESS(1, MATCH($B$4 & " " & $B5, rawv3!$1:$1, 0), 4) & ":" & ADDRESS(1048576, MATCH($B$4 & " " & $B5, rawv3!$1:$1, 0), 4)), $C7 )/X7} -> 0.80711825 | Z8: {=COUNTIFS( rawv3!$F:$F, "Success", INDIRECT("rawv3!" & ADDRESS(1, MATCH($B$4 & " " & $B5, rawv3!$1:$1, 0), 4) & ":" & ADDRESS(1048576, MATCH($B$4 & " " & $B5, rawv3!$1:$1, 0), 4)), $C7)/Z7} -> 0.79961588 | AA8: {=COUNTIFS( rawv3!$F:$F, "Success", INDIRECT("rawv3!" & ADDRESS(1, MATCH($B$4 & " " & $B5, rawv3!$1:$1, 0), 4) & ":" & ADDRESS(1048576, MATCH($B$4 & " " & $B5, rawv3!$1:$1, 0), 4)), $C7)} -> 1249
B10: Decision | C10: Data-Driven | D10: # | E10: {=COUNTIFS( rawv3!$F:$F, "<>Ongoing", INDIRECT("rawv3!" & ADDRESS(1, MATCH($D$2 & " " & E$3, rawv3!$1:$1, 0), 4) & ":" & ADDRESS(1048576, MATCH($D$2 & " " & E$3, rawv3!$1:$1, 0), 4)), E$4, INDIRECT("rawv3!" & ADDRESS(1, MATCH($B$4 & " " & $B10, rawv3!$1:$1, 0), 4) & ":" & ADDRESS(1048576, MATCH($B$4 & " " & $B10, rawv3!$1:$1, 0), 4)), $C10 )} -> 1196 | F10: {=COUNTIFS( rawv3!$F:$F, "<>Ongoing", INDIRECT("rawv3!" & ADDRESS(1, MATCH($D$2 & " " & E$3, rawv3!$1:$1, 0), 4) & ":" & ADDRESS(1048576, MATCH($D$2 & " " & E$3, rawv3!$1:$1, 0), 4)), F$4, INDIRECT("rawv3!" & ADDRESS(1, MATCH($B$4 & " " & $B10, rawv3!$1:$1, 0), 4) & ":" & ADDRESS(1048576, MATCH($B$4 & " " & $B10, rawv3!$1:$1, 0), 4)), $C10 )} -> 1163 | H10: {=COUNTIFS( rawv3!$F:$F, "<>Ongoing", INDIRECT("rawv3!" & ADDRESS(1, MATCH($D$2 & " " & H$3, rawv3!$1:$1, 0), 4) & ":" & ADDRESS(1048576, MATCH($D$2 & " " & H$3, rawv3!$1:$1, 0), 4)), H$4, INDIRECT("rawv3!" & ADDRESS(1, MATCH($B$4 & " " & $B10, rawv3!$1:$1, 0), 4) & ":" & ADDRESS(1048576, MATCH($B$4 & " " & $B10, rawv3!$1:$1, 0), 4)), $C10 )} -> 1460 | I10: {=COUNTIFS( rawv3!$F:$F, "<>Ongoing", INDIRECT("rawv3!" & ADDRESS(1, MATCH($D$2 & " " & H$3, rawv3!$1:$1, 0), 4) & ":" & ADDRESS(1048576, MATCH($D$2 & " " & H$3, rawv3!$1:$1, 0), 4)), I$4, INDIRECT("rawv3!" & ADDRESS(1, MATCH($B$4 & " " & $B10, rawv3!$1:$1, 0), 4) & ":" & ADDRESS(1048576, MATCH($B$4 & " " & $B10, rawv3!$1:$1, 0), 4)), $C10 )} -> 904 | K10: {=COUNTIFS( rawv3!$F:$F, "<>Ongoing", INDIRECT("rawv3!" & ADDRESS(1, MATCH($D$2 & " " & K$3, rawv3!$1:$1, 0), 4) & ":" & ADDRESS(1048576, MATCH($D$2 & " " & K$3, rawv3!$1:$1, 0), 4)), K$4, INDIRECT("rawv3!" & ADDRESS(1, MATCH($B$4 & " " & $B10, rawv3!$1:$1, 0), 4) & ":" & ADDRESS(1048576, MATCH($B$4 & " " & $B10, rawv3!$1:$1, 0), 4)), $C10 )} -> 1145 | L10: {=COUNTIFS( rawv3!$F:$F, "<>Ongoing", INDIRECT("rawv3!" & ADDRESS(1, MATCH($D$2 & " " & K$3, rawv3!$1:$1, 0), 4) & ":" & ADDRESS(1048576, MATCH($D$2 & " " & K$3, rawv3!$1:$1, 0), 4)), L$4, INDIRECT("rawv3!" & ADDRESS(1, MATCH($B$4 & " " & $B10, rawv3!$1:$1, 0), 4) & ":" & ADDRESS(1048576, MATCH($B$4 & " " & $B10, rawv3!$1:$1, 0), 4)), $C10 )} -> 1218 | N10: {=COUNTIFS( rawv3!$F:$F, "<>Ongoing", INDIRECT("rawv3!" & ADDRESS(1, MATCH($D$2 & " " & N$3, rawv3!$1:$1, 0), 4) & ":" & ADDRESS(1048576, MATCH($D$2 & " " & N$3, rawv3!$1:$1, 0), 4)), N$4, INDIRECT("rawv3!" & ADDRESS(1, MATCH($B$4 & " " & $B10, rawv3!$1:$1, 0), 4) & ":" & ADDRESS(1048576, MATCH($B$4 & " " & $B10, rawv3!$1:$1, 0), 4)), $C10 )} -> 1408 | O10: {=COUNTIFS( rawv3!$F:$F, "<>Ongoing", INDIRECT("rawv3!" & ADDRESS(1, MATCH($D$2 & " " & N$3, rawv3!$1:$1, 0), 4) & ":" & ADDRESS(1048576, MATCH($D$2 & " " & N$3, rawv3!$1:$1, 0), 4)), O$4, INDIRECT("rawv3!" & ADDRESS(1, MATCH($B$4 & " " & $B10, rawv3!$1:$1, 0), 4) & ":" & ADDRESS(1048576, MATCH($B$4 & " " & $B10, rawv3!$1:$1, 0), 4)), $C10 )} -> 956 | Q10: {=COUNTIFS( rawv3!$F:$F, "<>Ongoing", INDIRECT("rawv3!" & ADDRESS(1, MATCH($D$2 & " " & Q$3, rawv3!$1:$1, 0), 4) & ":" & ADDRESS(1048576, MATCH($D$2 & " " & Q$3, rawv3!$1:$1, 0), 4)), Q$4, INDIRECT("rawv3!" & ADDRESS(1, MATCH($B$4 & " " & $B10, rawv3!$1:$1, 0), 4) & ":" & ADDRESS(1048576, MATCH($B$4 & " " & $B10, rawv3!$1:$1, 0), 4)), $C10 )} -> 1719 | R10: {=COUNTIFS( rawv3!$F:$F, "<>Ongoing", INDIRECT("rawv3!" & ADDRESS(1, MATCH($D$2 & " " & Q$3, rawv3!$1:$1, 0), 4) & ":" & ADDRESS(1048576, MATCH($D$2 & " " & Q$3, rawv3!$1:$1, 0), 4)), R$4, INDIRECT("rawv3!" & ADDRESS(1, MATCH($B$4 & " " & $B10, rawv3!$1:$1, 0), 4) & ":" & ADDRESS(1048576, MATCH($B$4 & " " & $B10, rawv3!$1:$1, 0), 4)), $C10 )} -> 643 | T10: {=COUNTIFS( rawv3!$F:$F, "<>Ongoing", INDIRECT("rawv3!" & ADDRESS(1, MATCH($D$2 & " " & T$3, rawv3!$1:$1, 0), 4) & ":" & ADDRESS(1048576, MATCH($D$2 & " " & T$3, rawv3!$1:$1, 0), 4)), T$4, INDIRECT("rawv3!" & ADDRESS(1, MATCH($B$4 & " " & $B10, rawv3!$1:$1, 0), 4) & ":" & ADDRESS(1048576, MATCH($B$4 & " " & $B10, rawv3!$1:$1, 0), 4)), $C10 )} -> 1793 | U10: {=COUNTIFS( rawv3!$F:$F, "<>Ongoing", INDIRECT("rawv3!" & ADDRESS(1, MATCH($D$2 & " " & T$3, rawv3!$1:$1, 0), 4) & ":" & ADDRESS(1048576, MATCH($D$2 & " " & T$3, rawv3!$1:$1, 0), 4)), U$4, INDIRECT("rawv3!" & ADDRESS(1, MATCH($B$4 & " " & $B10, rawv3!$1:$1, 0), 4) & ":" & ADDRESS(1048576, MATCH($B$4 & " " & $B10, rawv3!$1:$1, 0), 4)), $C10 )} -> 570 | W10: {=COUNTIFS( rawv3!$F:$F, "<>Ongoing", INDIRECT("rawv3!" & ADDRESS(1, MATCH($D$2 & " " & W$3, rawv3!$1:$1, 0), 4) & ":" & ADDRESS(1048576, MATCH($D$2 & " " & W$3, rawv3!$1:$1, 0), 4)), W$4, INDIRECT("rawv3!" & ADDRESS(1, MATCH($B$4 & " " & $B10, rawv3!$1:$1, 0), 4) & ":" & ADDRESS(1048576, MATCH($B$4 & " " & $B10, rawv3!$1:$1, 0), 4)), $C10 )} -> 1045 | X10: {=COUNTIFS( rawv3!$F:$F, "<>Ongoing", INDIRECT("rawv3!" & ADDRESS(1, MATCH($D$2 & " " & W$3, rawv3!$1:$1, 0), 4) & ":" & ADDRESS(1048576, MATCH($D$2 & " " & W$3, rawv3!$1:$1, 0), 4)), X$4, INDIRECT("rawv3!" & ADDRESS(1, MATCH($B$4 & " " & $B10, rawv3!$1:$1, 0), 4) & ":" & ADDRESS(1048576, MATCH($B$4 & " " & $B10, rawv3!$1:$1, 0), 4)), $C10 )} -> 1319 | Z10: {=COUNTIFS( rawv3!$F:$F, "<>Ongoing", INDIRECT("rawv3!" & ADDRESS(1, MATCH($B$4 & " " & $B10, rawv3!$1:$1, 0), 4) & ":" & ADDRESS(1048576, MATCH($B$4 & " " & $B10, rawv3!$1:$1, 0), 4)), $C10)} -> 2364
D11: F90D % | E11: {=COUNTIFS( rawv3!$F:$F, "Success", INDIRECT("rawv3!" & ADDRESS(1, MATCH($D$2 & " " & E$3, rawv3!$1:$1, 0), 4) & ":" & ADDRESS(1048576, MATCH($D$2 & " " & E$3, rawv3!$1:$1, 0), 4)), E$4, INDIRECT("rawv3!" & ADDRESS(1, MATCH($B$4 & " " & $B10, rawv3!$1:$1, 0), 4) & ":" & ADDRESS(1048576, MATCH($B$4 & " " & $B10, rawv3!$1:$1, 0), 4)), $C10 )/E10} -> 0.77675585 | F11: {=COUNTIFS( rawv3!$F:$F, "Success", INDIRECT("rawv3!" & ADDRESS(1, MATCH($D$2 & " " & E$3, rawv3!$1:$1, 0), 4) & ":" & ADDRESS(1048576, MATCH($D$2 & " " & E$3, rawv3!$1:$1, 0), 4)), F$4, INDIRECT("rawv3!" & ADDRESS(1, MATCH($B$4 & " " & $B10, rawv3!$1:$1, 0), 4) & ":" & ADDRESS(1048576, MATCH($B$4 & " " & $B10, rawv3!$1:$1, 0), 4)), $C10 )/F10} -> 0.8022356 | H11: {=COUNTIFS( rawv3!$F:$F, "Success", INDIRECT("rawv3!" & ADDRESS(1, MATCH($D$2 & " " & H$3, rawv3!$1:$1, 0), 4) & ":" & ADDRESS(1048576, MATCH($D$2 & " " & H$3, rawv3!$1:$1, 0), 4)), H$4, INDIRECT("rawv3!" & ADDRESS(1, MATCH($B$4 & " " & $B10, rawv3!$1:$1, 0), 4) & ":" & ADDRESS(1048576, MATCH($B$4 & " " & $B10, rawv3!$1:$1, 0), 4)), $C10 )/H10} -> 0.79657534 | I11: {=COUNTIFS( rawv3!$F:$F, "Success", INDIRECT("rawv3!" & ADDRESS(1, MATCH($D$2 & " " & H$3, rawv3!$1:$1, 0), 4) & ":" & ADDRESS(1048576, MATCH($D$2 & " " & H$3, rawv3!$1:$1, 0), 4)), I$4, INDIRECT("rawv3!" & ADDRESS(1, MATCH($B$4 & " " & $B10, rawv3!$1:$1, 0), 4) & ":" & ADDRESS(1048576, MATCH($B$4 & " " & $B10, rawv3!$1:$1, 0), 4)), $C10 )/I10} -> 0.77876106 | K11: {=COUNTIFS( rawv3!$F:$F, "Success", INDIRECT("rawv3!" & ADDRESS(1, MATCH($D$2 & " " & K$3, rawv3!$1:$1, 0), 4) & ":" & ADDRESS(1048576, MATCH($D$2 & " " & K$3, rawv3!$1:$1, 0), 4)), K$4, INDIRECT("rawv3!" & ADDRESS(1, MATCH($B$4 & " " & $B10, rawv3!$1:$1, 0), 4) & ":" & ADDRESS(1048576, MATCH($B$4 & " " & $B10, rawv3!$1:$1, 0), 4)), $C10 )/K10} -> 0.78689956 | L11: {=COUNTIFS( rawv3!$F:$F, "Success", INDIRECT("rawv3!" & ADDRESS(1, MATCH($D$2 & " " & K$3, rawv3!$1:$1, 0), 4) & ":" & ADDRESS(1048576, MATCH($D$2 & " " & K$3, rawv3!$1:$1, 0), 4)), L$4, INDIRECT("rawv3!" & ADDRESS(1, MATCH($B$4 & " " & $B10, rawv3!$1:$1, 0), 4) & ":" & ADDRESS(1048576, MATCH($B$4 & " " & $B10, rawv3!$1:$1, 0), 4)), $C10 )/L10} -> 0.79310345 | N11: {=COUNTIFS( rawv3!$F:$F, "Success", INDIRECT("rawv3!" & ADDRESS(1, MATCH($D$2 & " " & N$3, rawv3!$1:$1, 0), 4) & ":" & ADDRESS(1048576, MATCH($D$2 & " " & N$3, rawv3!$1:$1, 0), 4)), N$4, INDIRECT("rawv3!" & ADDRESS(1, MATCH($B$4 & " " & $B10, rawv3!$1:$1, 0), 4) & ":" & ADDRESS(1048576, MATCH($B$4 & " " & $B10, rawv3!$1:$1, 0), 4)), $C10 )/N10} -> 0.79332386 | O11: {=COUNTIFS( rawv3!$F:$F, "Success", INDIRECT("rawv3!" & ADDRESS(1, MATCH($D$2 & " " & N$3, rawv3!$1:$1, 0), 4) & ":" & ADDRESS(1048576, MATCH($D$2 & " " & N$3, rawv3!$1:$1, 0), 4)), O$4, INDIRECT("rawv3!" & ADDRESS(1, MATCH($B$4 & " " & $B10, rawv3!$1:$1, 0), 4) & ":" & ADDRESS(1048576, MATCH($B$4 & " " & $B10, rawv3!$1:$1, 0), 4)), $C10 )/O10} -> 0.78451883 | Q11: {=COUNTIFS( rawv3!$F:$F, "Success", INDIRECT("rawv3!" & ADDRESS(1, MATCH($D$2 & " " & Q$3, rawv3!$1:$1, 0), 4) & ":" & ADDRESS(1048576, MATCH($D$2 & " " & Q$3, rawv3!$1:$1, 0), 4)), Q$4, INDIRECT("rawv3!" & ADDRESS(1, MATCH($B$4 & " " & $B10, rawv3!$1:$1, 0), 4) & ":" & ADDRESS(1048576, MATCH($B$4 & " " & $B10, rawv3!$1:$1, 0), 4)), $C10 )/Q10} -> 0.79348458 | R11: {=COUNTIFS( rawv3!$F:$F, "Success", INDIRECT("rawv3!" & ADDRESS(1, MATCH($D$2 & " " & Q$3, rawv3!$1:$1, 0), 4) & ":" & ADDRESS(1048576, MATCH($D$2 & " " & Q$3, rawv3!$1:$1, 0), 4)), R$4, INDIRECT("rawv3!" & ADDRESS(1, MATCH($B$4 & " " & $B10, rawv3!$1:$1, 0), 4) & ":" & ADDRESS(1048576, MATCH($B$4 & " " & $B10, rawv3!$1:$1, 0), 4)), $C10 )/R10} -> 0.7807154 | T11: {=COUNTIFS( rawv3!$F:$F, "Success", INDIRECT("rawv3!" & ADDRESS(1, MATCH($D$2 & " " & T$3, rawv3!$1:$1, 0), 4) & ":" & ADDRESS(1048576, MATCH($D$2 & " " & T$3, rawv3!$1:$1, 0), 4)), T$4, INDIRECT("rawv3!" & ADDRESS(1, MATCH($B$4 & " " & $B10, rawv3!$1:$1, 0), 4) & ":" & ADDRESS(1048576, MATCH($B$4 & " " & $B10, rawv3!$1:$1, 0), 4)), $C10 )/T10} -> 0.79085332 | U11: {=COUNTIFS( rawv3!$F:$F, "Success", INDIRECT("rawv3!" & ADDRESS(1, MATCH($D$2 & " " & T$3, rawv3!$1:$1, 0), 4) & ":" & ADDRESS(1048576, MATCH($D$2 & " " & T$3, rawv3!$1:$1, 0), 4)), U$4, INDIRECT("rawv3!" & ADDRESS(1, MATCH($B$4 & " " & $B10, rawv3!$1:$1, 0), 4) & ":" & ADDRESS(1048576, MATCH($B$4 & " " & $B10, rawv3!$1:$1, 0), 4)), $C10 )/U10} -> 0.78596491 | W11: {=COUNTIFS( rawv3!$F:$F, "Success", INDIRECT("rawv3!" & ADDRESS(1, MATCH($D$2 & " " & W$3, rawv3!$1:$1, 0), 4) & ":" & ADDRESS(1048576, MATCH($D$2 & " " & W$3, rawv3!$1:$1, 0), 4)), W$4, INDIRECT("rawv3!" & ADDRESS(1, MATCH($B$4 & " " & $B10, rawv3!$1:$1, 0), 4) & ":" & ADDRESS(1048576, MATCH($B$4 & " " & $B10, rawv3!$1:$1, 0), 4)), $C10 )/W10} -> 0.77990431 | X11: {=COUNTIFS( rawv3!$F:$F, "Success", INDIRECT("rawv3!" & ADDRESS(1, MATCH($D$2 & " " & W$3, rawv3!$1:$1, 0), 4) & ":" & ADDRESS(1048576, MATCH($D$2 & " " & W$3, rawv3!$1:$1, 0), 4)), X$4, INDIRECT("rawv3!" & ADDRESS(1, MATCH($B$4 & " " & $B10, rawv3!$1:$1, 0), 4) & ":" & ADDRESS(1048576, MATCH($B$4 & " " & $B10, rawv3!$1:$1, 0), 4)), $C10 )/X10} -> 0.79757392 | Z11: {=COUNTIFS( rawv3!$F:$F, "Success", INDIRECT("rawv3!" & ADDRESS(1, MATCH($B$4 & " " & $B10, rawv3!$1:$1, 0), 4) & ":" & ADDRESS(1048576, MATCH($B$4 & " " & $B10, rawv3!$1:$1, 0), 4)), $C10)/Z10} -> 0.78976311 | AA11: {=COUNTIFS( rawv3!$F:$F, "Success", INDIRECT("rawv3!" & ADDRESS(1, MATCH($B$4 & " " & $B10, rawv3!$1:$1, 0), 4) & ":" & ADDRESS(1048576, MATCH($B$4 & " " & $B10, rawv3!$1:$1, 0), 4)), $C10)} -> 1867
C12: Intuition | D12: # | E12: {=COUNTIFS( rawv3!$F:$F, "<>Ongoing", INDIRECT("rawv3!" & ADDRESS(1, MATCH($D$2 & " " & E$3, rawv3!$1:$1, 0), 4) & ":" & ADDRESS(1048576, MATCH($D$2 & " " & E$3, rawv3!$1:$1, 0), 4)), E$4, INDIRECT("rawv3!" & ADDRESS(1, MATCH($B$4 & " " & $B10, rawv3!$1:$1, 0), 4) & ":" & ADDRESS(1048576, MATCH($B$4 & " " & $B10, rawv3!$1:$1, 0), 4)), $C12 )} -> 87 | F12: {=COUNTIFS( rawv3!$F:$F, "<>Ongoing", INDIRECT("rawv3!" & ADDRESS(1, MATCH($D$2 & " " & E$3, rawv3!$1:$1, 0), 4) & ":" & ADDRESS(1048576, MATCH($D$2 & " " & E$3, rawv3!$1:$1, 0), 4)), F$4, INDIRECT("rawv3!" & ADDRESS(1, MATCH($B$4 & " " & $B10, rawv3!$1:$1, 0), 4) & ":" & ADDRESS(1048576, MATCH($B$4 & " " & $B10, rawv3!$1:$1, 0), 4)), $C12 )} -> 87 | H12: {=COUNTIFS( rawv3!$F:$F, "<>Ongoing", INDIRECT("rawv3!" & ADDRESS(1, MATCH($D$2 & " " & H$3, rawv3!$1:$1, 0), 4) & ":" & ADDRESS(1048576, MATCH($D$2 & " " & H$3, rawv3!$1:$1, 0), 4)), H$4, INDIRECT("rawv3!" & ADDRESS(1, MATCH($B$4 & " " & $B10, rawv3!$1:$1, 0), 4) & ":" & ADDRESS(1048576, MATCH($B$4 & " " & $B10, rawv3!$1:$1, 0), 4)), $C12 )} -> 84 | I12: {=COUNTIFS( rawv3!$F:$F, "<>Ongoing", INDIRECT("rawv3!" & ADDRESS(1, MATCH($D$2 & " " & H$3, rawv3!$1:$1, 0), 4) & ":" & ADDRESS(1048576, MATCH($D$2 & " " & H$3, rawv3!$1:$1, 0), 4)), I$4, INDIRECT("rawv3!" & ADDRESS(1, MATCH($B$4 & " " & $B10, rawv3!$1:$1, 0), 4) & ":" & ADDRESS(1048576, MATCH($B$4 & " " & $B10, rawv3!$1:$1, 0), 4)), $C12 )} -> 90 | K12: {=COUNTIFS( rawv3!$F:$F, "<>Ongoing", INDIRECT("rawv3!" & ADDRESS(1, MATCH($D$2 & " " & K$3, rawv3!$1:$1, 0), 4) & ":" & ADDRESS(1048576, MATCH($D$2 & " " & K$3, rawv3!$1:$1, 0), 4)), K$4, INDIRECT("rawv3!" & ADDRESS(1, MATCH($B$4 & " " & $B10, rawv3!$1:$1, 0), 4) & ":" & ADDRESS(1048576, MATCH($B$4 & " " & $B10, rawv3!$1:$1, 0), 4)), $C12 )} -> 77 | L12: {=COUNTIFS( rawv3!$F:$F, "<>Ongoing", INDIRECT("rawv3!" & ADDRESS(1, MATCH($D$2 & " " & K$3, rawv3!$1:$1, 0), 4) & ":" & ADDRESS(1048576, MATCH($D$2 & " " & K$3, rawv3!$1:$1, 0), 4)), L$4, INDIRECT("rawv3!" & ADDRESS(1, MATCH($B$4 & " " & $B10, rawv3!$1:$1, 0), 4) & ":" & ADDRESS(1048576, MATCH($B$4 & " " & $B10, rawv3!$1:$1, 0), 4)), $C12 )} -> 97 | N12: {=COUNTIFS( rawv3!$F:$F, "<>Ongoing", INDIRECT("rawv3!" & ADDRESS(1, MATCH($D$2 & " " & N$3, rawv3!$1:$1, 0), 4) & ":" & ADDRESS(1048576, MATCH($D$2 & " " & N$3, rawv3!$1:$1, 0), 4)), N$4, INDIRECT("rawv3!" & ADDRESS(1, MATCH($B$4 & " " & $B10, rawv3!$1:$1, 0), 4) & ":" & ADDRESS(1048576, MATCH($B$4 & " " & $B10, rawv3!$1:$1, 0), 4)), $C12 )} -> 113 | O12: {=COUNTIFS( rawv3!$F:$F, "<>Ongoing", INDIRECT("rawv3!" & ADDRESS(1, MATCH($D$2 & " " & N$3, rawv3!$1:$1, 0), 4) & ":" & ADDRESS(1048576, MATCH($D$2 & " " & N$3, rawv3!$1:$1, 0), 4)), O$4, INDIRECT("rawv3!" & ADDRESS(1, MATCH($B$4 & " " & $B10, rawv3!$1:$1, 0), 4) & ":" & ADDRESS(1048576, MATCH($B$4 & " " & $B10, rawv3!$1:$1, 0), 4)), $C12 )} -> 61 | Q12: {=COUNTIFS( rawv3!$F:$F, "<>Ongoing", INDIRECT("rawv3!" & ADDRESS(1, MATCH($D$2 & " " & Q$3, rawv3!$1:$1, 0), 4) & ":" & ADDRESS(1048576, MATCH($D$2 & " " & Q$3, rawv3!$1:$1, 0), 4)), Q$4, INDIRECT("rawv3!" & ADDRESS(1, MATCH($B$4 & " " & $B10, rawv3!$1:$1, 0), 4) & ":" & ADDRESS(1048576, MATCH($B$4 & " " & $B10, rawv3!$1:$1, 0), 4)), $C12 )} -> 121 | R12: {=COUNTIFS( rawv3!$F:$F, "<>Ongoing", INDIRECT("rawv3!" & ADDRESS(1, MATCH($D$2 & " " & Q$3, rawv3!$1:$1, 0), 4) & ":" & ADDRESS(1048576, MATCH($D$2 & " " & Q$3, rawv3!$1:$1, 0), 4)), R$4, INDIRECT("rawv3!" & ADDRESS(1, MATCH($B$4 & " " & $B10, rawv3!$1:$1, 0), 4) & ":" & ADDRESS(1048576, MATCH($B$4 & " " & $B10, rawv3!$1:$1, 0), 4)), $C12 )} -> 53 | T12: {=COUNTIFS( rawv3!$F:$F, "<>Ongoing", INDIRECT("rawv3!" & ADDRESS(1, MATCH($D$2 & " " & T$3, rawv3!$1:$1, 0), 4) & ":" & ADDRESS(1048576, MATCH($D$2 & " " & T$3, rawv3!$1:$1, 0), 4)), T$4, INDIRECT("rawv3!" & ADDRESS(1, MATCH($B$4 & " " & $B10, rawv3!$1:$1, 0), 4) & ":" & ADDRESS(1048576, MATCH($B$4 & " " & $B10, rawv3!$1:$1, 0), 4)), $C12 )} -> 128 | U12: {=COUNTIFS( rawv3!$F:$F, "<>Ongoing", INDIRECT("rawv3!" & ADDRESS(1, MATCH($D$2 & " " & T$3, rawv3!$1:$1, 0), 4) & ":" & ADDRESS(1048576, MATCH($D$2 & " " & T$3, rawv3!$1:$1, 0), 4)), U$4, INDIRECT("rawv3!" & ADDRESS(1, MATCH($B$4 & " " & $B10, rawv3!$1:$1, 0), 4) & ":" & ADDRESS(1048576, MATCH($B$4 & " " & $B10, rawv3!$1:$1, 0), 4)), $C12 )} -> 46 | W12: {=COUNTIFS( rawv3!$F:$F, "<>Ongoing", INDIRECT("rawv3!" & ADDRESS(1, MATCH($D$2 & " " & W$3, rawv3!$1:$1, 0), 4) & ":" & ADDRESS(1048576, MATCH($D$2 & " " & W$3, rawv3!$1:$1, 0), 4)), W$4, INDIRECT("rawv3!" & ADDRESS(1, MATCH($B$4 & " " & $B10, rawv3!$1:$1, 0), 4) & ":" & ADDRESS(1048576, MATCH($B$4 & " " & $B10, rawv3!$1:$1, 0), 4)), $C12 )} -> 82 | X12: {=COUNTIFS( rawv3!$F:$F, "<>Ongoing", INDIRECT("rawv3!" & ADDRESS(1, MATCH($D$2 & " " & W$3, rawv3!$1:$1, 0), 4) & ":" & ADDRESS(1048576, MATCH($D$2 & " " & W$3, rawv3!$1:$1, 0), 4)), X$4, INDIRECT("rawv3!" & ADDRESS(1, MATCH($B$4 & " " & $B10, rawv3!$1:$1, 0), 4) & ":" & ADDRESS(1048576, MATCH($B$4 & " " & $B10, rawv3!$1:$1, 0), 4)), $C12 )} -> 92 | Z12: {=COUNTIFS( rawv3!$F:$F, "<>Ongoing", INDIRECT("rawv3!" & ADDRESS(1, MATCH($B$4 & " " & $B10, rawv3!$1:$1, 0), 4) & ":" & ADDRESS(1048576, MATCH($B$4 & " " & $B10, rawv3!$1:$1, 0), 4)), $C12)} -> 174
D13: F90D % | E13: {=COUNTIFS( rawv3!$F:$F, "Success", INDIRECT("rawv3!" & ADDRESS(1, MATCH($D$2 & " " & E$3, rawv3!$1:$1, 0), 4) & ":" & ADDRESS(1048576, MATCH($D$2 & " " & E$3, rawv3!$1:$1, 0), 4)), E$4, INDIRECT("rawv3!" & ADDRESS(1, MATCH($B$4 & " " & $B10, rawv3!$1:$1, 0), 4) & ":" & ADDRESS(1048576, MATCH($B$4 & " " & $B10, rawv3!$1:$1, 0), 4)), $C12 )/E12} -> 0.81609195 | F13: {=COUNTIFS( rawv3!$F:$F, "Success", INDIRECT("rawv3!" & ADDRESS(1, MATCH($D$2 & " " & E$3, rawv3!$1:$1, 0), 4) & ":" & ADDRESS(1048576, MATCH($D$2 & " " & E$3, rawv3!$1:$1, 0), 4)), F$4, INDIRECT("rawv3!" & ADDRESS(1, MATCH($B$4 & " " & $B10, rawv3!$1:$1, 0), 4) & ":" & ADDRESS(1048576, MATCH($B$4 & " " & $B10, rawv3!$1:$1, 0), 4)), $C12 )/F12} -> 0.74712644 | H13: {=COUNTIFS( rawv3!$F:$F, "Success", INDIRECT("rawv3!" & ADDRESS(1, MATCH($D$2 & " " & H$3, rawv3!$1:$1, 0), 4) & ":" & ADDRESS(1048576, MATCH($D$2 & " " & H$3, rawv3!$1:$1, 0), 4)), H$4, INDIRECT("rawv3!" & ADDRESS(1, MATCH($B$4 & " " & $B10, rawv3!$1:$1, 0), 4) & ":" & ADDRESS(1048576, MATCH($B$4 & " " & $B10, rawv3!$1:$1, 0), 4)), $C12 )/H12} -> 0.78571429 | I13: {=COUNTIFS( rawv3!$F:$F, "Success", INDIRECT("rawv3!" & ADDRESS(1, MATCH($D$2 & " " & H$3, rawv3!$1:$1, 0), 4) & ":" & ADDRESS(1048576, MATCH($D$2 & " " & H$3, rawv3!$1:$1, 0), 4)), I$4, INDIRECT("rawv3!" & ADDRESS(1, MATCH($B$4 & " " & $B10, rawv3!$1:$1, 0), 4) & ":" & ADDRESS(1048576, MATCH($B$4 & " " & $B10, rawv3!$1:$1, 0), 4)), $C12 )/I12} -> 0.77777778 | K13: {=COUNTIFS( rawv3!$F:$F, "Success", INDIRECT("rawv3!" & ADDRESS(1, MATCH($D$2 & " " & K$3, rawv3!$1:$1, 0), 4) & ":" & ADDRESS(1048576, MATCH($D$2 & " " & K$3, rawv3!$1:$1, 0), 4)), K$4, INDIRECT("rawv3!" & ADDRESS(1, MATCH($B$4 & " " & $B10, rawv3!$1:$1, 0), 4) & ":" & ADDRESS(1048576, MATCH($B$4 & " " & $B10, rawv3!$1:$1, 0), 4)), $C12 )/K12} -> 0.79220779 | L13: {=COUNTIFS( rawv3!$F:$F, "Success", INDIRECT("rawv3!" & ADDRESS(1, MATCH($D$2 & " " & K$3, rawv3!$1:$1, 0), 4) & ":" & ADDRESS(1048576, MATCH($D$2 & " " & K$3, rawv3!$1:$1, 0), 4)), L$4, INDIRECT("rawv3!" & ADDRESS(1, MATCH($B$4 & " " & $B10, rawv3!$1:$1, 0), 4) & ":" & ADDRESS(1048576, MATCH($B$4 & " " & $B10, rawv3!$1:$1, 0), 4)), $C12 )/L12} -> 0.77319588 | N13: {=COUNTIFS( rawv3!$F:$F, "Success", INDIRECT("rawv3!" & ADDRESS(1, MATCH($D$2 & " " & N$3, rawv3!$1:$1, 0), 4) & ":" & ADDRESS(1048576, MATCH($D$2 & " " & N$3, rawv3!$1:$1, 0), 4)), N$4, INDIRECT("rawv3!" & ADDRESS(1, MATCH($B$4 & " " & $B10, rawv3!$1:$1, 0), 4) & ":" & ADDRESS(1048576, MATCH($B$4 & " " & $B10, rawv3!$1:$1, 0), 4)), $C12 )/N12} -> 0.79646018 | O13: {=COUNTIFS( rawv3!$F:$F, "Success", INDIRECT("rawv3!" & ADDRESS(1, MATCH($D$2 & " " & N$3, rawv3!$1:$1, 0), 4) & ":" & ADDRESS(1048576, MATCH($D$2 & " " & N$3, rawv3!$1:$1, 0), 4)), O$4, INDIRECT("rawv3!" & ADDRESS(1, MATCH($B$4 & " " & $B10, rawv3!$1:$1, 0), 4) & ":" & ADDRESS(1048576, MATCH($B$4 & " " & $B10, rawv3!$1:$1, 0), 4)), $C12 )/O12} -> 0.75409836 | Q13: {=COUNTIFS( rawv3!$F:$F, "Success", INDIRECT("rawv3!" & ADDRESS(1, MATCH($D$2 & " " & Q$3, rawv3!$1:$1, 0), 4) & ":" & ADDRESS(1048576, MATCH($D$2 & " " & Q$3, rawv3!$1:$1, 0), 4)), Q$4, INDIRECT("rawv3!" & ADDRESS(1, MATCH($B$4 & " " & $B10, rawv3!$1:$1, 0), 4) & ":" & ADDRESS(1048576, MATCH($B$4 & " " & $B10, rawv3!$1:$1, 0), 4)), $C12 )/Q12} -> 0.81818182 | R13: {=COUNTIFS( rawv3!$F:$F, "Success", INDIRECT("rawv3!" & ADDRESS(1, MATCH($D$2 & " " & Q$3, rawv3!$1:$1, 0), 4) & ":" & ADDRESS(1048576, MATCH($D$2 & " " & Q$3, rawv3!$1:$1, 0), 4)), R$4, INDIRECT("rawv3!" & ADDRESS(1, MATCH($B$4 & " " & $B10, rawv3!$1:$1, 0), 4) & ":" & ADDRESS(1048576, MATCH($B$4 & " " & $B10, rawv3!$1:$1, 0), 4)), $C12 )/R12} -> 0.69811321 | T13: {=COUNTIFS( rawv3!$F:$F, "Success", INDIRECT("rawv3!" & ADDRESS(1, MATCH($D$2 & " " & T$3, rawv3!$1:$1, 0), 4) & ":" & ADDRESS(1048576, MATCH($D$2 & " " & T$3, rawv3!$1:$1, 0), 4)), T$4, INDIRECT("rawv3!" & ADDRESS(1, MATCH($B$4 & " " & $B10, rawv3!$1:$1, 0), 4) & ":" & ADDRESS(1048576, MATCH($B$4 & " " & $B10, rawv3!$1:$1, 0), 4)), $C12 )/T12} -> 0.796875 | U13: {=COUNTIFS( rawv3!$F:$F, "Success", INDIRECT("rawv3!" & ADDRESS(1, MATCH($D$2 & " " & T$3, rawv3!$1:$1, 0), 4) & ":" & ADDRESS(1048576, MATCH($D$2 & " " & T$3, rawv3!$1:$1, 0), 4)), U$4, INDIRECT("rawv3!" & ADDRESS(1, MATCH($B$4 & " " & $B10, rawv3!$1:$1, 0), 4) & ":" & ADDRESS(1048576, MATCH($B$4 & " " & $B10, rawv3!$1:$1, 0), 4)), $C12 )/U12} -> 0.73913043 | W13: {=COUNTIFS( rawv3!$F:$F, "Success", INDIRECT("rawv3!" & ADDRESS(1, MATCH($D$2 & " " & W$3, rawv3!$1:$1, 0), 4) & ":" & ADDRESS(1048576, MATCH($D$2 & " " & W$3, rawv3!$1:$1, 0), 4)), W$4, INDIRECT("rawv3!" & ADDRESS(1, MATCH($B$4 & " " & $B10, rawv3!$1:$1, 0), 4) & ":" & ADDRESS(1048576, MATCH($B$4 & " " & $B10, rawv3!$1:$1, 0), 4)), $C12 )/W12} -> 0.76829268 | X13: {=COUNTIFS( rawv3!$F:$F, "Success", INDIRECT("rawv3!" & ADDRESS(1, MATCH($D$2 & " " & W$3, rawv3!$1:$1, 0), 4) & ":" & ADDRESS(1048576, MATCH($D$2 & " " & W$3, rawv3!$1:$1, 0), 4)), X$4, INDIRECT("rawv3!" & ADDRESS(1, MATCH($B$4 & " " & $B10, rawv3!$1:$1, 0), 4) & ":" & ADDRESS(1048576, MATCH($B$4 & " " & $B10, rawv3!$1:$1, 0), 4)), $C12 )/X12} -> 0.79347826 | Z13: {=COUNTIFS( rawv3!$F:$F, "Success", INDIRECT("rawv3!" & ADDRESS(1, MATCH($B$4 & " " & $B10, rawv3!$1:$1, 0), 4) & ":" & ADDRESS(1048576, MATCH($B$4 & " " & $B10, rawv3!$1:$1, 0), 4)), $C12)/Z12} -> 0.7816092 | AA13: {=COUNTIFS( rawv3!$F:$F, "Success", INDIRECT("rawv3!" & ADDRESS(1, MATCH($B$4 & " " & $B10, rawv3!$1:$1, 0), 4) & ":" & ADDRESS(1048576, MATCH($B$4 & " " & $B10, rawv3!$1:$1, 0), 4)), $C12)} -> 136
B15: Drive | C15: Small tangible goals | D15: # | E15: {=COUNTIFS( rawv3!$F:$F, "<>Ongoing", INDIRECT("rawv3!" & ADDRESS(1, MATCH($D$2 & " " & E$3, rawv3!$1:$1, 0), 4) & ":" & ADDRESS(1048576, MATCH($D$2 & " " & E$3, rawv3!$1:$1, 0), 4)), E$4, INDIRECT("rawv3!" & ADDRESS(1, MATCH($B$4 & " " & $B15, rawv3!$1:$1, 0), 4) & ":" & ADDRESS(1048576, MATCH($B$4 & " " & $B15, rawv3!$1:$1, 0), 4)), $C15 )} -> 689 | F15: {=COUNTIFS( rawv3!$F:$F, "<>Ongoing", INDIRECT("rawv3!" & ADDRESS(1, MATCH($D$2 & " " & E$3, rawv3!$1:$1, 0), 4) & ":" & ADDRESS(1048576, MATCH($D$2 & " " & E$3, rawv3!$1:$1, 0), 4)), F$4, INDIRECT("rawv3!" & ADDRESS(1, MATCH($B$4 & " " & $B15, rawv3!$1:$1, 0), 4) & ":" & ADDRESS(1048576, MATCH($B$4 & " " & $B15, rawv3!$1:$1, 0), 4)), $C15 )} -> 708 | H15: {=COUNTIFS( rawv3!$F:$F, "<>Ongoing", INDIRECT("rawv3!" & ADDRESS(1, MATCH($D$2 & " " & H$3, rawv3!$1:$1, 0), 4) & ":" & ADDRESS(1048576, MATCH($D$2 & " " & H$3, rawv3!$1:$1, 0), 4)), H$4, INDIRECT("rawv3!" & ADDRESS(1, MATCH($B$4 & " " & $B15, rawv3!$1:$1, 0), 4) & ":" & ADDRESS(1048576, MATCH($B$4 & " " & $B15, rawv3!$1:$1, 0), 4)), $C15 )} -> 844 | I15: {=COUNTIFS( rawv3!$F:$F, "<>Ongoing", INDIRECT("rawv3!" & ADDRESS(1, MATCH($D$2 & " " & H$3, rawv3!$1:$1, 0), 4) & ":" & ADDRESS(1048576, MATCH($D$2 & " " & H$3, rawv3!$1:$1, 0), 4)), I$4, INDIRECT("rawv3!" & ADDRESS(1, MATCH($B$4 & " " & $B15, rawv3!$1:$1, 0), 4) & ":" & ADDRESS(1048576, MATCH($B$4 & " " & $B15, rawv3!$1:$1, 0), 4)), $C15 )} -> 557 | K15: {=COUNTIFS( rawv3!$F:$F, "<>Ongoing", INDIRECT("rawv3!" & ADDRESS(1, MATCH($D$2 & " " & K$3, rawv3!$1:$1, 0), 4) & ":" & ADDRESS(1048576, MATCH($D$2 & " " & K$3, rawv3!$1:$1, 0), 4)), K$4, INDIRECT("rawv3!" & ADDRESS(1, MATCH($B$4 & " " & $B15, rawv3!$1:$1, 0), 4) & ":" & ADDRESS(1048576, MATCH($B$4 & " " & $B15, rawv3!$1:$1, 0), 4)), $C15 )} -> 790 | L15: {=COUNTIFS( rawv3!$F:$F, "<>Ongoing", INDIRECT("rawv3!" & ADDRESS(1, MATCH($D$2 & " " & K$3, rawv3!$1:$1, 0), 4) & ":" & ADDRESS(1048576, MATCH($D$2 & " " & K$3, rawv3!$1:$1, 0), 4)), L$4, INDIRECT("rawv3!" & ADDRESS(1, MATCH($B$4 & " " & $B15, rawv3!$1:$1, 0), 4) & ":" & ADDRESS(1048576, MATCH($B$4 & " " & $B15, rawv3!$1:$1, 0), 4)), $C15 )} -> 611 | N15: {=COUNTIFS( rawv3!$F:$F, "<>Ongoing", INDIRECT("rawv3!" & ADDRESS(1, MATCH($D$2 & " " & N$3, rawv3!$1:$1, 0), 4) & ":" & ADDRESS(1048576, MATCH($D$2 & " " & N$3, rawv3!$1:$1, 0), 4)), N$4, INDIRECT("rawv3!" & ADDRESS(1, MATCH($B$4 & " " & $B15, rawv3!$1:$1, 0), 4) & ":" & ADDRESS(1048576, MATCH($B$4 & " " & $B15, rawv3!$1:$1, 0), 4)), $C15 )} -> 833 | O15: {=COUNTIFS( rawv3!$F:$F, "<>Ongoing", INDIRECT("rawv3!" & ADDRESS(1, MATCH($D$2 & " " & N$3, rawv3!$1:$1, 0), 4) & ":" & ADDRESS(1048576, MATCH($D$2 & " " & N$3, rawv3!$1:$1, 0), 4)), O$4, INDIRECT("rawv3!" & ADDRESS(1, MATCH($B$4 & " " & $B15, rawv3!$1:$1, 0), 4) & ":" & ADDRESS(1048576, MATCH($B$4 & " " & $B15, rawv3!$1:$1, 0), 4)), $C15 )} -> 568 | Q15: {=COUNTIFS( rawv3!$F:$F, "<>Ongoing", INDIRECT("rawv3!" & ADDRESS(1, MATCH($D$2 & " " & Q$3, rawv3!$1:$1, 0), 4) & ":" & ADDRESS(1048576, MATCH($D$2 & " " & Q$3, rawv3!$1:$1, 0), 4)), Q$4, INDIRECT("rawv3!" & ADDRESS(1, MATCH($B$4 & " " & $B15, rawv3!$1:$1, 0), 4) & ":" & ADDRESS(1048576, MATCH($B$4 & " " & $B15, rawv3!$1:$1, 0), 4)), $C15 )} -> 1006 | R15: {=COUNTIFS( rawv3!$F:$F, "<>Ongoing", INDIRECT("rawv3!" & ADDRESS(1, MATCH($D$2 & " " & Q$3, rawv3!$1:$1, 0), 4) & ":" & ADDRESS(1048576, MATCH($D$2 & " " & Q$3, rawv3!$1:$1, 0), 4)), R$4, INDIRECT("rawv3!" & ADDRESS(1, MATCH($B$4 & " " & $B15, rawv3!$1:$1, 0), 4) & ":" & ADDRESS(1048576, MATCH($B$4 & " " & $B15, rawv3!$1:$1, 0), 4)), $C15 )} -> 394 | T15: {=COUNTIFS( rawv3!$F:$F, "<>Ongoing", INDIRECT("rawv3!" & ADDRESS(1, MATCH($D$2 & " " & T$3, rawv3!$1:$1, 0), 4) & ":" & ADDRESS(1048576, MATCH($D$2 & " " & T$3, rawv3!$1:$1, 0), 4)), T$4, INDIRECT("rawv3!" & ADDRESS(1, MATCH($B$4 & " " & $B15, rawv3!$1:$1, 0), 4) & ":" & ADDRESS(1048576, MATCH($B$4 & " " & $B15, rawv3!$1:$1, 0), 4)), $C15 )} -> 1055 | U15: {=COUNTIFS( rawv3!$F:$F, "<>Ongoing", INDIRECT("rawv3!" & ADDRESS(1, MATCH($D$2 & " " & T$3, rawv3!$1:$1, 0), 4) & ":" & ADDRESS(1048576, MATCH($D$2 & " " & T$3, rawv3!$1:$1, 0), 4)), U$4, INDIRECT("rawv3!" & ADDRESS(1, MATCH($B$4 & " " & $B15, rawv3!$1:$1, 0), 4) & ":" & ADDRESS(1048576, MATCH($B$4 & " " & $B15, rawv3!$1:$1, 0), 4)), $C15 )} -> 345 | W15: {=COUNTIFS( rawv3!$F:$F, "<>Ongoing", INDIRECT("rawv3!" & ADDRESS(1, MATCH($D$2 & " " & W$3, rawv3!$1:$1, 0), 4) & ":" & ADDRESS(1048576, MATCH($D$2 & " " & W$3, rawv3!$1:$1, 0), 4)), W$4, INDIRECT("rawv3!" & ADDRESS(1, MATCH($B$4 & " " & $B15, rawv3!$1:$1, 0), 4) & ":" & ADDRESS(1048576, MATCH($B$4 & " " & $B15, rawv3!$1:$1, 0), 4)), $C15 )} -> 632 | X15: {=COUNTIFS( rawv3!$F:$F, "<>Ongoing", INDIRECT("rawv3!" & ADDRESS(1, MATCH($D$2 & " " & W$3, rawv3!$1:$1, 0), 4) & ":" & ADDRESS(1048576, MATCH($D$2 & " " & W$3, rawv3!$1:$1, 0), 4)), X$4, INDIRECT("rawv3!" & ADDRESS(1, MATCH($B$4 & " " & $B15, rawv3!$1:$1, 0), 4) & ":" & ADDRESS(1048576, MATCH($B$4 & " " & $B15, rawv3!$1:$1, 0), 4)), $C15 )} -> 769 | Z15: {=COUNTIFS( rawv3!$F:$F, "<>Ongoing", INDIRECT("rawv3!" & ADDRESS(1, MATCH($B$4 & " " & $B15, rawv3!$1:$1, 0), 4) & ":" & ADDRESS(1048576, MATCH($B$4 & " " & $B15, rawv3!$1:$1, 0), 4)), $C15)} -> 1401
D16: F90D % | E16: {=COUNTIFS( rawv3!$F:$F, "Success", INDIRECT("rawv3!" & ADDRESS(1, MATCH($D$2 & " " & E$3, rawv3!$1:$1, 0), 4) & ":" & ADDRESS(1048576, MATCH($D$2 & " " & E$3, rawv3!$1:$1, 0), 4)), E$4, INDIRECT("rawv3!" & ADDRESS(1, MATCH($B$4 & " " & $B15, rawv3!$1:$1, 0), 4) & ":" & ADDRESS(1048576, MATCH($B$4 & " " & $B15, rawv3!$1:$1, 0), 4)), $C15 )/E15} -> 0.76632801 | F16: {=COUNTIFS( rawv3!$F:$F, "Success", INDIRECT("rawv3!" & ADDRESS(1, MATCH($D$2 & " " & E$3, rawv3!$1:$1, 0), 4) & ":" & ADDRESS(1048576, MATCH($D$2 & " " & E$3, rawv3!$1:$1, 0), 4)), F$4, INDIRECT("rawv3!" & ADDRESS(1, MATCH($B$4 & " " & $B15, rawv3!$1:$1, 0), 4) & ":" & ADDRESS(1048576, MATCH($B$4 & " " & $B15, rawv3!$1:$1, 0), 4)), $C15 )/F15} -> 0.80932203 | H16: {=COUNTIFS( rawv3!$F:$F, "Success", INDIRECT("rawv3!" & ADDRESS(1, MATCH($D$2 & " " & H$3, rawv3!$1:$1, 0), 4) & ":" & ADDRESS(1048576, MATCH($D$2 & " " & H$3, rawv3!$1:$1, 0), 4)), H$4, INDIRECT("rawv3!" & ADDRESS(1, MATCH($B$4 & " " & $B15, rawv3!$1:$1, 0), 4) & ":" & ADDRESS(1048576, MATCH($B$4 & " " & $B15, rawv3!$1:$1, 0), 4)), $C15 )/H15} -> 0.79265403 | I16: {=COUNTIFS( rawv3!$F:$F, "Success", INDIRECT("rawv3!" & ADDRESS(1, MATCH($D$2 & " " & H$3, rawv3!$1:$1, 0), 4) & ":" & ADDRESS(1048576, MATCH($D$2 & " " & H$3, rawv3!$1:$1, 0), 4)), I$4, INDIRECT("rawv3!" & ADDRESS(1, MATCH($B$4 & " " & $B15, rawv3!$1:$1, 0), 4) & ":" & ADDRESS(1048576, MATCH($B$4 & " " & $B15, rawv3!$1:$1, 0), 4)), $C15 )/I15} -> 0.78276481 | K16: {=COUNTIFS( rawv3!$F:$F, "Success", INDIRECT("rawv3!" & ADDRESS(1, MATCH($D$2 & " " & K$3, rawv3!$1:$1, 0), 4) & ":" & ADDRESS(1048576, MATCH($D$2 & " " & K$3, rawv3!$1:$1, 0), 4)), K$4, INDIRECT("rawv3!" & ADDRESS(1, MATCH($B$4 & " " & $B15, rawv3!$1:$1, 0), 4) & ":" & ADDRESS(1048576, MATCH($B$4 & " " & $B15, rawv3!$1:$1, 0), 4)), $C15 )/K15} -> 0.79746835 | L16: {=COUNTIFS( rawv3!$F:$F, "Success", INDIRECT("rawv3!" & ADDRESS(1, MATCH($D$2 & " " & K$3, rawv3!$1:$1, 0), 4) & ":" & ADDRESS(1048576, MATCH($D$2 & " " & K$3, rawv3!$1:$1, 0), 4)), L$4, INDIRECT("rawv3!" & ADDRESS(1, MATCH($B$4 & " " & $B15, rawv3!$1:$1, 0), 4) & ":" & ADDRESS(1048576, MATCH($B$4 & " " & $B15, rawv3!$1:$1, 0), 4)), $C15 )/L15} -> 0.77741408 | N16: {=COUNTIFS( rawv3!$F:$F, "Success", INDIRECT("rawv3!" & ADDRESS(1, MATCH($D$2 & " " & N$3, rawv3!$1:$1, 0), 4) & ":" & ADDRESS(1048576, MATCH($D$2 & " " & N$3, rawv3!$1:$1, 0), 4)), N$4, INDIRECT("rawv3!" & ADDRESS(1, MATCH($B$4 & " " & $B15, rawv3!$1:$1, 0), 4) & ":" & ADDRESS(1048576, MATCH($B$4 & " " & $B15, rawv3!$1:$1, 0), 4)), $C15 )/N15} -> 0.80552221 | O16: {=COUNTIFS( rawv3!$F:$F, "Success", INDIRECT("rawv3!" & ADDRESS(1, MATCH($D$2 & " " & N$3, rawv3!$1:$1, 0), 4) & ":" & ADDRESS(1048576, MATCH($D$2 & " " & N$3, rawv3!$1:$1, 0), 4)), O$4, INDIRECT("rawv3!" & ADDRESS(1, MATCH($B$4 & " " & $B15, rawv3!$1:$1, 0), 4) & ":" & ADDRESS(1048576, MATCH($B$4 & " " & $B15, rawv3!$1:$1, 0), 4)), $C15 )/O15} -> 0.76408451 | Q16: {=COUNTIFS( rawv3!$F:$F, "Success", INDIRECT("rawv3!" & ADDRESS(1, MATCH($D$2 & " " & Q$3, rawv3!$1:$1, 0), 4) & ":" & ADDRESS(1048576, MATCH($D$2 & " " & Q$3, rawv3!$1:$1, 0), 4)), Q$4, INDIRECT("rawv3!" & ADDRESS(1, MATCH($B$4 & " " & $B15, rawv3!$1:$1, 0), 4) & ":" & ADDRESS(1048576, MATCH($B$4 & " " & $B15, rawv3!$1:$1, 0), 4)), $C15 )/Q15} -> 0.79522863 | R16: {=COUNTIFS( rawv3!$F:$F, "Success", INDIRECT("rawv3!" & ADDRESS(1, MATCH($D$2 & " " & Q$3, rawv3!$1:$1, 0), 4) & ":" & ADDRESS(1048576, MATCH($D$2 & " " & Q$3, rawv3!$1:$1, 0), 4)), R$4, INDIRECT("rawv3!" & ADDRESS(1, MATCH($B$4 & " " & $B15, rawv3!$1:$1, 0), 4) & ":" & ADDRESS(1048576, MATCH($B$4 & " " & $B15, rawv3!$1:$1, 0), 4)), $C15 )/R15} -> 0.7715736 | T16: {=COUNTIFS( rawv3!$F:$F, "Success", INDIRECT("rawv3!" & ADDRESS(1, MATCH($D$2 & " " & T$3, rawv3!$1:$1, 0), 4) & ":" & ADDRESS(1048576, MATCH($D$2 & " " & T$3, rawv3!$1:$1, 0), 4)), T$4, INDIRECT("rawv3!" & ADDRESS(1, MATCH($B$4 & " " & $B15, rawv3!$1:$1, 0), 4) & ":" & ADDRESS(1048576, MATCH($B$4 & " " & $B15, rawv3!$1:$1, 0), 4)), $C15 )/T15} -> 0.79810427 | U16: {=COUNTIFS( rawv3!$F:$F, "Success", INDIRECT("rawv3!" & ADDRESS(1, MATCH($D$2 & " " & T$3, rawv3!$1:$1, 0), 4) & ":" & ADDRESS(1048576, MATCH($D$2 & " " & T$3, rawv3!$1:$1, 0), 4)), U$4, INDIRECT("rawv3!" & ADDRESS(1, MATCH($B$4 & " " & $B15, rawv3!$1:$1, 0), 4) & ":" & ADDRESS(1048576, MATCH($B$4 & " " & $B15, rawv3!$1:$1, 0), 4)), $C15 )/U15} -> 0.75942029 | W16: {=COUNTIFS( rawv3!$F:$F, "Success", INDIRECT("rawv3!" & ADDRESS(1, MATCH($D$2 & " " & W$3, rawv3!$1:$1, 0), 4) & ":" & ADDRESS(1048576, MATCH($D$2 & " " & W$3, rawv3!$1:$1, 0), 4)), W$4, INDIRECT("rawv3!" & ADDRESS(1, MATCH($B$4 & " " & $B15, rawv3!$1:$1, 0), 4) & ":" & ADDRESS(1048576, MATCH($B$4 & " " & $B15, rawv3!$1:$1, 0), 4)), $C15 )/W15} -> 0.78006329 | X16: {=COUNTIFS( rawv3!$F:$F, "Success", INDIRECT("rawv3!" & ADDRESS(1, MATCH($D$2 & " " & W$3, rawv3!$1:$1, 0), 4) & ":" & ADDRESS(1048576, MATCH($D$2 & " " & W$3, rawv3!$1:$1, 0), 4)), X$4, INDIRECT("rawv3!" & ADDRESS(1, MATCH($B$4 & " " & $B15, rawv3!$1:$1, 0), 4) & ":" & ADDRESS(1048576, MATCH($B$4 & " " & $B15, rawv3!$1:$1, 0), 4)), $C15 )/X15} -> 0.79583875 | Z16: {=COUNTIFS( rawv3!$F:$F, "Success", INDIRECT("rawv3!" & ADDRESS(1, MATCH($B$4 & " " & $B15, rawv3!$1:$1, 0), 4) & ":" & ADDRESS(1048576, MATCH($B$4 & " " & $B15, rawv3!$1:$1, 0), 4)), $C15)/Z15} -> 0.78872234 | AA16: {=COUNTIFS( rawv3!$F:$F, "Success", INDIRECT("rawv3!" & ADDRESS(1, MATCH($B$4 & " " & $B15, rawv3!$1:$1, 0), 4) & ":" & ADDRESS(1048576, MATCH($B$4 & " " & $B15, rawv3!$1:$1, 0), 4)), $C15)} -> 1105
C17: Towards visionary ideas | D17: # | E17: {=COUNTIFS( rawv3!$F:$F, "<>Ongoing", INDIRECT("rawv3!" & ADDRESS(1, MATCH($D$2 & " " & E$3, rawv3!$1:$1, 0), 4) & ":" & ADDRESS(1048576, MATCH($D$2 & " " & E$3, rawv3!$1:$1, 0), 4)), E$4, INDIRECT("rawv3!" & ADDRESS(1, MATCH($B$4 & " " & $B15, rawv3!$1:$1, 0), 4) & ":" & ADDRESS(1048576, MATCH($B$4 & " " & $B15, rawv3!$1:$1, 0), 4)), $C17 )} -> 594 | F17: {=COUNTIFS( rawv3!$F:$F, "<>Ongoing", INDIRECT("rawv3!" & ADDRESS(1, MATCH($D$2 & " " & E$3, rawv3!$1:$1, 0), 4) & ":" & ADDRESS(1048576, MATCH($D$2 & " " & E$3, rawv3!$1:$1, 0), 4)), F$4, INDIRECT("rawv3!" & ADDRESS(1, MATCH($B$4 & " " & $B15, rawv3!$1:$1, 0), 4) & ":" & ADDRESS(1048576, MATCH($B$4 & " " & $B15, rawv3!$1:$1, 0), 4)), $C17 )} -> 542 | H17: {=COUNTIFS( rawv3!$F:$F, "<>Ongoing", INDIRECT("rawv3!" & ADDRESS(1, MATCH($D$2 & " " & H$3, rawv3!$1:$1, 0), 4) & ":" & ADDRESS(1048576, MATCH($D$2 & " " & H$3, rawv3!$1:$1, 0), 4)), H$4, INDIRECT("rawv3!" & ADDRESS(1, MATCH($B$4 & " " & $B15, rawv3!$1:$1, 0), 4) & ":" & ADDRESS(1048576, MATCH($B$4 & " " & $B15, rawv3!$1:$1, 0), 4)), $C17 )} -> 700 | I17: {=COUNTIFS( rawv3!$F:$F, "<>Ongoing", INDIRECT("rawv3!" & ADDRESS(1, MATCH($D$2 & " " & H$3, rawv3!$1:$1, 0), 4) & ":" & ADDRESS(1048576, MATCH($D$2 & " " & H$3, rawv3!$1:$1, 0), 4)), I$4, INDIRECT("rawv3!" & ADDRESS(1, MATCH($B$4 & " " & $B15, rawv3!$1:$1, 0), 4) & ":" & ADDRESS(1048576, MATCH($B$4 & " " & $B15, rawv3!$1:$1, 0), 4)), $C17 )} -> 437 | K17: {=COUNTIFS( rawv3!$F:$F, "<>Ongoing", INDIRECT("rawv3!" & ADDRESS(1, MATCH($D$2 & " " & K$3, rawv3!$1:$1, 0), 4) & ":" & ADDRESS(1048576, MATCH($D$2 & " " & K$3, rawv3!$1:$1, 0), 4)), K$4, INDIRECT("rawv3!" & ADDRESS(1, MATCH($B$4 & " " & $B15, rawv3!$1:$1, 0), 4) & ":" & ADDRESS(1048576, MATCH($B$4 & " " & $B15, rawv3!$1:$1, 0), 4)), $C17 )} -> 432 | L17: {=COUNTIFS( rawv3!$F:$F, "<>Ongoing", INDIRECT("rawv3!" & ADDRESS(1, MATCH($D$2 & " " & K$3, rawv3!$1:$1, 0), 4) & ":" & ADDRESS(1048576, MATCH($D$2 & " " & K$3, rawv3!$1:$1, 0), 4)), L$4, INDIRECT("rawv3!" & ADDRESS(1, MATCH($B$4 & " " & $B15, rawv3!$1:$1, 0), 4) & ":" & ADDRESS(1048576, MATCH($B$4 & " " & $B15, rawv3!$1:$1, 0), 4)), $C17 )} -> 704 | N17: {=COUNTIFS( rawv3!$F:$F, "<>Ongoing", INDIRECT("rawv3!" & ADDRESS(1, MATCH($D$2 & " " & N$3, rawv3!$1:$1, 0), 4) & ":" & ADDRESS(1048576, MATCH($D$2 & " " & N$3, rawv3!$1:$1, 0), 4)), N$4, INDIRECT("rawv3!" & ADDRESS(1, MATCH($B$4 & " " & $B15, rawv3!$1:$1, 0), 4) & ":" & ADDRESS(1048576, MATCH($B$4 & " " & $B15, rawv3!$1:$1, 0), 4)), $C17 )} -> 688 | O17: {=COUNTIFS( rawv3!$F:$F, "<>Ongoing", INDIRECT("rawv3!" & ADDRESS(1, MATCH($D$2 & " " & N$3, rawv3!$1:$1, 0), 4) & ":" & ADDRESS(1048576, MATCH($D$2 & " " & N$3, rawv3!$1:$1, 0), 4)), O$4, INDIRECT("rawv3!" & ADDRESS(1, MATCH($B$4 & " " & $B15, rawv3!$1:$1, 0), 4) & ":" & ADDRESS(1048576, MATCH($B$4 & " " & $B15, rawv3!$1:$1, 0), 4)), $C17 )} -> 449 | Q17: {=COUNTIFS( rawv3!$F:$F, "<>Ongoing", INDIRECT("rawv3!" & ADDRESS(1, MATCH($D$2 & " " & Q$3, rawv3!$1:$1, 0), 4) & ":" & ADDRESS(1048576, MATCH($D$2 & " " & Q$3, rawv3!$1:$1, 0), 4)), Q$4, INDIRECT("rawv3!" & ADDRESS(1, MATCH($B$4 & " " & $B15, rawv3!$1:$1, 0), 4) & ":" & ADDRESS(1048576, MATCH($B$4 & " " & $B15, rawv3!$1:$1, 0), 4)), $C17 )} -> 834 | R17: {=COUNTIFS( rawv3!$F:$F, "<>Ongoing", INDIRECT("rawv3!" & ADDRESS(1, MATCH($D$2 & " " & Q$3, rawv3!$1:$1, 0), 4) & ":" & ADDRESS(1048576, MATCH($D$2 & " " & Q$3, rawv3!$1:$1, 0), 4)), R$4, INDIRECT("rawv3!" & ADDRESS(1, MATCH($B$4 & " " & $B15, rawv3!$1:$1, 0), 4) & ":" & ADDRESS(1048576, MATCH($B$4 & " " & $B15, rawv3!$1:$1, 0), 4)), $C17 )} -> 302 | T17: {=COUNTIFS( rawv3!$F:$F, "<>Ongoing", INDIRECT("rawv3!" & ADDRESS(1, MATCH($D$2 & " " & T$3, rawv3!$1:$1, 0), 4) & ":" & ADDRESS(1048576, MATCH($D$2 & " " & T$3, rawv3!$1:$1, 0), 4)), T$4, INDIRECT("rawv3!" & ADDRESS(1, MATCH($B$4 & " " & $B15, rawv3!$1:$1, 0), 4) & ":" & ADDRESS(1048576, MATCH($B$4 & " " & $B15, rawv3!$1:$1, 0), 4)), $C17 )} -> 866 | U17: {=COUNTIFS( rawv3!$F:$F, "<>Ongoing", INDIRECT("rawv3!" & ADDRESS(1, MATCH($D$2 & " " & T$3, rawv3!$1:$1, 0), 4) & ":" & ADDRESS(1048576, MATCH($D$2 & " " & T$3, rawv3!$1:$1, 0), 4)), U$4, INDIRECT("rawv3!" & ADDRESS(1, MATCH($B$4 & " " & $B15, rawv3!$1:$1, 0), 4) & ":" & ADDRESS(1048576, MATCH($B$4 & " " & $B15, rawv3!$1:$1, 0), 4)), $C17 )} -> 271 | W17: {=COUNTIFS( rawv3!$F:$F, "<>Ongoing", INDIRECT("rawv3!" & ADDRESS(1, MATCH($D$2 & " " & W$3, rawv3!$1:$1, 0), 4) & ":" & ADDRESS(1048576, MATCH($D$2 & " " & W$3, rawv3!$1:$1, 0), 4)), W$4, INDIRECT("rawv3!" & ADDRESS(1, MATCH($B$4 & " " & $B15, rawv3!$1:$1, 0), 4) & ":" & ADDRESS(1048576, MATCH($B$4 & " " & $B15, rawv3!$1:$1, 0), 4)), $C17 )} -> 495 | X17: {=COUNTIFS( rawv3!$F:$F, "<>Ongoing", INDIRECT("rawv3!" & ADDRESS(1, MATCH($D$2 & " " & W$3, rawv3!$1:$1, 0), 4) & ":" & ADDRESS(1048576, MATCH($D$2 & " " & W$3, rawv3!$1:$1, 0), 4)), X$4, INDIRECT("rawv3!" & ADDRESS(1, MATCH($B$4 & " " & $B15, rawv3!$1:$1, 0), 4) & ":" & ADDRESS(1048576, MATCH($B$4 & " " & $B15, rawv3!$1:$1, 0), 4)), $C17 )} -> 642 | Z17: {=COUNTIFS( rawv3!$F:$F, "<>Ongoing", INDIRECT("rawv3!" & ADDRESS(1, MATCH($B$4 & " " & $B15, rawv3!$1:$1, 0), 4) & ":" & ADDRESS(1048576, MATCH($B$4 & " " & $B15, rawv3!$1:$1, 0), 4)), $C17)} -> 1137
D18: F90D % | E18: {=COUNTIFS( rawv3!$F:$F, "Success", INDIRECT("rawv3!" & ADDRESS(1, MATCH($D$2 & " " & E$3, rawv3!$1:$1, 0), 4) & ":" & ADDRESS(1048576, MATCH($D$2 & " " & E$3, rawv3!$1:$1, 0), 4)), E$4, INDIRECT("rawv3!" & ADDRESS(1, MATCH($B$4 & " " & $B15, rawv3!$1:$1, 0), 4) & ":" & ADDRESS(1048576, MATCH($B$4 & " " & $B15, rawv3!$1:$1, 0), 4)), $C17 )/E17} -> 0.79461279 | F18: {=COUNTIFS( rawv3!$F:$F, "Success", INDIRECT("rawv3!" & ADDRESS(1, MATCH($D$2 & " " & E$3, rawv3!$1:$1, 0), 4) & ":" & ADDRESS(1048576, MATCH($D$2 & " " & E$3, rawv3!$1:$1, 0), 4)), F$4, INDIRECT("rawv3!" & ADDRESS(1, MATCH($B$4 & " " & $B15, rawv3!$1:$1, 0), 4) & ":" & ADDRESS(1048576, MATCH($B$4 & " " & $B15, rawv3!$1:$1, 0), 4)), $C17 )/F17} -> 0.78413284 | H18: {=COUNTIFS( rawv3!$F:$F, "Success", INDIRECT("rawv3!" & ADDRESS(1, MATCH($D$2 & " " & H$3, rawv3!$1:$1, 0), 4) & ":" & ADDRESS(1048576, MATCH($D$2 & " " & H$3, rawv3!$1:$1, 0), 4)), H$4, INDIRECT("rawv3!" & ADDRESS(1, MATCH($B$4 & " " & $B15, rawv3!$1:$1, 0), 4) & ":" & ADDRESS(1048576, MATCH($B$4 & " " & $B15, rawv3!$1:$1, 0), 4)), $C17 )/H17} -> 0.8 | I18: {=COUNTIFS( rawv3!$F:$F, "Success", INDIRECT("rawv3!" & ADDRESS(1, MATCH($D$2 & " " & H$3, rawv3!$1:$1, 0), 4) & ":" & ADDRESS(1048576, MATCH($D$2 & " " & H$3, rawv3!$1:$1, 0), 4)), I$4, INDIRECT("rawv3!" & ADDRESS(1, MATCH($B$4 & " " & $B15, rawv3!$1:$1, 0), 4) & ":" & ADDRESS(1048576, MATCH($B$4 & " " & $B15, rawv3!$1:$1, 0), 4)), $C17 )/I17} -> 0.77345538 | K18: {=COUNTIFS( rawv3!$F:$F, "Success", INDIRECT("rawv3!" & ADDRESS(1, MATCH($D$2 & " " & K$3, rawv3!$1:$1, 0), 4) & ":" & ADDRESS(1048576, MATCH($D$2 & " " & K$3, rawv3!$1:$1, 0), 4)), K$4, INDIRECT("rawv3!" & ADDRESS(1, MATCH($B$4 & " " & $B15, rawv3!$1:$1, 0), 4) & ":" & ADDRESS(1048576, MATCH($B$4 & " " & $B15, rawv3!$1:$1, 0), 4)), $C17 )/K17} -> 0.76851852 | L18: {=COUNTIFS( rawv3!$F:$F, "Success", INDIRECT("rawv3!" & ADDRESS(1, MATCH($D$2 & " " & K$3, rawv3!$1:$1, 0), 4) & ":" & ADDRESS(1048576, MATCH($D$2 & " " & K$3, rawv3!$1:$1, 0), 4)), L$4, INDIRECT("rawv3!" & ADDRESS(1, MATCH($B$4 & " " & $B15, rawv3!$1:$1, 0), 4) & ":" & ADDRESS(1048576, MATCH($B$4 & " " & $B15, rawv3!$1:$1, 0), 4)), $C17 )/L17} -> 0.80397727 | N18: {=COUNTIFS( rawv3!$F:$F, "Success", INDIRECT("rawv3!" & ADDRESS(1, MATCH($D$2 & " " & N$3, rawv3!$1:$1, 0), 4) & ":" & ADDRESS(1048576, MATCH($D$2 & " " & N$3, rawv3!$1:$1, 0), 4)), N$4, INDIRECT("rawv3!" & ADDRESS(1, MATCH($B$4 & " " & $B15, rawv3!$1:$1, 0), 4) & ":" & ADDRESS(1048576, MATCH($B$4 & " " & $B15, rawv3!$1:$1, 0), 4)), $C17 )/N17} -> 0.77906977 | O18: {=COUNTIFS( rawv3!$F:$F, "Success", INDIRECT("rawv3!" & ADDRESS(1, MATCH($D$2 & " " & N$3, rawv3!$1:$1, 0), 4) & ":" & ADDRESS(1048576, MATCH($D$2 & " " & N$3, rawv3!$1:$1, 0), 4)), O$4, INDIRECT("rawv3!" & ADDRESS(1, MATCH($B$4 & " " & $B15, rawv3!$1:$1, 0), 4) & ":" & ADDRESS(1048576, MATCH($B$4 & " " & $B15, rawv3!$1:$1, 0), 4)), $C17 )/O17} -> 0.80623608 | Q18: {=COUNTIFS( rawv3!$F:$F, "Success", INDIRECT("rawv3!" & ADDRESS(1, MATCH($D$2 & " " & Q$3, rawv3!$1:$1, 0), 4) & ":" & ADDRESS(1048576, MATCH($D$2 & " " & Q$3, rawv3!$1:$1, 0), 4)), Q$4, INDIRECT("rawv3!" & ADDRESS(1, MATCH($B$4 & " " & $B15, rawv3!$1:$1, 0), 4) & ":" & ADDRESS(1048576, MATCH($B$4 & " " & $B15, rawv3!$1:$1, 0), 4)), $C17 )/Q17} -> 0.79496403 | R18: {=COUNTIFS( rawv3!$F:$F, "Success", INDIRECT("rawv3!" & ADDRESS(1, MATCH($D$2 & " " & Q$3, rawv3!$1:$1, 0), 4) & ":" & ADDRESS(1048576, MATCH($D$2 & " " & Q$3, rawv3!$1:$1, 0), 4)), R$4, INDIRECT("rawv3!" & ADDRESS(1, MATCH($B$4 & " " & $B15, rawv3!$1:$1, 0), 4) & ":" & ADDRESS(1048576, MATCH($B$4 & " " & $B15, rawv3!$1:$1, 0), 4)), $C17 )/R17} -> 0.7781457 | T18: {=COUNTIFS( rawv3!$F:$F, "Success", INDIRECT("rawv3!" & ADDRESS(1, MATCH($D$2 & " " & T$3, rawv3!$1:$1, 0), 4) & ":" & ADDRESS(1048576, MATCH($D$2 & " " & T$3, rawv3!$1:$1, 0), 4)), T$4, INDIRECT("rawv3!" & ADDRESS(1, MATCH($B$4 & " " & $B15, rawv3!$1:$1, 0), 4) & ":" & ADDRESS(1048576, MATCH($B$4 & " " & $B15, rawv3!$1:$1, 0), 4)), $C17 )/T17} -> 0.78290993 | U18: {=COUNTIFS( rawv3!$F:$F, "Success", INDIRECT("rawv3!" & ADDRESS(1, MATCH($D$2 & " " & T$3, rawv3!$1:$1, 0), 4) & ":" & ADDRESS(1048576, MATCH($D$2 & " " & T$3, rawv3!$1:$1, 0), 4)), U$4, INDIRECT("rawv3!" & ADDRESS(1, MATCH($B$4 & " " & $B15, rawv3!$1:$1, 0), 4) & ":" & ADDRESS(1048576, MATCH($B$4 & " " & $B15, rawv3!$1:$1, 0), 4)), $C17 )/U17} -> 0.81180812 | W18: {=COUNTIFS( rawv3!$F:$F, "Success", INDIRECT("rawv3!" & ADDRESS(1, MATCH($D$2 & " " & W$3, rawv3!$1:$1, 0), 4) & ":" & ADDRESS(1048576, MATCH($D$2 & " " & W$3, rawv3!$1:$1, 0), 4)), W$4, INDIRECT("rawv3!" & ADDRESS(1, MATCH($B$4 & " " & $B15, rawv3!$1:$1, 0), 4) & ":" & ADDRESS(1048576, MATCH($B$4 & " " & $B15, rawv3!$1:$1, 0), 4)), $C17 )/W17} -> 0.77777778 | X18: {=COUNTIFS( rawv3!$F:$F, "Success", INDIRECT("rawv3!" & ADDRESS(1, MATCH($D$2 & " " & W$3, rawv3!$1:$1, 0), 4) & ":" & ADDRESS(1048576, MATCH($D$2 & " " & W$3, rawv3!$1:$1, 0), 4)), X$4, INDIRECT("rawv3!" & ADDRESS(1, MATCH($B$4 & " " & $B15, rawv3!$1:$1, 0), 4) & ":" & ADDRESS(1048576, MATCH($B$4 & " " & $B15, rawv3!$1:$1, 0), 4)), $C17 )/X17} -> 0.79906542 | Z18: {=COUNTIFS( rawv3!$F:$F, "Success", INDIRECT("rawv3!" & ADDRESS(1, MATCH($B$4 & " " & $B15, rawv3!$1:$1, 0), 4) & ":" & ADDRESS(1048576, MATCH($B$4 & " " & $B15, rawv3!$1:$1, 0), 4)), $C17)/Z17} -> 0.78979771 | AA18: {=COUNTIFS( rawv3!$F:$F, "Success", INDIRECT("rawv3!" & ADDRESS(1, MATCH($B$4 & " " & $B15, rawv3!$1:$1, 0), 4) & ":" & ADDRESS(1048576, MATCH($B$4 & " " & $B15, rawv3!$1:$1, 0), 4)), $C17)} -> 898
B20: Emotion | C20: Investment | D20: # | E20: {=COUNTIFS( rawv3!$F:$F, "<>Ongoing", INDIRECT("rawv3!" & ADDRESS(1, MATCH($D$2 & " " & E$3, rawv3!$1:$1, 0), 4) & ":" & ADDRESS(1048576, MATCH($D$2 & " " & E$3, rawv3!$1:$1, 0), 4)), E$4, INDIRECT("rawv3!" & ADDRESS(1, MATCH($B$4 & " " & $B20, rawv3!$1:$1, 0), 4) & ":" & ADDRESS(1048576, MATCH($B$4 & " " & $B20, rawv3!$1:$1, 0), 4)), $C20 )} -> 508 | F20: {=COUNTIFS( rawv3!$F:$F, "<>Ongoing", INDIRECT("rawv3!" & ADDRESS(1, MATCH($D$2 & " " & E$3, rawv3!$1:$1, 0), 4) & ":" & ADDRESS(1048576, MATCH($D$2 & " " & E$3, rawv3!$1:$1, 0), 4)), F$4, INDIRECT("rawv3!" & ADDRESS(1, MATCH($B$4 & " " & $B20, rawv3!$1:$1, 0), 4) & ":" & ADDRESS(1048576, MATCH($B$4 & " " & $B20, rawv3!$1:$1, 0), 4)), $C20 )} -> 451 | H20: {=COUNTIFS( rawv3!$F:$F, "<>Ongoing", INDIRECT("rawv3!" & ADDRESS(1, MATCH($D$2 & " " & H$3, rawv3!$1:$1, 0), 4) & ":" & ADDRESS(1048576, MATCH($D$2 & " " & H$3, rawv3!$1:$1, 0), 4)), H$4, INDIRECT("rawv3!" & ADDRESS(1, MATCH($B$4 & " " & $B20, rawv3!$1:$1, 0), 4) & ":" & ADDRESS(1048576, MATCH($B$4 & " " & $B20, rawv3!$1:$1, 0), 4)), $C20 )} -> 565 | I20: {=COUNTIFS( rawv3!$F:$F, "<>Ongoing", INDIRECT("rawv3!" & ADDRESS(1, MATCH($D$2 & " " & H$3, rawv3!$1:$1, 0), 4) & ":" & ADDRESS(1048576, MATCH($D$2 & " " & H$3, rawv3!$1:$1, 0), 4)), I$4, INDIRECT("rawv3!" & ADDRESS(1, MATCH($B$4 & " " & $B20, rawv3!$1:$1, 0), 4) & ":" & ADDRESS(1048576, MATCH($B$4 & " " & $B20, rawv3!$1:$1, 0), 4)), $C20 )} -> 396 | K20: {=COUNTIFS( rawv3!$F:$F, "<>Ongoing", INDIRECT("rawv3!" & ADDRESS(1, MATCH($D$2 & " " & K$3, rawv3!$1:$1, 0), 4) & ":" & ADDRESS(1048576, MATCH($D$2 & " " & K$3, rawv3!$1:$1, 0), 4)), K$4, INDIRECT("rawv3!" & ADDRESS(1, MATCH($B$4 & " " & $B20, rawv3!$1:$1, 0), 4) & ":" & ADDRESS(1048576, MATCH($B$4 & " " & $B20, rawv3!$1:$1, 0), 4)), $C20 )} -> 470 | L20: {=COUNTIFS( rawv3!$F:$F, "<>Ongoing", INDIRECT("rawv3!" & ADDRESS(1, MATCH($D$2 & " " & K$3, rawv3!$1:$1, 0), 4) & ":" & ADDRESS(1048576, MATCH($D$2 & " " & K$3, rawv3!$1:$1, 0), 4)), L$4, INDIRECT("rawv3!" & ADDRESS(1, MATCH($B$4 & " " & $B20, rawv3!$1:$1, 0), 4) & ":" & ADDRESS(1048576, MATCH($B$4 & " " & $B20, rawv3!$1:$1, 0), 4)), $C20 )} -> 491 | N20: {=COUNTIFS( rawv3!$F:$F, "<>Ongoing", INDIRECT("rawv3!" & ADDRESS(1, MATCH($D$2 & " " & N$3, rawv3!$1:$1, 0), 4) & ":" & ADDRESS(1048576, MATCH($D$2 & " " & N$3, rawv3!$1:$1, 0), 4)), N$4, INDIRECT("rawv3!" & ADDRESS(1, MATCH($B$4 & " " & $B20, rawv3!$1:$1, 0), 4) & ":" & ADDRESS(1048576, MATCH($B$4 & " " & $B20, rawv3!$1:$1, 0), 4)), $C20 )} -> 665 | O20: {=COUNTIFS( rawv3!$F:$F, "<>Ongoing", INDIRECT("rawv3!" & ADDRESS(1, MATCH($D$2 & " " & N$3, rawv3!$1:$1, 0), 4) & ":" & ADDRESS(1048576, MATCH($D$2 & " " & N$3, rawv3!$1:$1, 0), 4)), O$4, INDIRECT("rawv3!" & ADDRESS(1, MATCH($B$4 & " " & $B20, rawv3!$1:$1, 0), 4) & ":" & ADDRESS(1048576, MATCH($B$4 & " " & $B20, rawv3!$1:$1, 0), 4)), $C20 )} -> 296 | Q20: {=COUNTIFS( rawv3!$F:$F, "<>Ongoing", INDIRECT("rawv3!" & ADDRESS(1, MATCH($D$2 & " " & Q$3, rawv3!$1:$1, 0), 4) & ":" & ADDRESS(1048576, MATCH($D$2 & " " & Q$3, rawv3!$1:$1, 0), 4)), Q$4, INDIRECT("rawv3!" & ADDRESS(1, MATCH($B$4 & " " & $B20, rawv3!$1:$1, 0), 4) & ":" & ADDRESS(1048576, MATCH($B$4 & " " & $B20, rawv3!$1:$1, 0), 4)), $C20 )} -> 702 | R20: {=COUNTIFS( rawv3!$F:$F, "<>Ongoing", INDIRECT("rawv3!" & ADDRESS(1, MATCH($D$2 & " " & Q$3, rawv3!$1:$1, 0), 4) & ":" & ADDRESS(1048576, MATCH($D$2 & " " & Q$3, rawv3!$1:$1, 0), 4)), R$4, INDIRECT("rawv3!" & ADDRESS(1, MATCH($B$4 & " " & $B20, rawv3!$1:$1, 0), 4) & ":" & ADDRESS(1048576, MATCH($B$4 & " " & $B20, rawv3!$1:$1, 0), 4)), $C20 )} -> 258 | T20: {=COUNTIFS( rawv3!$F:$F, "<>Ongoing", INDIRECT("rawv3!" & ADDRESS(1, MATCH($D$2 & " " & T$3, rawv3!$1:$1, 0), 4) & ":" & ADDRESS(1048576, MATCH($D$2 & " " & T$3, rawv3!$1:$1, 0), 4)), T$4, INDIRECT("rawv3!" & ADDRESS(1, MATCH($B$4 & " " & $B20, rawv3!$1:$1, 0), 4) & ":" & ADDRESS(1048576, MATCH($B$4 & " " & $B20, rawv3!$1:$1, 0), 4)), $C20 )} -> 729 | U20: {=COUNTIFS( rawv3!$F:$F, "<>Ongoing", INDIRECT("rawv3!" & ADDRESS(1, MATCH($D$2 & " " & T$3, rawv3!$1:$1, 0), 4) & ":" & ADDRESS(1048576, MATCH($D$2 & " " & T$3, rawv3!$1:$1, 0), 4)), U$4, INDIRECT("rawv3!" & ADDRESS(1, MATCH($B$4 & " " & $B20, rawv3!$1:$1, 0), 4) & ":" & ADDRESS(1048576, MATCH($B$4 & " " & $B20, rawv3!$1:$1, 0), 4)), $C20 )} -> 232 | W20: {=COUNTIFS( rawv3!$F:$F, "<>Ongoing", INDIRECT("rawv3!" & ADDRESS(1, MATCH($D$2 & " " & W$3, rawv3!$1:$1, 0), 4) & ":" & ADDRESS(1048576, MATCH($D$2 & " " & W$3, rawv3!$1:$1, 0), 4)), W$4, INDIRECT("rawv3!" & ADDRESS(1, MATCH($B$4 & " " & $B20, rawv3!$1:$1, 0), 4) & ":" & ADDRESS(1048576, MATCH($B$4 & " " & $B20, rawv3!$1:$1, 0), 4)), $C20 )} -> 431 | X20: {=COUNTIFS( rawv3!$F:$F, "<>Ongoing", INDIRECT("rawv3!" & ADDRESS(1, MATCH($D$2 & " " & W$3, rawv3!$1:$1, 0), 4) & ":" & ADDRESS(1048576, MATCH($D$2 & " " & W$3, rawv3!$1:$1, 0), 4)), X$4, INDIRECT("rawv3!" & ADDRESS(1, MATCH($B$4 & " " & $B20, rawv3!$1:$1, 0), 4) & ":" & ADDRESS(1048576, MATCH($B$4 & " " & $B20, rawv3!$1:$1, 0), 4)), $C20 )} -> 530 | Z20: {=COUNTIFS( rawv3!$F:$F, "<>Ongoing", INDIRECT("rawv3!" & ADDRESS(1, MATCH($B$4 & " " & $B20, rawv3!$1:$1, 0), 4) & ":" & ADDRESS(1048576, MATCH($B$4 & " " & $B20, rawv3!$1:$1, 0), 4)), $C20)} -> 961
D21: F90D % | E21: {=COUNTIFS( rawv3!$F:$F, "Success", INDIRECT("rawv3!" & ADDRESS(1, MATCH($D$2 & " " & E$3, rawv3!$1:$1, 0), 4) & ":" & ADDRESS(1048576, MATCH($D$2 & " " & E$3, rawv3!$1:$1, 0), 4)), E$4, INDIRECT("rawv3!" & ADDRESS(1, MATCH($B$4 & " " & $B20, rawv3!$1:$1, 0), 4) & ":" & ADDRESS(1048576, MATCH($B$4 & " " & $B20, rawv3!$1:$1, 0), 4)), $C20 )/E20} -> 0.77362205 | F21: {=COUNTIFS( rawv3!$F:$F, "Success", INDIRECT("rawv3!" & ADDRESS(1, MATCH($D$2 & " " & E$3, rawv3!$1:$1, 0), 4) & ":" & ADDRESS(1048576, MATCH($D$2 & " " & E$3, rawv3!$1:$1, 0), 4)), F$4, INDIRECT("rawv3!" & ADDRESS(1, MATCH($B$4 & " " & $B20, rawv3!$1:$1, 0), 4) & ":" & ADDRESS(1048576, MATCH($B$4 & " " & $B20, rawv3!$1:$1, 0), 4)), $C20 )/F20} -> 0.7827051 | H21: {=COUNTIFS( rawv3!$F:$F, "Success", INDIRECT("rawv3!" & ADDRESS(1, MATCH($D$2 & " " & H$3, rawv3!$1:$1, 0), 4) & ":" & ADDRESS(1048576, MATCH($D$2 & " " & H$3, rawv3!$1:$1, 0), 4)), H$4, INDIRECT("rawv3!" & ADDRESS(1, MATCH($B$4 & " " & $B20, rawv3!$1:$1, 0), 4) & ":" & ADDRESS(1048576, MATCH($B$4 & " " & $B20, rawv3!$1:$1, 0), 4)), $C20 )/H20} -> 0.79115044 | I21: {=COUNTIFS( rawv3!$F:$F, "Success", INDIRECT("rawv3!" & ADDRESS(1, MATCH($D$2 & " " & H$3, rawv3!$1:$1, 0), 4) & ":" & ADDRESS(1048576, MATCH($D$2 & " " & H$3, rawv3!$1:$1, 0), 4)), I$4, INDIRECT("rawv3!" & ADDRESS(1, MATCH($B$4 & " " & $B20, rawv3!$1:$1, 0), 4) & ":" & ADDRESS(1048576, MATCH($B$4 & " " & $B20, rawv3!$1:$1, 0), 4)), $C20 )/I20} -> 0.76010101 | K21: {=COUNTIFS( rawv3!$F:$F, "Success", INDIRECT("rawv3!" & ADDRESS(1, MATCH($D$2 & " " & K$3, rawv3!$1:$1, 0), 4) & ":" & ADDRESS(1048576, MATCH($D$2 & " " & K$3, rawv3!$1:$1, 0), 4)), K$4, INDIRECT("rawv3!" & ADDRESS(1, MATCH($B$4 & " " & $B20, rawv3!$1:$1, 0), 4) & ":" & ADDRESS(1048576, MATCH($B$4 & " " & $B20, rawv3!$1:$1, 0), 4)), $C20 )/K20} -> 0.79574468 | L21: {=COUNTIFS( rawv3!$F:$F, "Success", INDIRECT("rawv3!" & ADDRESS(1, MATCH($D$2 & " " & K$3, rawv3!$1:$1, 0), 4) & ":" & ADDRESS(1048576, MATCH($D$2 & " " & K$3, rawv3!$1:$1, 0), 4)), L$4, INDIRECT("rawv3!" & ADDRESS(1, MATCH($B$4 & " " & $B20, rawv3!$1:$1, 0), 4) & ":" & ADDRESS(1048576, MATCH($B$4 & " " & $B20, rawv3!$1:$1, 0), 4)), $C20 )/L20} -> 0.76171079 | N21: {=COUNTIFS( rawv3!$F:$F, "Success", INDIRECT("rawv3!" & ADDRESS(1, MATCH($D$2 & " " & N$3, rawv3!$1:$1, 0), 4) & ":" & ADDRESS(1048576, MATCH($D$2 & " " & N$3, rawv3!$1:$1, 0), 4)), N$4, INDIRECT("rawv3!" & ADDRESS(1, MATCH($B$4 & " " & $B20, rawv3!$1:$1, 0), 4) & ":" & ADDRESS(1048576, MATCH($B$4 & " " & $B20, rawv3!$1:$1, 0), 4)), $C20 )/N20} -> 0.77744361 | O21: {=COUNTIFS( rawv3!$F:$F, "Success", INDIRECT("rawv3!" & ADDRESS(1, MATCH($D$2 & " " & N$3, rawv3!$1:$1, 0), 4) & ":" & ADDRESS(1048576, MATCH($D$2 & " " & N$3, rawv3!$1:$1, 0), 4)), O$4, INDIRECT("rawv3!" & ADDRESS(1, MATCH($B$4 & " " & $B20, rawv3!$1:$1, 0), 4) & ":" & ADDRESS(1048576, MATCH($B$4 & " " & $B20, rawv3!$1:$1, 0), 4)), $C20 )/O20} -> 0.78040541 | Q21: {=COUNTIFS( rawv3!$F:$F, "Success", INDIRECT("rawv3!" & ADDRESS(1, MATCH($D$2 & " " & Q$3, rawv3!$1:$1, 0), 4) & ":" & ADDRESS(1048576, MATCH($D$2 & " " & Q$3, rawv3!$1:$1, 0), 4)), Q$4, INDIRECT("rawv3!" & ADDRESS(1, MATCH($B$4 & " " & $B20, rawv3!$1:$1, 0), 4) & ":" & ADDRESS(1048576, MATCH($B$4 & " " & $B20, rawv3!$1:$1, 0), 4)), $C20 )/Q20} -> 0.78347578 | R21: {=COUNTIFS( rawv3!$F:$F, "Success", INDIRECT("rawv3!" & ADDRESS(1, MATCH($D$2 & " " & Q$3, rawv3!$1:$1, 0), 4) & ":" & ADDRESS(1048576, MATCH($D$2 & " " & Q$3, rawv3!$1:$1, 0), 4)), R$4, INDIRECT("rawv3!" & ADDRESS(1, MATCH($B$4 & " " & $B20, rawv3!$1:$1, 0), 4) & ":" & ADDRESS(1048576, MATCH($B$4 & " " & $B20, rawv3!$1:$1, 0), 4)), $C20 )/R20} -> 0.76356589 | T21: {=COUNTIFS( rawv3!$F:$F, "Success", INDIRECT("rawv3!" & ADDRESS(1, MATCH($D$2 & " " & T$3, rawv3!$1:$1, 0), 4) & ":" & ADDRESS(1048576, MATCH($D$2 & " " & T$3, rawv3!$1:$1, 0), 4)), T$4, INDIRECT("rawv3!" & ADDRESS(1, MATCH($B$4 & " " & $B20, rawv3!$1:$1, 0), 4) & ":" & ADDRESS(1048576, MATCH($B$4 & " " & $B20, rawv3!$1:$1, 0), 4)), $C20 )/T20} -> 0.77640604 | U21: {=COUNTIFS( rawv3!$F:$F, "Success", INDIRECT("rawv3!" & ADDRESS(1, MATCH($D$2 & " " & T$3, rawv3!$1:$1, 0), 4) & ":" & ADDRESS(1048576, MATCH($D$2 & " " & T$3, rawv3!$1:$1, 0), 4)), U$4, INDIRECT("rawv3!" & ADDRESS(1, MATCH($B$4 & " " & $B20, rawv3!$1:$1, 0), 4) & ":" & ADDRESS(1048576, MATCH($B$4 & " " & $B20, rawv3!$1:$1, 0), 4)), $C20 )/U20} -> 0.78448276 | W21: {=COUNTIFS( rawv3!$F:$F, "Success", INDIRECT("rawv3!" & ADDRESS(1, MATCH($D$2 & " " & W$3, rawv3!$1:$1, 0), 4) & ":" & ADDRESS(1048576, MATCH($D$2 & " " & W$3, rawv3!$1:$1, 0), 4)), W$4, INDIRECT("rawv3!" & ADDRESS(1, MATCH($B$4 & " " & $B20, rawv3!$1:$1, 0), 4) & ":" & ADDRESS(1048576, MATCH($B$4 & " " & $B20, rawv3!$1:$1, 0), 4)), $C20 )/W20} -> 0.76566125 | X21: {=COUNTIFS( rawv3!$F:$F, "Success", INDIRECT("rawv3!" & ADDRESS(1, MATCH($D$2 & " " & W$3, rawv3!$1:$1, 0), 4) & ":" & ADDRESS(1048576, MATCH($D$2 & " " & W$3, rawv3!$1:$1, 0), 4)), X$4, INDIRECT("rawv3!" & ADDRESS(1, MATCH($B$4 & " " & $B20, rawv3!$1:$1, 0), 4) & ":" & ADDRESS(1048576, MATCH($B$4 & " " & $B20, rawv3!$1:$1, 0), 4)), $C20 )/X20} -> 0.78867925 | Z21: {=COUNTIFS( rawv3!$F:$F, "Success", INDIRECT("rawv3!" & ADDRESS(1, MATCH($B$4 & " " & $B20, rawv3!$1:$1, 0), 4) & ":" & ADDRESS(1048576, MATCH($B$4 & " " & $B20, rawv3!$1:$1, 0), 4)), $C20)/Z20} -> 0.77835588 | AA21: {=COUNTIFS( rawv3!$F:$F, "Success", INDIRECT("rawv3!" & ADDRESS(1, MATCH($B$4 & " " & $B20, rawv3!$1:$1, 0), 4) & ":" & ADDRESS(1048576, MATCH($B$4 & " " & $B20, rawv3!$1:$1, 0), 4)), $C20)} -> 748
C22: Separation | D22: # | E22: {=COUNTIFS( rawv3!$F:$F, "<>Ongoing", INDIRECT("rawv3!" & ADDRESS(1, MATCH($D$2 & " " & E$3, rawv3!$1:$1, 0), 4) & ":" & ADDRESS(1048576, MATCH($D$2 & " " & E$3, rawv3!$1:$1, 0), 4)), E$4, INDIRECT("rawv3!" & ADDRESS(1, MATCH($B$4 & " " & $B20, rawv3!$1:$1, 0), 4) & ":" & ADDRESS(1048576, MATCH($B$4 & " " & $B20, rawv3!$1:$1, 0), 4)), $C22 )} -> 775 | F22: {=COUNTIFS( rawv3!$F:$F, "<>Ongoing", INDIRECT("rawv3!" & ADDRESS(1, MATCH($D$2 & " " & E$3, rawv3!$1:$1, 0), 4) & ":" & ADDRESS(1048576, MATCH($D$2 & " " & E$3, rawv3!$1:$1, 0), 4)), F$4, INDIRECT("rawv3!" & ADDRESS(1, MATCH($B$4 & " " & $B20, rawv3!$1:$1, 0), 4) & ":" & ADDRESS(1048576, MATCH($B$4 & " " & $B20, rawv3!$1:$1, 0), 4)), $C22 )} -> 799 | H22: {=COUNTIFS( rawv3!$F:$F, "<>Ongoing", INDIRECT("rawv3!" & ADDRESS(1, MATCH($D$2 & " " & H$3, rawv3!$1:$1, 0), 4) & ":" & ADDRESS(1048576, MATCH($D$2 & " " & H$3, rawv3!$1:$1, 0), 4)), H$4, INDIRECT("rawv3!" & ADDRESS(1, MATCH($B$4 & " " & $B20, rawv3!$1:$1, 0), 4) & ":" & ADDRESS(1048576, MATCH($B$4 & " " & $B20, rawv3!$1:$1, 0), 4)), $C22 )} -> 979 | I22: {=COUNTIFS( rawv3!$F:$F, "<>Ongoing", INDIRECT("rawv3!" & ADDRESS(1, MATCH($D$2 & " " & H$3, rawv3!$1:$1, 0), 4) & ":" & ADDRESS(1048576, MATCH($D$2 & " " & H$3, rawv3!$1:$1, 0), 4)), I$4, INDIRECT("rawv3!" & ADDRESS(1, MATCH($B$4 & " " & $B20, rawv3!$1:$1, 0), 4) & ":" & ADDRESS(1048576, MATCH($B$4 & " " & $B20, rawv3!$1:$1, 0), 4)), $C22 )} -> 598 | K22: {=COUNTIFS( rawv3!$F:$F, "<>Ongoing", INDIRECT("rawv3!" & ADDRESS(1, MATCH($D$2 & " " & K$3, rawv3!$1:$1, 0), 4) & ":" & ADDRESS(1048576, MATCH($D$2 & " " & K$3, rawv3!$1:$1, 0), 4)), K$4, INDIRECT("rawv3!" & ADDRESS(1, MATCH($B$4 & " " & $B20, rawv3!$1:$1, 0), 4) & ":" & ADDRESS(1048576, MATCH($B$4 & " " & $B20, rawv3!$1:$1, 0), 4)), $C22 )} -> 752 | L22: {=COUNTIFS( rawv3!$F:$F, "<>Ongoing", INDIRECT("rawv3!" & ADDRESS(1, MATCH($D$2 & " " & K$3, rawv3!$1:$1, 0), 4) & ":" & ADDRESS(1048576, MATCH($D$2 & " " & K$3, rawv3!$1:$1, 0), 4)), L$4, INDIRECT("rawv3!" & ADDRESS(1, MATCH($B$4 & " " & $B20, rawv3!$1:$1, 0), 4) & ":" & ADDRESS(1048576, MATCH($B$4 & " " & $B20, rawv3!$1:$1, 0), 4)), $C22 )} -> 824 | N22: {=COUNTIFS( rawv3!$F:$F, "<>Ongoing", INDIRECT("rawv3!" & ADDRESS(1, MATCH($D$2 & " " & N$3, rawv3!$1:$1, 0), 4) & ":" & ADDRESS(1048576, MATCH($D$2 & " " & N$3, rawv3!$1:$1, 0), 4)), N$4, INDIRECT("rawv3!" & ADDRESS(1, MATCH($B$4 & " " & $B20, rawv3!$1:$1, 0), 4) & ":" & ADDRESS(1048576, MATCH($B$4 & " " & $B20, rawv3!$1:$1, 0), 4)), $C22 )} -> 856 | O22: {=COUNTIFS( rawv3!$F:$F, "<>Ongoing", INDIRECT("rawv3!" & ADDRESS(1, MATCH($D$2 & " " & N$3, rawv3!$1:$1, 0), 4) & ":" & ADDRESS(1048576, MATCH($D$2 & " " & N$3, rawv3!$1:$1, 0), 4)), O$4, INDIRECT("rawv3!" & ADDRESS(1, MATCH($B$4 & " " & $B20, rawv3!$1:$1, 0), 4) & ":" & ADDRESS(1048576, MATCH($B$4 & " " & $B20, rawv3!$1:$1, 0), 4)), $C22 )} -> 721 | Q22: {=COUNTIFS( rawv3!$F:$F, "<>Ongoing", INDIRECT("rawv3!" & ADDRESS(1, MATCH($D$2 & " " & Q$3, rawv3!$1:$1, 0), 4) & ":" & ADDRESS(1048576, MATCH($D$2 & " " & Q$3, rawv3!$1:$1, 0), 4)), Q$4, INDIRECT("rawv3!" & ADDRESS(1, MATCH($B$4 & " " & $B20, rawv3!$1:$1, 0), 4) & ":" & ADDRESS(1048576, MATCH($B$4 & " " & $B20, rawv3!$1:$1, 0), 4)), $C22 )} -> 1138 | R22: {=COUNTIFS( rawv3!$F:$F, "<>Ongoing", INDIRECT("rawv3!" & ADDRESS(1, MATCH($D$2 & " " & Q$3, rawv3!$1:$1, 0), 4) & ":" & ADDRESS(1048576, MATCH($D$2 & " " & Q$3, rawv3!$1:$1, 0), 4)), R$4, INDIRECT("rawv3!" & ADDRESS(1, MATCH($B$4 & " " & $B20, rawv3!$1:$1, 0), 4) & ":" & ADDRESS(1048576, MATCH($B$4 & " " & $B20, rawv3!$1:$1, 0), 4)), $C22 )} -> 438 | T22: {=COUNTIFS( rawv3!$F:$F, "<>Ongoing", INDIRECT("rawv3!" & ADDRESS(1, MATCH($D$2 & " " & T$3, rawv3!$1:$1, 0), 4) & ":" & ADDRESS(1048576, MATCH($D$2 & " " & T$3, rawv3!$1:$1, 0), 4)), T$4, INDIRECT("rawv3!" & ADDRESS(1, MATCH($B$4 & " " & $B20, rawv3!$1:$1, 0), 4) & ":" & ADDRESS(1048576, MATCH($B$4 & " " & $B20, rawv3!$1:$1, 0), 4)), $C22 )} -> 1192 | U22: {=COUNTIFS( rawv3!$F:$F, "<>Ongoing", INDIRECT("rawv3!" & ADDRESS(1, MATCH($D$2 & " " & T$3, rawv3!$1:$1, 0), 4) & ":" & ADDRESS(1048576, MATCH($D$2 & " " & T$3, rawv3!$1:$1, 0), 4)), U$4, INDIRECT("rawv3!" & ADDRESS(1, MATCH($B$4 & " " & $B20, rawv3!$1:$1, 0), 4) & ":" & ADDRESS(1048576, MATCH($B$4 & " " & $B20, rawv3!$1:$1, 0), 4)), $C22 )} -> 384 | W22: {=COUNTIFS( rawv3!$F:$F, "<>Ongoing", INDIRECT("rawv3!" & ADDRESS(1, MATCH($D$2 & " " & W$3, rawv3!$1:$1, 0), 4) & ":" & ADDRESS(1048576, MATCH($D$2 & " " & W$3, rawv3!$1:$1, 0), 4)), W$4, INDIRECT("rawv3!" & ADDRESS(1, MATCH($B$4 & " " & $B20, rawv3!$1:$1, 0), 4) & ":" & ADDRESS(1048576, MATCH($B$4 & " " & $B20, rawv3!$1:$1, 0), 4)), $C22 )} -> 696 | X22: {=COUNTIFS( rawv3!$F:$F, "<>Ongoing", INDIRECT("rawv3!" & ADDRESS(1, MATCH($D$2 & " " & W$3, rawv3!$1:$1, 0), 4) & ":" & ADDRESS(1048576, MATCH($D$2 & " " & W$3, rawv3!$1:$1, 0), 4)), X$4, INDIRECT("rawv3!" & ADDRESS(1, MATCH($B$4 & " " & $B20, rawv3!$1:$1, 0), 4) & ":" & ADDRESS(1048576, MATCH($B$4 & " " & $B20, rawv3!$1:$1, 0), 4)), $C22 )} -> 881 | Z22: {=COUNTIFS( rawv3!$F:$F, "<>Ongoing", INDIRECT("rawv3!" & ADDRESS(1, MATCH($B$4 & " " & $B20, rawv3!$1:$1, 0), 4) & ":" & ADDRESS(1048576, MATCH($B$4 & " " & $B20, rawv3!$1:$1, 0), 4)), $C22)} -> 1577
D23: F90D % | E23: {=COUNTIFS( rawv3!$F:$F, "Success", INDIRECT("rawv3!" & ADDRESS(1, MATCH($D$2 & " " & E$3, rawv3!$1:$1, 0), 4) & ":" & ADDRESS(1048576, MATCH($D$2 & " " & E$3, rawv3!$1:$1, 0), 4)), E$4, INDIRECT("rawv3!" & ADDRESS(1, MATCH($B$4 & " " & $B20, rawv3!$1:$1, 0), 4) & ":" & ADDRESS(1048576, MATCH($B$4 & " " & $B20, rawv3!$1:$1, 0), 4)), $C22 )/E22} -> 0.78322581 | F23: {=COUNTIFS( rawv3!$F:$F, "Success", INDIRECT("rawv3!" & ADDRESS(1, MATCH($D$2 & " " & E$3, rawv3!$1:$1, 0), 4) & ":" & ADDRESS(1048576, MATCH($D$2 & " " & E$3, rawv3!$1:$1, 0), 4)), F$4, INDIRECT("rawv3!" & ADDRESS(1, MATCH($B$4 & " " & $B20, rawv3!$1:$1, 0), 4) & ":" & ADDRESS(1048576, MATCH($B$4 & " " & $B20, rawv3!$1:$1, 0), 4)), $C22 )/F22} -> 0.80725907 | H23: {=COUNTIFS( rawv3!$F:$F, "Success", INDIRECT("rawv3!" & ADDRESS(1, MATCH($D$2 & " " & H$3, rawv3!$1:$1, 0), 4) & ":" & ADDRESS(1048576, MATCH($D$2 & " " & H$3, rawv3!$1:$1, 0), 4)), H$4, INDIRECT("rawv3!" & ADDRESS(1, MATCH($B$4 & " " & $B20, rawv3!$1:$1, 0), 4) & ":" & ADDRESS(1048576, MATCH($B$4 & " " & $B20, rawv3!$1:$1, 0), 4)), $C22 )/H22} -> 0.79877426 | I23: {=COUNTIFS( rawv3!$F:$F, "Success", INDIRECT("rawv3!" & ADDRESS(1, MATCH($D$2 & " " & H$3, rawv3!$1:$1, 0), 4) & ":" & ADDRESS(1048576, MATCH($D$2 & " " & H$3, rawv3!$1:$1, 0), 4)), I$4, INDIRECT("rawv3!" & ADDRESS(1, MATCH($B$4 & " " & $B20, rawv3!$1:$1, 0), 4) & ":" & ADDRESS(1048576, MATCH($B$4 & " " & $B20, rawv3!$1:$1, 0), 4)), $C22 )/I22} -> 0.7909699 | K23: {=COUNTIFS( rawv3!$F:$F, "Success", INDIRECT("rawv3!" & ADDRESS(1, MATCH($D$2 & " " & K$3, rawv3!$1:$1, 0), 4) & ":" & ADDRESS(1048576, MATCH($D$2 & " " & K$3, rawv3!$1:$1, 0), 4)), K$4, INDIRECT("rawv3!" & ADDRESS(1, MATCH($B$4 & " " & $B20, rawv3!$1:$1, 0), 4) & ":" & ADDRESS(1048576, MATCH($B$4 & " " & $B20, rawv3!$1:$1, 0), 4)), $C22 )/K22} -> 0.78191489 | L23: {=COUNTIFS( rawv3!$F:$F, "Success", INDIRECT("rawv3!" & ADDRESS(1, MATCH($D$2 & " " & K$3, rawv3!$1:$1, 0), 4) & ":" & ADDRESS(1048576, MATCH($D$2 & " " & K$3, rawv3!$1:$1, 0), 4)), L$4, INDIRECT("rawv3!" & ADDRESS(1, MATCH($B$4 & " " & $B20, rawv3!$1:$1, 0), 4) & ":" & ADDRESS(1048576, MATCH($B$4 & " " & $B20, rawv3!$1:$1, 0), 4)), $C22 )/L22} -> 0.80946602 | N23: {=COUNTIFS( rawv3!$F:$F, "Success", INDIRECT("rawv3!" & ADDRESS(1, MATCH($D$2 & " " & N$3, rawv3!$1:$1, 0), 4) & ":" & ADDRESS(1048576, MATCH($D$2 & " " & N$3, rawv3!$1:$1, 0), 4)), N$4, INDIRECT("rawv3!" & ADDRESS(1, MATCH($B$4 & " " & $B20, rawv3!$1:$1, 0), 4) & ":" & ADDRESS(1048576, MATCH($B$4 & " " & $B20, rawv3!$1:$1, 0), 4)), $C22 )/N22} -> 0.80607477 | O23: {=COUNTIFS( rawv3!$F:$F, "Success", INDIRECT("rawv3!" & ADDRESS(1, MATCH($D$2 & " " & N$3, rawv3!$1:$1, 0), 4) & ":" & ADDRESS(1048576, MATCH($D$2 & " " & N$3, rawv3!$1:$1, 0), 4)), O$4, INDIRECT("rawv3!" & ADDRESS(1, MATCH($B$4 & " " & $B20, rawv3!$1:$1, 0), 4) & ":" & ADDRESS(1048576, MATCH($B$4 & " " & $B20, rawv3!$1:$1, 0), 4)), $C22 )/O22} -> 0.78363384 | Q23: {=COUNTIFS( rawv3!$F:$F, "Success", INDIRECT("rawv3!" & ADDRESS(1, MATCH($D$2 & " " & Q$3, rawv3!$1:$1, 0), 4) & ":" & ADDRESS(1048576, MATCH($D$2 & " " & Q$3, rawv3!$1:$1, 0), 4)), Q$4, INDIRECT("rawv3!" & ADDRESS(1, MATCH($B$4 & " " & $B20, rawv3!$1:$1, 0), 4) & ":" & ADDRESS(1048576, MATCH($B$4 & " " & $B20, rawv3!$1:$1, 0), 4)), $C22 )/Q22} -> 0.80228471 | R23: {=COUNTIFS( rawv3!$F:$F, "Success", INDIRECT("rawv3!" & ADDRESS(1, MATCH($D$2 & " " & Q$3, rawv3!$1:$1, 0), 4) & ":" & ADDRESS(1048576, MATCH($D$2 & " " & Q$3, rawv3!$1:$1, 0), 4)), R$4, INDIRECT("rawv3!" & ADDRESS(1, MATCH($B$4 & " " & $B20, rawv3!$1:$1, 0), 4) & ":" & ADDRESS(1048576, MATCH($B$4 & " " & $B20, rawv3!$1:$1, 0), 4)), $C22 )/R22} -> 0.78082192 | T23: {=COUNTIFS( rawv3!$F:$F, "Success", INDIRECT("rawv3!" & ADDRESS(1, MATCH($D$2 & " " & T$3, rawv3!$1:$1, 0), 4) & ":" & ADDRESS(1048576, MATCH($D$2 & " " & T$3, rawv3!$1:$1, 0), 4)), T$4, INDIRECT("rawv3!" & ADDRESS(1, MATCH($B$4 & " " & $B20, rawv3!$1:$1, 0), 4) & ":" & ADDRESS(1048576, MATCH($B$4 & " " & $B20, rawv3!$1:$1, 0), 4)), $C22 )/T22} -> 0.80033557 | U23: {=COUNTIFS( rawv3!$F:$F, "Success", INDIRECT("rawv3!" & ADDRESS(1, MATCH($D$2 & " " & T$3, rawv3!$1:$1, 0), 4) & ":" & ADDRESS(1048576, MATCH($D$2 & " " & T$3, rawv3!$1:$1, 0), 4)), U$4, INDIRECT("rawv3!" & ADDRESS(1, MATCH($B$4 & " " & $B20, rawv3!$1:$1, 0), 4) & ":" & ADDRESS(1048576, MATCH($B$4 & " " & $B20, rawv3!$1:$1, 0), 4)), $C22 )/U22} -> 0.78125 | W23: {=COUNTIFS( rawv3!$F:$F, "Success", INDIRECT("rawv3!" & ADDRESS(1, MATCH($D$2 & " " & W$3, rawv3!$1:$1, 0), 4) & ":" & ADDRESS(1048576, MATCH($D$2 & " " & W$3, rawv3!$1:$1, 0), 4)), W$4, INDIRECT("rawv3!" & ADDRESS(1, MATCH($B$4 & " " & $B20, rawv3!$1:$1, 0), 4) & ":" & ADDRESS(1048576, MATCH($B$4 & " " & $B20, rawv3!$1:$1, 0), 4)), $C22 )/W22} -> 0.78735632 | X23: {=COUNTIFS( rawv3!$F:$F, "Success", INDIRECT("rawv3!" & ADDRESS(1, MATCH($D$2 & " " & W$3, rawv3!$1:$1, 0), 4) & ":" & ADDRESS(1048576, MATCH($D$2 & " " & W$3, rawv3!$1:$1, 0), 4)), X$4, INDIRECT("rawv3!" & ADDRESS(1, MATCH($B$4 & " " & $B20, rawv3!$1:$1, 0), 4) & ":" & ADDRESS(1048576, MATCH($B$4 & " " & $B20, rawv3!$1:$1, 0), 4)), $C22 )/X22} -> 0.80249716 | Z23: {=COUNTIFS( rawv3!$F:$F, "Success", INDIRECT("rawv3!" & ADDRESS(1, MATCH($B$4 & " " & $B20, rawv3!$1:$1, 0), 4) & ":" & ADDRESS(1048576, MATCH($B$4 & " " & $B20, rawv3!$1:$1, 0), 4)), $C22)/Z22} -> 0.79581484 | AA23: {=COUNTIFS( rawv3!$F:$F, "Success", INDIRECT("rawv3!" & ADDRESS(1, MATCH($B$4 & " " & $B20, rawv3!$1:$1, 0), 4) & ":" & ADDRESS(1048576, MATCH($B$4 & " " & $B20, rawv3!$1:$1, 0), 4)), $C22)} -> 1255
B25: Environment | C25: Flexibility | D25: # | E25: {=COUNTIFS( rawv3!$F:$F, "<>Ongoing", INDIRECT("rawv3!" & ADDRESS(1, MATCH($D$2 & " " & E$3, rawv3!$1:$1, 0), 4) & ":" & ADDRESS(1048576, MATCH($D$2 & " " & E$3, rawv3!$1:$1, 0), 4)), E$4, INDIRECT("rawv3!" & ADDRESS(1, MATCH($B$4 & " " & $B25, rawv3!$1:$1, 0), 4) & ":" & ADDRESS(1048576, MATCH($B$4 & " " & $B25, rawv3!$1:$1, 0), 4)), $C25 )} -> 885 | F25: {=COUNTIFS( rawv3!$F:$F, "<>Ongoing", INDIRECT("rawv3!" & ADDRESS(1, MATCH($D$2 & " " & E$3, rawv3!$1:$1, 0), 4) & ":" & ADDRESS(1048576, MATCH($D$2 & " " & E$3, rawv3!$1:$1, 0), 4)), F$4, INDIRECT("rawv3!" & ADDRESS(1, MATCH($B$4 & " " & $B25, rawv3!$1:$1, 0), 4) & ":" & ADDRESS(1048576, MATCH($B$4 & " " & $B25, rawv3!$1:$1, 0), 4)), $C25 )} -> 858 | H25: {=COUNTIFS( rawv3!$F:$F, "<>Ongoing", INDIRECT("rawv3!" & ADDRESS(1, MATCH($D$2 & " " & H$3, rawv3!$1:$1, 0), 4) & ":" & ADDRESS(1048576, MATCH($D$2 & " " & H$3, rawv3!$1:$1, 0), 4)), H$4, INDIRECT("rawv3!" & ADDRESS(1, MATCH($B$4 & " " & $B25, rawv3!$1:$1, 0), 4) & ":" & ADDRESS(1048576, MATCH($B$4 & " " & $B25, rawv3!$1:$1, 0), 4)), $C25 )} -> 1048 | I25: {=COUNTIFS( rawv3!$F:$F, "<>Ongoing", INDIRECT("rawv3!" & ADDRESS(1, MATCH($D$2 & " " & H$3, rawv3!$1:$1, 0), 4) & ":" & ADDRESS(1048576, MATCH($D$2 & " " & H$3, rawv3!$1:$1, 0), 4)), I$4, INDIRECT("rawv3!" & ADDRESS(1, MATCH($B$4 & " " & $B25, rawv3!$1:$1, 0), 4) & ":" & ADDRESS(1048576, MATCH($B$4 & " " & $B25, rawv3!$1:$1, 0), 4)), $C25 )} -> 699 | K25: {=COUNTIFS( rawv3!$F:$F, "<>Ongoing", INDIRECT("rawv3!" & ADDRESS(1, MATCH($D$2 & " " & K$3, rawv3!$1:$1, 0), 4) & ":" & ADDRESS(1048576, MATCH($D$2 & " " & K$3, rawv3!$1:$1, 0), 4)), K$4, INDIRECT("rawv3!" & ADDRESS(1, MATCH($B$4 & " " & $B25, rawv3!$1:$1, 0), 4) & ":" & ADDRESS(1048576, MATCH($B$4 & " " & $B25, rawv3!$1:$1, 0), 4)), $C25 )} -> 834 | L25: {=COUNTIFS( rawv3!$F:$F, "<>Ongoing", INDIRECT("rawv3!" & ADDRESS(1, MATCH($D$2 & " " & K$3, rawv3!$1:$1, 0), 4) & ":" & ADDRESS(1048576, MATCH($D$2 & " " & K$3, rawv3!$1:$1, 0), 4)), L$4, INDIRECT("rawv3!" & ADDRESS(1, MATCH($B$4 & " " & $B25, rawv3!$1:$1, 0), 4) & ":" & ADDRESS(1048576, MATCH($B$4 & " " & $B25, rawv3!$1:$1, 0), 4)), $C25 )} -> 912 | N25: {=COUNTIFS( rawv3!$F:$F, "<>Ongoing", INDIRECT("rawv3!" & ADDRESS(1, MATCH($D$2 & " " & N$3, rawv3!$1:$1, 0), 4) & ":" & ADDRESS(1048576, MATCH($D$2 & " " & N$3, rawv3!$1:$1, 0), 4)), N$4, INDIRECT("rawv3!" & ADDRESS(1, MATCH($B$4 & " " & $B25, rawv3!$1:$1, 0), 4) & ":" & ADDRESS(1048576, MATCH($B$4 & " " & $B25, rawv3!$1:$1, 0), 4)), $C25 )} -> 1045 | O25: {=COUNTIFS( rawv3!$F:$F, "<>Ongoing", INDIRECT("rawv3!" & ADDRESS(1, MATCH($D$2 & " " & N$3, rawv3!$1:$1, 0), 4) & ":" & ADDRESS(1048576, MATCH($D$2 & " " & N$3, rawv3!$1:$1, 0), 4)), O$4, INDIRECT("rawv3!" & ADDRESS(1, MATCH($B$4 & " " & $B25, rawv3!$1:$1, 0), 4) & ":" & ADDRESS(1048576, MATCH($B$4 & " " & $B25, rawv3!$1:$1, 0), 4)), $C25 )} -> 702 | Q25: {=COUNTIFS( rawv3!$F:$F, "<>Ongoing", INDIRECT("rawv3!" & ADDRESS(1, MATCH($D$2 & " " & Q$3, rawv3!$1:$1, 0), 4) & ":" & ADDRESS(1048576, MATCH($D$2 & " " & Q$3, rawv3!$1:$1, 0), 4)), Q$4, INDIRECT("rawv3!" & ADDRESS(1, MATCH($B$4 & " " & $B25, rawv3!$1:$1, 0), 4) & ":" & ADDRESS(1048576, MATCH($B$4 & " " & $B25, rawv3!$1:$1, 0), 4)), $C25 )} -> 1335 | R25: {=COUNTIFS( rawv3!$F:$F, "<>Ongoing", INDIRECT("rawv3!" & ADDRESS(1, MATCH($D$2 & " " & Q$3, rawv3!$1:$1, 0), 4) & ":" & ADDRESS(1048576, MATCH($D$2 & " " & Q$3, rawv3!$1:$1, 0), 4)), R$4, INDIRECT("rawv3!" & ADDRESS(1, MATCH($B$4 & " " & $B25, rawv3!$1:$1, 0), 4) & ":" & ADDRESS(1048576, MATCH($B$4 & " " & $B25, rawv3!$1:$1, 0), 4)), $C25 )} -> 410 | T25: {=COUNTIFS( rawv3!$F:$F, "<>Ongoing", INDIRECT("rawv3!" & ADDRESS(1, MATCH($D$2 & " " & T$3, rawv3!$1:$1, 0), 4) & ":" & ADDRESS(1048576, MATCH($D$2 & " " & T$3, rawv3!$1:$1, 0), 4)), T$4, INDIRECT("rawv3!" & ADDRESS(1, MATCH($B$4 & " " & $B25, rawv3!$1:$1, 0), 4) & ":" & ADDRESS(1048576, MATCH($B$4 & " " & $B25, rawv3!$1:$1, 0), 4)), $C25 )} -> 1331 | U25: {=COUNTIFS( rawv3!$F:$F, "<>Ongoing", INDIRECT("rawv3!" & ADDRESS(1, MATCH($D$2 & " " & T$3, rawv3!$1:$1, 0), 4) & ":" & ADDRESS(1048576, MATCH($D$2 & " " & T$3, rawv3!$1:$1, 0), 4)), U$4, INDIRECT("rawv3!" & ADDRESS(1, MATCH($B$4 & " " & $B25, rawv3!$1:$1, 0), 4) & ":" & ADDRESS(1048576, MATCH($B$4 & " " & $B25, rawv3!$1:$1, 0), 4)), $C25 )} -> 415 | W25: {=COUNTIFS( rawv3!$F:$F, "<>Ongoing", INDIRECT("rawv3!" & ADDRESS(1, MATCH($D$2 & " " & W$3, rawv3!$1:$1, 0), 4) & ":" & ADDRESS(1048576, MATCH($D$2 & " " & W$3, rawv3!$1:$1, 0), 4)), W$4, INDIRECT("rawv3!" & ADDRESS(1, MATCH($B$4 & " " & $B25, rawv3!$1:$1, 0), 4) & ":" & ADDRESS(1048576, MATCH($B$4 & " " & $B25, rawv3!$1:$1, 0), 4)), $C25 )} -> 798 | X25: {=COUNTIFS( rawv3!$F:$F, "<>Ongoing", INDIRECT("rawv3!" & ADDRESS(1, MATCH($D$2 & " " & W$3, rawv3!$1:$1, 0), 4) & ":" & ADDRESS(1048576, MATCH($D$2 & " " & W$3, rawv3!$1:$1, 0), 4)), X$4, INDIRECT("rawv3!" & ADDRESS(1, MATCH($B$4 & " " & $B25, rawv3!$1:$1, 0), 4) & ":" & ADDRESS(1048576, MATCH($B$4 & " " & $B25, rawv3!$1:$1, 0), 4)), $C25 )} -> 949 | Z25: {=COUNTIFS( rawv3!$F:$F, "<>Ongoing", INDIRECT("rawv3!" & ADDRESS(1, MATCH($B$4 & " " & $B25, rawv3!$1:$1, 0), 4) & ":" & ADDRESS(1048576, MATCH($B$4 & " " & $B25, rawv3!$1:$1, 0), 4)), $C25)} -> 1747
D26: F90D % | E26: {=COUNTIFS( rawv3!$F:$F, "Success", INDIRECT("rawv3!" & ADDRESS(1, MATCH($D$2 & " " & E$3, rawv3!$1:$1, 0), 4) & ":" & ADDRESS(1048576, MATCH($D$2 & " " & E$3, rawv3!$1:$1, 0), 4)), E$4, INDIRECT("rawv3!" & ADDRESS(1, MATCH($B$4 & " " & $B25, rawv3!$1:$1, 0), 4) & ":" & ADDRESS(1048576, MATCH($B$4 & " " & $B25, rawv3!$1:$1, 0), 4)), $C25 )/E25} -> 0.77853107 | F26: {=COUNTIFS( rawv3!$F:$F, "Success", INDIRECT("rawv3!" & ADDRESS(1, MATCH($D$2 & " " & E$3, rawv3!$1:$1, 0), 4) & ":" & ADDRESS(1048576, MATCH($D$2 & " " & E$3, rawv3!$1:$1, 0), 4)), F$4, INDIRECT("rawv3!" & ADDRESS(1, MATCH($B$4 & " " & $B25, rawv3!$1:$1, 0), 4) & ":" & ADDRESS(1048576, MATCH($B$4 & " " & $B25, rawv3!$1:$1, 0), 4)), $C25 )/F25} -> 0.78088578 | H26: {=COUNTIFS( rawv3!$F:$F, "Success", INDIRECT("rawv3!" & ADDRESS(1, MATCH($D$2 & " " & H$3, rawv3!$1:$1, 0), 4) & ":" & ADDRESS(1048576, MATCH($D$2 & " " & H$3, rawv3!$1:$1, 0), 4)), H$4, INDIRECT("rawv3!" & ADDRESS(1, MATCH($B$4 & " " & $B25, rawv3!$1:$1, 0), 4) & ":" & ADDRESS(1048576, MATCH($B$4 & " " & $B25, rawv3!$1:$1, 0), 4)), $C25 )/H25} -> 0.78148855 | I26: {=COUNTIFS( rawv3!$F:$F, "Success", INDIRECT("rawv3!" & ADDRESS(1, MATCH($D$2 & " " & H$3, rawv3!$1:$1, 0), 4) & ":" & ADDRESS(1048576, MATCH($D$2 & " " & H$3, rawv3!$1:$1, 0), 4)), I$4, INDIRECT("rawv3!" & ADDRESS(1, MATCH($B$4 & " " & $B25, rawv3!$1:$1, 0), 4) & ":" & ADDRESS(1048576, MATCH($B$4 & " " & $B25, rawv3!$1:$1, 0), 4)), $C25 )/I25} -> 0.77825465 | K26: {=COUNTIFS( rawv3!$F:$F, "Success", INDIRECT("rawv3!" & ADDRESS(1, MATCH($D$2 & " " & K$3, rawv3!$1:$1, 0), 4) & ":" & ADDRESS(1048576, MATCH($D$2 & " " & K$3, rawv3!$1:$1, 0), 4)), K$4, INDIRECT("rawv3!" & ADDRESS(1, MATCH($B$4 & " " & $B25, rawv3!$1:$1, 0), 4) & ":" & ADDRESS(1048576, MATCH($B$4 & " " & $B25, rawv3!$1:$1, 0), 4)), $C25 )/K25} -> 0.7793765 | L26: {=COUNTIFS( rawv3!$F:$F, "Success", INDIRECT("rawv3!" & ADDRESS(1, MATCH($D$2 & " " & K$3, rawv3!$1:$1, 0), 4) & ":" & ADDRESS(1048576, MATCH($D$2 & " " & K$3, rawv3!$1:$1, 0), 4)), L$4, INDIRECT("rawv3!" & ADDRESS(1, MATCH($B$4 & " " & $B25, rawv3!$1:$1, 0), 4) & ":" & ADDRESS(1048576, MATCH($B$4 & " " & $B25, rawv3!$1:$1, 0), 4)), $C25 )/L25} -> 0.78179825 | N26: {=COUNTIFS( rawv3!$F:$F, "Success", INDIRECT("rawv3!" & ADDRESS(1, MATCH($D$2 & " " & N$3, rawv3!$1:$1, 0), 4) & ":" & ADDRESS(1048576, MATCH($D$2 & " " & N$3, rawv3!$1:$1, 0), 4)), N$4, INDIRECT("rawv3!" & ADDRESS(1, MATCH($B$4 & " " & $B25, rawv3!$1:$1, 0), 4) & ":" & ADDRESS(1048576, MATCH($B$4 & " " & $B25, rawv3!$1:$1, 0), 4)), $C25 )/N25} -> 0.784689 | O26: {=COUNTIFS( rawv3!$F:$F, "Success", INDIRECT("rawv3!" & ADDRESS(1, MATCH($D$2 & " " & N$3, rawv3!$1:$1, 0), 4) & ":" & ADDRESS(1048576, MATCH($D$2 & " " & N$3, rawv3!$1:$1, 0), 4)), O$4, INDIRECT("rawv3!" & ADDRESS(1, MATCH($B$4 & " " & $B25, rawv3!$1:$1, 0), 4) & ":" & ADDRESS(1048576, MATCH($B$4 & " " & $B25, rawv3!$1:$1, 0), 4)), $C25 )/O25} -> 0.77350427 | Q26: {=COUNTIFS( rawv3!$F:$F, "Success", INDIRECT("rawv3!" & ADDRESS(1, MATCH($D$2 & " " & Q$3, rawv3!$1:$1, 0), 4) & ":" & ADDRESS(1048576, MATCH($D$2 & " " & Q$3, rawv3!$1:$1, 0), 4)), Q$4, INDIRECT("rawv3!" & ADDRESS(1, MATCH($B$4 & " " & $B25, rawv3!$1:$1, 0), 4) & ":" & ADDRESS(1048576, MATCH($B$4 & " " & $B25, rawv3!$1:$1, 0), 4)), $C25 )/Q25} -> 0.7917603 | R26: {=COUNTIFS( rawv3!$F:$F, "Success", INDIRECT("rawv3!" & ADDRESS(1, MATCH($D$2 & " " & Q$3, rawv3!$1:$1, 0), 4) & ":" & ADDRESS(1048576, MATCH($D$2 & " " & Q$3, rawv3!$1:$1, 0), 4)), R$4, INDIRECT("rawv3!" & ADDRESS(1, MATCH($B$4 & " " & $B25, rawv3!$1:$1, 0), 4) & ":" & ADDRESS(1048576, MATCH($B$4 & " " & $B25, rawv3!$1:$1, 0), 4)), $C25 )/R25} -> 0.74390244 | T26: {=COUNTIFS( rawv3!$F:$F, "Success", INDIRECT("rawv3!" & ADDRESS(1, MATCH($D$2 & " " & T$3, rawv3!$1:$1, 0), 4) & ":" & ADDRESS(1048576, MATCH($D$2 & " " & T$3, rawv3!$1:$1, 0), 4)), T$4, INDIRECT("rawv3!" & ADDRESS(1, MATCH($B$4 & " " & $B25, rawv3!$1:$1, 0), 4) & ":" & ADDRESS(1048576, MATCH($B$4 & " " & $B25, rawv3!$1:$1, 0), 4)), $C25 )/T25} -> 0.78437265 | U26: {=COUNTIFS( rawv3!$F:$F, "Success", INDIRECT("rawv3!" & ADDRESS(1, MATCH($D$2 & " " & T$3, rawv3!$1:$1, 0), 4) & ":" & ADDRESS(1048576, MATCH($D$2 & " " & T$3, rawv3!$1:$1, 0), 4)), U$4, INDIRECT("rawv3!" & ADDRESS(1, MATCH($B$4 & " " & $B25, rawv3!$1:$1, 0), 4) & ":" & ADDRESS(1048576, MATCH($B$4 & " " & $B25, rawv3!$1:$1, 0), 4)), $C25 )/U25} -> 0.76626506 | W26: {=COUNTIFS( rawv3!$F:$F, "Success", INDIRECT("rawv3!" & ADDRESS(1, MATCH($D$2 & " " & W$3, rawv3!$1:$1, 0), 4) & ":" & ADDRESS(1048576, MATCH($D$2 & " " & W$3, rawv3!$1:$1, 0), 4)), W$4, INDIRECT("rawv3!" & ADDRESS(1, MATCH($B$4 & " " & $B25, rawv3!$1:$1, 0), 4) & ":" & ADDRESS(1048576, MATCH($B$4 & " " & $B25, rawv3!$1:$1, 0), 4)), $C25 )/W25} -> 0.77819549 | X26: {=COUNTIFS( rawv3!$F:$F, "Success", INDIRECT("rawv3!" & ADDRESS(1, MATCH($D$2 & " " & W$3, rawv3!$1:$1, 0), 4) & ":" & ADDRESS(1048576, MATCH($D$2 & " " & W$3, rawv3!$1:$1, 0), 4)), X$4, INDIRECT("rawv3!" & ADDRESS(1, MATCH($B$4 & " " & $B25, rawv3!$1:$1, 0), 4) & ":" & ADDRESS(1048576, MATCH($B$4 & " " & $B25, rawv3!$1:$1, 0), 4)), $C25 )/X25} -> 0.78187566 | Z26: {=COUNTIFS( rawv3!$F:$F, "Success", INDIRECT("rawv3!" & ADDRESS(1, MATCH($B$4 & " " & $B25, rawv3!$1:$1, 0), 4) & ":" & ADDRESS(1048576, MATCH($B$4 & " " & $B25, rawv3!$1:$1, 0), 4)), $C25)/Z25} -> 0.78019462 | AA26: {=COUNTIFS( rawv3!$F:$F, "Success", INDIRECT("rawv3!" & ADDRESS(1, MATCH($B$4 & " " & $B25, rawv3!$1:$1, 0), 4) & ":" & ADDRESS(1048576, MATCH($B$4 & " " & $B25, rawv3!$1:$1, 0), 4)), $C25)} -> 1363
C27: Structure | D27: # | E27: {=COUNTIFS( rawv3!$F:$F, "<>Ongoing", INDIRECT("rawv3!" & ADDRESS(1, MATCH($D$2 & " " & E$3, rawv3!$1:$1, 0), 4) & ":" & ADDRESS(1048576, MATCH($D$2 & " " & E$3, rawv3!$1:$1, 0), 4)), E$4, INDIRECT("rawv3!" & ADDRESS(1, MATCH($B$4 & " " & $B25, rawv3!$1:$1, 0), 4) & ":" & ADDRESS(1048576, MATCH($B$4 & " " & $B25, rawv3!$1:$1, 0), 4)), $C27 )} -> 398 | F27: {=COUNTIFS( rawv3!$F:$F, "<>Ongoing", INDIRECT("rawv3!" & ADDRESS(1, MATCH($D$2 & " " & E$3, rawv3!$1:$1, 0), 4) & ":" & ADDRESS(1048576, MATCH($D$2 & " " & E$3, rawv3!$1:$1, 0), 4)), F$4, INDIRECT("rawv3!" & ADDRESS(1, MATCH($B$4 & " " & $B25, rawv3!$1:$1, 0), 4) & ":" & ADDRESS(1048576, MATCH($B$4 & " " & $B25, rawv3!$1:$1, 0), 4)), $C27 )} -> 392 | H27: {=COUNTIFS( rawv3!$F:$F, "<>Ongoing", INDIRECT("rawv3!" & ADDRESS(1, MATCH($D$2 & " " & H$3, rawv3!$1:$1, 0), 4) & ":" & ADDRESS(1048576, MATCH($D$2 & " " & H$3, rawv3!$1:$1, 0), 4)), H$4, INDIRECT("rawv3!" & ADDRESS(1, MATCH($B$4 & " " & $B25, rawv3!$1:$1, 0), 4) & ":" & ADDRESS(1048576, MATCH($B$4 & " " & $B25, rawv3!$1:$1, 0), 4)), $C27 )} -> 496 | I27: {=COUNTIFS( rawv3!$F:$F, "<>Ongoing", INDIRECT("rawv3!" & ADDRESS(1, MATCH($D$2 & " " & H$3, rawv3!$1:$1, 0), 4) & ":" & ADDRESS(1048576, MATCH($D$2 & " " & H$3, rawv3!$1:$1, 0), 4)), I$4, INDIRECT("rawv3!" & ADDRESS(1, MATCH($B$4 & " " & $B25, rawv3!$1:$1, 0), 4) & ":" & ADDRESS(1048576, MATCH($B$4 & " " & $B25, rawv3!$1:$1, 0), 4)), $C27 )} -> 295 | K27: {=COUNTIFS( rawv3!$F:$F, "<>Ongoing", INDIRECT("rawv3!" & ADDRESS(1, MATCH($D$2 & " " & K$3, rawv3!$1:$1, 0), 4) & ":" & ADDRESS(1048576, MATCH($D$2 & " " & K$3, rawv3!$1:$1, 0), 4)), K$4, INDIRECT("rawv3!" & ADDRESS(1, MATCH($B$4 & " " & $B25, rawv3!$1:$1, 0), 4) & ":" & ADDRESS(1048576, MATCH($B$4 & " " & $B25, rawv3!$1:$1, 0), 4)), $C27 )} -> 388 | L27: {=COUNTIFS( rawv3!$F:$F, "<>Ongoing", INDIRECT("rawv3!" & ADDRESS(1, MATCH($D$2 & " " & K$3, rawv3!$1:$1, 0), 4) & ":" & ADDRESS(1048576, MATCH($D$2 & " " & K$3, rawv3!$1:$1, 0), 4)), L$4, INDIRECT("rawv3!" & ADDRESS(1, MATCH($B$4 & " " & $B25, rawv3!$1:$1, 0), 4) & ":" & ADDRESS(1048576, MATCH($B$4 & " " & $B25, rawv3!$1:$1, 0), 4)), $C27 )} -> 403 | N27: {=COUNTIFS( rawv3!$F:$F, "<>Ongoing", INDIRECT("rawv3!" & ADDRESS(1, MATCH($D$2 & " " & N$3, rawv3!$1:$1, 0), 4) & ":" & ADDRESS(1048576, MATCH($D$2 & " " & N$3, rawv3!$1:$1, 0), 4)), N$4, INDIRECT("rawv3!" & ADDRESS(1, MATCH($B$4 & " " & $B25, rawv3!$1:$1, 0), 4) & ":" & ADDRESS(1048576, MATCH($B$4 & " " & $B25, rawv3!$1:$1, 0), 4)), $C27 )} -> 476 | O27: {=COUNTIFS( rawv3!$F:$F, "<>Ongoing", INDIRECT("rawv3!" & ADDRESS(1, MATCH($D$2 & " " & N$3, rawv3!$1:$1, 0), 4) & ":" & ADDRESS(1048576, MATCH($D$2 & " " & N$3, rawv3!$1:$1, 0), 4)), O$4, INDIRECT("rawv3!" & ADDRESS(1, MATCH($B$4 & " " & $B25, rawv3!$1:$1, 0), 4) & ":" & ADDRESS(1048576, MATCH($B$4 & " " & $B25, rawv3!$1:$1, 0), 4)), $C27 )} -> 315 | Q27: {=COUNTIFS( rawv3!$F:$F, "<>Ongoing", INDIRECT("rawv3!" & ADDRESS(1, MATCH($D$2 & " " & Q$3, rawv3!$1:$1, 0), 4) & ":" & ADDRESS(1048576, MATCH($D$2 & " " & Q$3, rawv3!$1:$1, 0), 4)), Q$4, INDIRECT("rawv3!" & ADDRESS(1, MATCH($B$4 & " " & $B25, rawv3!$1:$1, 0), 4) & ":" & ADDRESS(1048576, MATCH($B$4 & " " & $B25, rawv3!$1:$1, 0), 4)), $C27 )} -> 505 | R27: {=COUNTIFS( rawv3!$F:$F, "<>Ongoing", INDIRECT("rawv3!" & ADDRESS(1, MATCH($D$2 & " " & Q$3, rawv3!$1:$1, 0), 4) & ":" & ADDRESS(1048576, MATCH($D$2 & " " & Q$3, rawv3!$1:$1, 0), 4)), R$4, INDIRECT("rawv3!" & ADDRESS(1, MATCH($B$4 & " " & $B25, rawv3!$1:$1, 0), 4) & ":" & ADDRESS(1048576, MATCH($B$4 & " " & $B25, rawv3!$1:$1, 0), 4)), $C27 )} -> 286 | T27: {=COUNTIFS( rawv3!$F:$F, "<>Ongoing", INDIRECT("rawv3!" & ADDRESS(1, MATCH($D$2 & " " & T$3, rawv3!$1:$1, 0), 4) & ":" & ADDRESS(1048576, MATCH($D$2 & " " & T$3, rawv3!$1:$1, 0), 4)), T$4, INDIRECT("rawv3!" & ADDRESS(1, MATCH($B$4 & " " & $B25, rawv3!$1:$1, 0), 4) & ":" & ADDRESS(1048576, MATCH($B$4 & " " & $B25, rawv3!$1:$1, 0), 4)), $C27 )} -> 590 | U27: {=COUNTIFS( rawv3!$F:$F, "<>Ongoing", INDIRECT("rawv3!" & ADDRESS(1, MATCH($D$2 & " " & T$3, rawv3!$1:$1, 0), 4) & ":" & ADDRESS(1048576, MATCH($D$2 & " " & T$3, rawv3!$1:$1, 0), 4)), U$4, INDIRECT("rawv3!" & ADDRESS(1, MATCH($B$4 & " " & $B25, rawv3!$1:$1, 0), 4) & ":" & ADDRESS(1048576, MATCH($B$4 & " " & $B25, rawv3!$1:$1, 0), 4)), $C27 )} -> 201 | W27: {=COUNTIFS( rawv3!$F:$F, "<>Ongoing", INDIRECT("rawv3!" & ADDRESS(1, MATCH($D$2 & " " & W$3, rawv3!$1:$1, 0), 4) & ":" & ADDRESS(1048576, MATCH($D$2 & " " & W$3, rawv3!$1:$1, 0), 4)), W$4, INDIRECT("rawv3!" & ADDRESS(1, MATCH($B$4 & " " & $B25, rawv3!$1:$1, 0), 4) & ":" & ADDRESS(1048576, MATCH($B$4 & " " & $B25, rawv3!$1:$1, 0), 4)), $C27 )} -> 329 | X27: {=COUNTIFS( rawv3!$F:$F, "<>Ongoing", INDIRECT("rawv3!" & ADDRESS(1, MATCH($D$2 & " " & W$3, rawv3!$1:$1, 0), 4) & ":" & ADDRESS(1048576, MATCH($D$2 & " " & W$3, rawv3!$1:$1, 0), 4)), X$4, INDIRECT("rawv3!" & ADDRESS(1, MATCH($B$4 & " " & $B25, rawv3!$1:$1, 0), 4) & ":" & ADDRESS(1048576, MATCH($B$4 & " " & $B25, rawv3!$1:$1, 0), 4)), $C27 )} -> 462 | Z27: {=COUNTIFS( rawv3!$F:$F, "<>Ongoing", INDIRECT("rawv3!" & ADDRESS(1, MATCH($B$4 & " " & $B25, rawv3!$1:$1, 0), 4) & ":" & ADDRESS(1048576, MATCH($B$4 & " " & $B25, rawv3!$1:$1, 0), 4)), $C27)} -> 791
D28: F90D % | E28: {=COUNTIFS( rawv3!$F:$F, "Success", INDIRECT("rawv3!" & ADDRESS(1, MATCH($D$2 & " " & E$3, rawv3!$1:$1, 0), 4) & ":" & ADDRESS(1048576, MATCH($D$2 & " " & E$3, rawv3!$1:$1, 0), 4)), E$4, INDIRECT("rawv3!" & ADDRESS(1, MATCH($B$4 & " " & $B25, rawv3!$1:$1, 0), 4) & ":" & ADDRESS(1048576, MATCH($B$4 & " " & $B25, rawv3!$1:$1, 0), 4)), $C27 )/E27} -> 0.78140704 | F28: {=COUNTIFS( rawv3!$F:$F, "Success", INDIRECT("rawv3!" & ADDRESS(1, MATCH($D$2 & " " & E$3, rawv3!$1:$1, 0), 4) & ":" & ADDRESS(1048576, MATCH($D$2 & " " & E$3, rawv3!$1:$1, 0), 4)), F$4, INDIRECT("rawv3!" & ADDRESS(1, MATCH($B$4 & " " & $B25, rawv3!$1:$1, 0), 4) & ":" & ADDRESS(1048576, MATCH($B$4 & " " & $B25, rawv3!$1:$1, 0), 4)), $C27 )/F27} -> 0.83673469 | H28: {=COUNTIFS( rawv3!$F:$F, "Success", INDIRECT("rawv3!" & ADDRESS(1, MATCH($D$2 & " " & H$3, rawv3!$1:$1, 0), 4) & ":" & ADDRESS(1048576, MATCH($D$2 & " " & H$3, rawv3!$1:$1, 0), 4)), H$4, INDIRECT("rawv3!" & ADDRESS(1, MATCH($B$4 & " " & $B25, rawv3!$1:$1, 0), 4) & ":" & ADDRESS(1048576, MATCH($B$4 & " " & $B25, rawv3!$1:$1, 0), 4)), $C27 )/H27} -> 0.8266129 | I28: {=COUNTIFS( rawv3!$F:$F, "Success", INDIRECT("rawv3!" & ADDRESS(1, MATCH($D$2 & " " & H$3, rawv3!$1:$1, 0), 4) & ":" & ADDRESS(1048576, MATCH($D$2 & " " & H$3, rawv3!$1:$1, 0), 4)), I$4, INDIRECT("rawv3!" & ADDRESS(1, MATCH($B$4 & " " & $B25, rawv3!$1:$1, 0), 4) & ":" & ADDRESS(1048576, MATCH($B$4 & " " & $B25, rawv3!$1:$1, 0), 4)), $C27 )/I27} -> 0.77966102 | K28: {=COUNTIFS( rawv3!$F:$F, "Success", INDIRECT("rawv3!" & ADDRESS(1, MATCH($D$2 & " " & K$3, rawv3!$1:$1, 0), 4) & ":" & ADDRESS(1048576, MATCH($D$2 & " " & K$3, rawv3!$1:$1, 0), 4)), K$4, INDIRECT("rawv3!" & ADDRESS(1, MATCH($B$4 & " " & $B25, rawv3!$1:$1, 0), 4) & ":" & ADDRESS(1048576, MATCH($B$4 & " " & $B25, rawv3!$1:$1, 0), 4)), $C27 )/K27} -> 0.80412371 | L28: {=COUNTIFS( rawv3!$F:$F, "Success", INDIRECT("rawv3!" & ADDRESS(1, MATCH($D$2 & " " & K$3, rawv3!$1:$1, 0), 4) & ":" & ADDRESS(1048576, MATCH($D$2 & " " & K$3, rawv3!$1:$1, 0), 4)), L$4, INDIRECT("rawv3!" & ADDRESS(1, MATCH($B$4 & " " & $B25, rawv3!$1:$1, 0), 4) & ":" & ADDRESS(1048576, MATCH($B$4 & " " & $B25, rawv3!$1:$1, 0), 4)), $C27 )/L27} -> 0.81389578 | N28: {=COUNTIFS( rawv3!$F:$F, "Success", INDIRECT("rawv3!" & ADDRESS(1, MATCH($D$2 & " " & N$3, rawv3!$1:$1, 0), 4) & ":" & ADDRESS(1048576, MATCH($D$2 & " " & N$3, rawv3!$1:$1, 0), 4)), N$4, INDIRECT("rawv3!" & ADDRESS(1, MATCH($B$4 & " " & $B25, rawv3!$1:$1, 0), 4) & ":" & ADDRESS(1048576, MATCH($B$4 & " " & $B25, rawv3!$1:$1, 0), 4)), $C27 )/N27} -> 0.81302521 | O28: {=COUNTIFS( rawv3!$F:$F, "Success", INDIRECT("rawv3!" & ADDRESS(1, MATCH($D$2 & " " & N$3, rawv3!$1:$1, 0), 4) & ":" & ADDRESS(1048576, MATCH($D$2 & " " & N$3, rawv3!$1:$1, 0), 4)), O$4, INDIRECT("rawv3!" & ADDRESS(1, MATCH($B$4 & " " & $B25, rawv3!$1:$1, 0), 4) & ":" & ADDRESS(1048576, MATCH($B$4 & " " & $B25, rawv3!$1:$1, 0), 4)), $C27 )/O27} -> 0.8031746 | Q28: {=COUNTIFS( rawv3!$F:$F, "Success", INDIRECT("rawv3!" & ADDRESS(1, MATCH($D$2 & " " & Q$3, rawv3!$1:$1, 0), 4) & ":" & ADDRESS(1048576, MATCH($D$2 & " " & Q$3, rawv3!$1:$1, 0), 4)), Q$4, INDIRECT("rawv3!" & ADDRESS(1, MATCH($B$4 & " " & $B25, rawv3!$1:$1, 0), 4) & ":" & ADDRESS(1048576, MATCH($B$4 & " " & $B25, rawv3!$1:$1, 0), 4)), $C27 )/Q27} -> 0.8039604 | R28: {=COUNTIFS( rawv3!$F:$F, "Success", INDIRECT("rawv3!" & ADDRESS(1, MATCH($D$2 & " " & Q$3, rawv3!$1:$1, 0), 4) & ":" & ADDRESS(1048576, MATCH($D$2 & " " & Q$3, rawv3!$1:$1, 0), 4)), R$4, INDIRECT("rawv3!" & ADDRESS(1, MATCH($B$4 & " " & $B25, rawv3!$1:$1, 0), 4) & ":" & ADDRESS(1048576, MATCH($B$4 & " " & $B25, rawv3!$1:$1, 0), 4)), $C27 )/R27} -> 0.81818182 | T28: {=COUNTIFS( rawv3!$F:$F, "Success", INDIRECT("rawv3!" & ADDRESS(1, MATCH($D$2 & " " & T$3, rawv3!$1:$1, 0), 4) & ":" & ADDRESS(1048576, MATCH($D$2 & " " & T$3, rawv3!$1:$1, 0), 4)), T$4, INDIRECT("rawv3!" & ADDRESS(1, MATCH($B$4 & " " & $B25, rawv3!$1:$1, 0), 4) & ":" & ADDRESS(1048576, MATCH($B$4 & " " & $B25, rawv3!$1:$1, 0), 4)), $C27 )/T27} -> 0.80677966 | U28: {=COUNTIFS( rawv3!$F:$F, "Success", INDIRECT("rawv3!" & ADDRESS(1, MATCH($D$2 & " " & T$3, rawv3!$1:$1, 0), 4) & ":" & ADDRESS(1048576, MATCH($D$2 & " " & T$3, rawv3!$1:$1, 0), 4)), U$4, INDIRECT("rawv3!" & ADDRESS(1, MATCH($B$4 & " " & $B25, rawv3!$1:$1, 0), 4) & ":" & ADDRESS(1048576, MATCH($B$4 & " " & $B25, rawv3!$1:$1, 0), 4)), $C27 )/U27} -> 0.8159204 | W28: {=COUNTIFS( rawv3!$F:$F, "Success", INDIRECT("rawv3!" & ADDRESS(1, MATCH($D$2 & " " & W$3, rawv3!$1:$1, 0), 4) & ":" & ADDRESS(1048576, MATCH($D$2 & " " & W$3, rawv3!$1:$1, 0), 4)), W$4, INDIRECT("rawv3!" & ADDRESS(1, MATCH($B$4 & " " & $B25, rawv3!$1:$1, 0), 4) & ":" & ADDRESS(1048576, MATCH($B$4 & " " & $B25, rawv3!$1:$1, 0), 4)), $C27 )/W27} -> 0.78115502 | X28: {=COUNTIFS( rawv3!$F:$F, "Success", INDIRECT("rawv3!" & ADDRESS(1, MATCH($D$2 & " " & W$3, rawv3!$1:$1, 0), 4) & ":" & ADDRESS(1048576, MATCH($D$2 & " " & W$3, rawv3!$1:$1, 0), 4)), X$4, INDIRECT("rawv3!" & ADDRESS(1, MATCH($B$4 & " " & $B25, rawv3!$1:$1, 0), 4) & ":" & ADDRESS(1048576, MATCH($B$4 & " " & $B25, rawv3!$1:$1, 0), 4)), $C27 )/X27} -> 0.82900433 | Z28: {=COUNTIFS( rawv3!$F:$F, "Success", INDIRECT("rawv3!" & ADDRESS(1, MATCH($B$4 & " " & $B25, rawv3!$1:$1, 0), 4) & ":" & ADDRESS(1048576, MATCH($B$4 & " " & $B25, rawv3!$1:$1, 0), 4)), $C27)/Z27} -> 0.8091024 | AA28: {=COUNTIFS( rawv3!$F:$F, "Success", INDIRECT("rawv3!" & ADDRESS(1, MATCH($B$4 & " " & $B25, rawv3!$1:$1, 0), 4) & ":" & ADDRESS(1048576, MATCH($B$4 & " " & $B25, rawv3!$1:$1, 0), 4)), $C27)} -> 640
B30: Preference | C30: One goal in mind | D30: # | E30: {=COUNTIFS( rawv3!$F:$F, "<>Ongoing", INDIRECT("rawv3!" & ADDRESS(1, MATCH($D$2 & " " & E$3, rawv3!$1:$1, 0), 4) & ":" & ADDRESS(1048576, MATCH($D$2 & " " & E$3, rawv3!$1:$1, 0), 4)), E$4, INDIRECT("rawv3!" & ADDRESS(1, MATCH($B$4 & " " & $B30, rawv3!$1:$1, 0), 4) & ":" & ADDRESS(1048576, MATCH($B$4 & " " & $B30, rawv3!$1:$1, 0), 4)), $C30 )} -> 291 | F30: {=COUNTIFS( rawv3!$F:$F, "<>Ongoing", INDIRECT("rawv3!" & ADDRESS(1, MATCH($D$2 & " " & E$3, rawv3!$1:$1, 0), 4) & ":" & ADDRESS(1048576, MATCH($D$2 & " " & E$3, rawv3!$1:$1, 0), 4)), F$4, INDIRECT("rawv3!" & ADDRESS(1, MATCH($B$4 & " " & $B30, rawv3!$1:$1, 0), 4) & ":" & ADDRESS(1048576, MATCH($B$4 & " " & $B30, rawv3!$1:$1, 0), 4)), $C30 )} -> 268 | H30: {=COUNTIFS( rawv3!$F:$F, "<>Ongoing", INDIRECT("rawv3!" & ADDRESS(1, MATCH($D$2 & " " & H$3, rawv3!$1:$1, 0), 4) & ":" & ADDRESS(1048576, MATCH($D$2 & " " & H$3, rawv3!$1:$1, 0), 4)), H$4, INDIRECT("rawv3!" & ADDRESS(1, MATCH($B$4 & " " & $B30, rawv3!$1:$1, 0), 4) & ":" & ADDRESS(1048576, MATCH($B$4 & " " & $B30, rawv3!$1:$1, 0), 4)), $C30 )} -> 326 | I30: {=COUNTIFS( rawv3!$F:$F, "<>Ongoing", INDIRECT("rawv3!" & ADDRESS(1, MATCH($D$2 & " " & H$3, rawv3!$1:$1, 0), 4) & ":" & ADDRESS(1048576, MATCH($D$2 & " " & H$3, rawv3!$1:$1, 0), 4)), I$4, INDIRECT("rawv3!" & ADDRESS(1, MATCH($B$4 & " " & $B30, rawv3!$1:$1, 0), 4) & ":" & ADDRESS(1048576, MATCH($B$4 & " " & $B30, rawv3!$1:$1, 0), 4)), $C30 )} -> 234 | K30: {=COUNTIFS( rawv3!$F:$F, "<>Ongoing", INDIRECT("rawv3!" & ADDRESS(1, MATCH($D$2 & " " & K$3, rawv3!$1:$1, 0), 4) & ":" & ADDRESS(1048576, MATCH($D$2 & " " & K$3, rawv3!$1:$1, 0), 4)), K$4, INDIRECT("rawv3!" & ADDRESS(1, MATCH($B$4 & " " & $B30, rawv3!$1:$1, 0), 4) & ":" & ADDRESS(1048576, MATCH($B$4 & " " & $B30, rawv3!$1:$1, 0), 4)), $C30 )} -> 243 | L30: {=COUNTIFS( rawv3!$F:$F, "<>Ongoing", INDIRECT("rawv3!" & ADDRESS(1, MATCH($D$2 & " " & K$3, rawv3!$1:$1, 0), 4) & ":" & ADDRESS(1048576, MATCH($D$2 & " " & K$3, rawv3!$1:$1, 0), 4)), L$4, INDIRECT("rawv3!" & ADDRESS(1, MATCH($B$4 & " " & $B30, rawv3!$1:$1, 0), 4) & ":" & ADDRESS(1048576, MATCH($B$4 & " " & $B30, rawv3!$1:$1, 0), 4)), $C30 )} -> 316 | N30: {=COUNTIFS( rawv3!$F:$F, "<>Ongoing", INDIRECT("rawv3!" & ADDRESS(1, MATCH($D$2 & " " & N$3, rawv3!$1:$1, 0), 4) & ":" & ADDRESS(1048576, MATCH($D$2 & " " & N$3, rawv3!$1:$1, 0), 4)), N$4, INDIRECT("rawv3!" & ADDRESS(1, MATCH($B$4 & " " & $B30, rawv3!$1:$1, 0), 4) & ":" & ADDRESS(1048576, MATCH($B$4 & " " & $B30, rawv3!$1:$1, 0), 4)), $C30 )} -> 357 | O30: {=COUNTIFS( rawv3!$F:$F, "<>Ongoing", INDIRECT("rawv3!" & ADDRESS(1, MATCH($D$2 & " " & N$3, rawv3!$1:$1, 0), 4) & ":" & ADDRESS(1048576, MATCH($D$2 & " " & N$3, rawv3!$1:$1, 0), 4)), O$4, INDIRECT("rawv3!" & ADDRESS(1, MATCH($B$4 & " " & $B30, rawv3!$1:$1, 0), 4) & ":" & ADDRESS(1048576, MATCH($B$4 & " " & $B30, rawv3!$1:$1, 0), 4)), $C30 )} -> 203 | Q30: {=COUNTIFS( rawv3!$F:$F, "<>Ongoing", INDIRECT("rawv3!" & ADDRESS(1, MATCH($D$2 & " " & Q$3, rawv3!$1:$1, 0), 4) & ":" & ADDRESS(1048576, MATCH($D$2 & " " & Q$3, rawv3!$1:$1, 0), 4)), Q$4, INDIRECT("rawv3!" & ADDRESS(1, MATCH($B$4 & " " & $B30, rawv3!$1:$1, 0), 4) & ":" & ADDRESS(1048576, MATCH($B$4 & " " & $B30, rawv3!$1:$1, 0), 4)), $C30 )} -> 425 | R30: {=COUNTIFS( rawv3!$F:$F, "<>Ongoing", INDIRECT("rawv3!" & ADDRESS(1, MATCH($D$2 & " " & Q$3, rawv3!$1:$1, 0), 4) & ":" & ADDRESS(1048576, MATCH($D$2 & " " & Q$3, rawv3!$1:$1, 0), 4)), R$4, INDIRECT("rawv3!" & ADDRESS(1, MATCH($B$4 & " " & $B30, rawv3!$1:$1, 0), 4) & ":" & ADDRESS(1048576, MATCH($B$4 & " " & $B30, rawv3!$1:$1, 0), 4)), $C30 )} -> 134 | T30: {=COUNTIFS( rawv3!$F:$F, "<>Ongoing", INDIRECT("rawv3!" & ADDRESS(1, MATCH($D$2 & " " & T$3, rawv3!$1:$1, 0), 4) & ":" & ADDRESS(1048576, MATCH($D$2 & " " & T$3, rawv3!$1:$1, 0), 4)), T$4, INDIRECT("rawv3!" & ADDRESS(1, MATCH($B$4 & " " & $B30, rawv3!$1:$1, 0), 4) & ":" & ADDRESS(1048576, MATCH($B$4 & " " & $B30, rawv3!$1:$1, 0), 4)), $C30 )} -> 461 | U30: {=COUNTIFS( rawv3!$F:$F, "<>Ongoing", INDIRECT("rawv3!" & ADDRESS(1, MATCH($D$2 & " " & T$3, rawv3!$1:$1, 0), 4) & ":" & ADDRESS(1048576, MATCH($D$2 & " " & T$3, rawv3!$1:$1, 0), 4)), U$4, INDIRECT("rawv3!" & ADDRESS(1, MATCH($B$4 & " " & $B30, rawv3!$1:$1, 0), 4) & ":" & ADDRESS(1048576, MATCH($B$4 & " " & $B30, rawv3!$1:$1, 0), 4)), $C30 )} -> 99 | W30: {=COUNTIFS( rawv3!$F:$F, "<>Ongoing", INDIRECT("rawv3!" & ADDRESS(1, MATCH($D$2 & " " & W$3, rawv3!$1:$1, 0), 4) & ":" & ADDRESS(1048576, MATCH($D$2 & " " & W$3, rawv3!$1:$1, 0), 4)), W$4, INDIRECT("rawv3!" & ADDRESS(1, MATCH($B$4 & " " & $B30, rawv3!$1:$1, 0), 4) & ":" & ADDRESS(1048576, MATCH($B$4 & " " & $B30, rawv3!$1:$1, 0), 4)), $C30 )} -> 266 | X30: {=COUNTIFS( rawv3!$F:$F, "<>Ongoing", INDIRECT("rawv3!" & ADDRESS(1, MATCH($D$2 & " " & W$3, rawv3!$1:$1, 0), 4) & ":" & ADDRESS(1048576, MATCH($D$2 & " " & W$3, rawv3!$1:$1, 0), 4)), X$4, INDIRECT("rawv3!" & ADDRESS(1, MATCH($B$4 & " " & $B30, rawv3!$1:$1, 0), 4) & ":" & ADDRESS(1048576, MATCH($B$4 & " " & $B30, rawv3!$1:$1, 0), 4)), $C30 )} -> 294 | Z30: {=COUNTIFS( rawv3!$F:$F, "<>Ongoing", INDIRECT("rawv3!" & ADDRESS(1, MATCH($B$4 & " " & $B30, rawv3!$1:$1, 0), 4) & ":" & ADDRESS(1048576, MATCH($B$4 & " " & $B30, rawv3!$1:$1, 0), 4)), $C30)} -> 560
D31: F90D % | E31: {=COUNTIFS( rawv3!$F:$F, "Success", INDIRECT("rawv3!" & ADDRESS(1, MATCH($D$2 & " " & E$3, rawv3!$1:$1, 0), 4) & ":" & ADDRESS(1048576, MATCH($D$2 & " " & E$3, rawv3!$1:$1, 0), 4)), E$4, INDIRECT("rawv3!" & ADDRESS(1, MATCH($B$4 & " " & $B30, rawv3!$1:$1, 0), 4) & ":" & ADDRESS(1048576, MATCH($B$4 & " " & $B30, rawv3!$1:$1, 0), 4)), $C30 )/E30} -> 0.76632302 | F31: {=COUNTIFS( rawv3!$F:$F, "Success", INDIRECT("rawv3!" & ADDRESS(1, MATCH($D$2 & " " & E$3, rawv3!$1:$1, 0), 4) & ":" & ADDRESS(1048576, MATCH($D$2 & " " & E$3, rawv3!$1:$1, 0), 4)), F$4, INDIRECT("rawv3!" & ADDRESS(1, MATCH($B$4 & " " & $B30, rawv3!$1:$1, 0), 4) & ":" & ADDRESS(1048576, MATCH($B$4 & " " & $B30, rawv3!$1:$1, 0), 4)), $C30 )/F30} -> 0.81343284 | H31: {=COUNTIFS( rawv3!$F:$F, "Success", INDIRECT("rawv3!" & ADDRESS(1, MATCH($D$2 & " " & H$3, rawv3!$1:$1, 0), 4) & ":" & ADDRESS(1048576, MATCH($D$2 & " " & H$3, rawv3!$1:$1, 0), 4)), H$4, INDIRECT("rawv3!" & ADDRESS(1, MATCH($B$4 & " " & $B30, rawv3!$1:$1, 0), 4) & ":" & ADDRESS(1048576, MATCH($B$4 & " " & $B30, rawv3!$1:$1, 0), 4)), $C30 )/H30} -> 0.76687117 | I31: {=COUNTIFS( rawv3!$F:$F, "Success", INDIRECT("rawv3!" & ADDRESS(1, MATCH($D$2 & " " & H$3, rawv3!$1:$1, 0), 4) & ":" & ADDRESS(1048576, MATCH($D$2 & " " & H$3, rawv3!$1:$1, 0), 4)), I$4, INDIRECT("rawv3!" & ADDRESS(1, MATCH($B$4 & " " & $B30, rawv3!$1:$1, 0), 4) & ":" & ADDRESS(1048576, MATCH($B$4 & " " & $B30, rawv3!$1:$1, 0), 4)), $C30 )/I30} -> 0.82051282 | K31: {=COUNTIFS( rawv3!$F:$F, "Success", INDIRECT("rawv3!" & ADDRESS(1, MATCH($D$2 & " " & K$3, rawv3!$1:$1, 0), 4) & ":" & ADDRESS(1048576, MATCH($D$2 & " " & K$3, rawv3!$1:$1, 0), 4)), K$4, INDIRECT("rawv3!" & ADDRESS(1, MATCH($B$4 & " " & $B30, rawv3!$1:$1, 0), 4) & ":" & ADDRESS(1048576, MATCH($B$4 & " " & $B30, rawv3!$1:$1, 0), 4)), $C30 )/K30} -> 0.80658436 | L31: {=COUNTIFS( rawv3!$F:$F, "Success", INDIRECT("rawv3!" & ADDRESS(1, MATCH($D$2 & " " & K$3, rawv3!$1:$1, 0), 4) & ":" & ADDRESS(1048576, MATCH($D$2 & " " & K$3, rawv3!$1:$1, 0), 4)), L$4, INDIRECT("rawv3!" & ADDRESS(1, MATCH($B$4 & " " & $B30, rawv3!$1:$1, 0), 4) & ":" & ADDRESS(1048576, MATCH($B$4 & " " & $B30, rawv3!$1:$1, 0), 4)), $C30 )/L30} -> 0.77848101 | N31: {=COUNTIFS( rawv3!$F:$F, "Success", INDIRECT("rawv3!" & ADDRESS(1, MATCH($D$2 & " " & N$3, rawv3!$1:$1, 0), 4) & ":" & ADDRESS(1048576, MATCH($D$2 & " " & N$3, rawv3!$1:$1, 0), 4)), N$4, INDIRECT("rawv3!" & ADDRESS(1, MATCH($B$4 & " " & $B30, rawv3!$1:$1, 0), 4) & ":" & ADDRESS(1048576, MATCH($B$4 & " " & $B30, rawv3!$1:$1, 0), 4)), $C30 )/N30} -> 0.77310924 | O31: {=COUNTIFS( rawv3!$F:$F, "Success", INDIRECT("rawv3!" & ADDRESS(1, MATCH($D$2 & " " & N$3, rawv3!$1:$1, 0), 4) & ":" & ADDRESS(1048576, MATCH($D$2 & " " & N$3, rawv3!$1:$1, 0), 4)), O$4, INDIRECT("rawv3!" & ADDRESS(1, MATCH($B$4 & " " & $B30, rawv3!$1:$1, 0), 4) & ":" & ADDRESS(1048576, MATCH($B$4 & " " & $B30, rawv3!$1:$1, 0), 4)), $C30 )/O30} -> 0.81773399 | Q31: {=COUNTIFS( rawv3!$F:$F, "Success", INDIRECT("rawv3!" & ADDRESS(1, MATCH($D$2 & " " & Q$3, rawv3!$1:$1, 0), 4) & ":" & ADDRESS(1048576, MATCH($D$2 & " " & Q$3, rawv3!$1:$1, 0), 4)), Q$4, INDIRECT("rawv3!" & ADDRESS(1, MATCH($B$4 & " " & $B30, rawv3!$1:$1, 0), 4) & ":" & ADDRESS(1048576, MATCH($B$4 & " " & $B30, rawv3!$1:$1, 0), 4)), $C30 )/Q30} -> 0.79058824 | R31: {=COUNTIFS( rawv3!$F:$F, "Success", INDIRECT("rawv3!" & ADDRESS(1, MATCH($D$2 & " " & Q$3, rawv3!$1:$1, 0), 4) & ":" & ADDRESS(1048576, MATCH($D$2 & " " & Q$3, rawv3!$1:$1, 0), 4)), R$4, INDIRECT("rawv3!" & ADDRESS(1, MATCH($B$4 & " " & $B30, rawv3!$1:$1, 0), 4) & ":" & ADDRESS(1048576, MATCH($B$4 & " " & $B30, rawv3!$1:$1, 0), 4)), $C30 )/R30} -> 0.79104478 | T31: {=COUNTIFS( rawv3!$F:$F, "Success", INDIRECT("rawv3!" & ADDRESS(1, MATCH($D$2 & " " & T$3, rawv3!$1:$1, 0), 4) & ":" & ADDRESS(1048576, MATCH($D$2 & " " & T$3, rawv3!$1:$1, 0), 4)), T$4, INDIRECT("rawv3!" & ADDRESS(1, MATCH($B$4 & " " & $B30, rawv3!$1:$1, 0), 4) & ":" & ADDRESS(1048576, MATCH($B$4 & " " & $B30, rawv3!$1:$1, 0), 4)), $C30 )/T30} -> 0.79175705 | U31: {=COUNTIFS( rawv3!$F:$F, "Success", INDIRECT("rawv3!" & ADDRESS(1, MATCH($D$2 & " " & T$3, rawv3!$1:$1, 0), 4) & ":" & ADDRESS(1048576, MATCH($D$2 & " " & T$3, rawv3!$1:$1, 0), 4)), U$4, INDIRECT("rawv3!" & ADDRESS(1, MATCH($B$4 & " " & $B30, rawv3!$1:$1, 0), 4) & ":" & ADDRESS(1048576, MATCH($B$4 & " " & $B30, rawv3!$1:$1, 0), 4)), $C30 )/U30} -> 0.77777778 | W31: {=COUNTIFS( rawv3!$F:$F, "Success", INDIRECT("rawv3!" & ADDRESS(1, MATCH($D$2 & " " & W$3, rawv3!$1:$1, 0), 4) & ":" & ADDRESS(1048576, MATCH($D$2 & " " & W$3, rawv3!$1:$1, 0), 4)), W$4, INDIRECT("rawv3!" & ADDRESS(1, MATCH($B$4 & " " & $B30, rawv3!$1:$1, 0), 4) & ":" & ADDRESS(1048576, MATCH($B$4 & " " & $B30, rawv3!$1:$1, 0), 4)), $C30 )/W30} -> 0.80451128 | X31: {=COUNTIFS( rawv3!$F:$F, "Success", INDIRECT("rawv3!" & ADDRESS(1, MATCH($D$2 & " " & W$3, rawv3!$1:$1, 0), 4) & ":" & ADDRESS(1048576, MATCH($D$2 & " " & W$3, rawv3!$1:$1, 0), 4)), X$4, INDIRECT("rawv3!" & ADDRESS(1, MATCH($B$4 & " " & $B30, rawv3!$1:$1, 0), 4) & ":" & ADDRESS(1048576, MATCH($B$4 & " " & $B30, rawv3!$1:$1, 0), 4)), $C30 )/X30} -> 0.7755102 | Z31: {=COUNTIFS( rawv3!$F:$F, "Success", INDIRECT("rawv3!" & ADDRESS(1, MATCH($B$4 & " " & $B30, rawv3!$1:$1, 0), 4) & ":" & ADDRESS(1048576, MATCH($B$4 & " " & $B30, rawv3!$1:$1, 0), 4)), $C30)/Z30} -> 0.78928571 | AA31: {=COUNTIFS( rawv3!$F:$F, "Success", INDIRECT("rawv3!" & ADDRESS(1, MATCH($B$4 & " " & $B30, rawv3!$1:$1, 0), 4) & ":" & ADDRESS(1048576, MATCH($B$4 & " " & $B30, rawv3!$1:$1, 0), 4)), $C30)} -> 442
C32: With detailed instructions | D32: # | E32: {=COUNTIFS( rawv3!$F:$F, "<>Ongoing", INDIRECT("rawv3!" & ADDRESS(1, MATCH($D$2 & " " & E$3, rawv3!$1:$1, 0), 4) & ":" & ADDRESS(1048576, MATCH($D$2 & " " & E$3, rawv3!$1:$1, 0), 4)), E$4, INDIRECT("rawv3!" & ADDRESS(1, MATCH($B$4 & " " & $B30, rawv3!$1:$1, 0), 4) & ":" & ADDRESS(1048576, MATCH($B$4 & " " & $B30, rawv3!$1:$1, 0), 4)), $C32 )} -> 992 | F32: {=COUNTIFS( rawv3!$F:$F, "<>Ongoing", INDIRECT("rawv3!" & ADDRESS(1, MATCH($D$2 & " " & E$3, rawv3!$1:$1, 0), 4) & ":" & ADDRESS(1048576, MATCH($D$2 & " " & E$3, rawv3!$1:$1, 0), 4)), F$4, INDIRECT("rawv3!" & ADDRESS(1, MATCH($B$4 & " " & $B30, rawv3!$1:$1, 0), 4) & ":" & ADDRESS(1048576, MATCH($B$4 & " " & $B30, rawv3!$1:$1, 0), 4)), $C32 )} -> 982 | H32: {=COUNTIFS( rawv3!$F:$F, "<>Ongoing", INDIRECT("rawv3!" & ADDRESS(1, MATCH($D$2 & " " & H$3, rawv3!$1:$1, 0), 4) & ":" & ADDRESS(1048576, MATCH($D$2 & " " & H$3, rawv3!$1:$1, 0), 4)), H$4, INDIRECT("rawv3!" & ADDRESS(1, MATCH($B$4 & " " & $B30, rawv3!$1:$1, 0), 4) & ":" & ADDRESS(1048576, MATCH($B$4 & " " & $B30, rawv3!$1:$1, 0), 4)), $C32 )} -> 1218 | I32: {=COUNTIFS( rawv3!$F:$F, "<>Ongoing", INDIRECT("rawv3!" & ADDRESS(1, MATCH($D$2 & " " & H$3, rawv3!$1:$1, 0), 4) & ":" & ADDRESS(1048576, MATCH($D$2 & " " & H$3, rawv3!$1:$1, 0), 4)), I$4, INDIRECT("rawv3!" & ADDRESS(1, MATCH($B$4 & " " & $B30, rawv3!$1:$1, 0), 4) & ":" & ADDRESS(1048576, MATCH($B$4 & " " & $B30, rawv3!$1:$1, 0), 4)), $C32 )} -> 760 | K32: {=COUNTIFS( rawv3!$F:$F, "<>Ongoing", INDIRECT("rawv3!" & ADDRESS(1, MATCH($D$2 & " " & K$3, rawv3!$1:$1, 0), 4) & ":" & ADDRESS(1048576, MATCH($D$2 & " " & K$3, rawv3!$1:$1, 0), 4)), K$4, INDIRECT("rawv3!" & ADDRESS(1, MATCH($B$4 & " " & $B30, rawv3!$1:$1, 0), 4) & ":" & ADDRESS(1048576, MATCH($B$4 & " " & $B30, rawv3!$1:$1, 0), 4)), $C32 )} -> 979 | L32: {=COUNTIFS( rawv3!$F:$F, "<>Ongoing", INDIRECT("rawv3!" & ADDRESS(1, MATCH($D$2 & " " & K$3, rawv3!$1:$1, 0), 4) & ":" & ADDRESS(1048576, MATCH($D$2 & " " & K$3, rawv3!$1:$1, 0), 4)), L$4, INDIRECT("rawv3!" & ADDRESS(1, MATCH($B$4 & " " & $B30, rawv3!$1:$1, 0), 4) & ":" & ADDRESS(1048576, MATCH($B$4 & " " & $B30, rawv3!$1:$1, 0), 4)), $C32 )} -> 999 | N32: {=COUNTIFS( rawv3!$F:$F, "<>Ongoing", INDIRECT("rawv3!" & ADDRESS(1, MATCH($D$2 & " " & N$3, rawv3!$1:$1, 0), 4) & ":" & ADDRESS(1048576, MATCH($D$2 & " " & N$3, rawv3!$1:$1, 0), 4)), N$4, INDIRECT("rawv3!" & ADDRESS(1, MATCH($B$4 & " " & $B30, rawv3!$1:$1, 0), 4) & ":" & ADDRESS(1048576, MATCH($B$4 & " " & $B30, rawv3!$1:$1, 0), 4)), $C32 )} -> 1164 | O32: {=COUNTIFS( rawv3!$F:$F, "<>Ongoing", INDIRECT("rawv3!" & ADDRESS(1, MATCH($D$2 & " " & N$3, rawv3!$1:$1, 0), 4) & ":" & ADDRESS(1048576, MATCH($D$2 & " " & N$3, rawv3!$1:$1, 0), 4)), O$4, INDIRECT("rawv3!" & ADDRESS(1, MATCH($B$4 & " " & $B30, rawv3!$1:$1, 0), 4) & ":" & ADDRESS(1048576, MATCH($B$4 & " " & $B30, rawv3!$1:$1, 0), 4)), $C32 )} -> 814 | Q32: {=COUNTIFS( rawv3!$F:$F, "<>Ongoing", INDIRECT("rawv3!" & ADDRESS(1, MATCH($D$2 & " " & Q$3, rawv3!$1:$1, 0), 4) & ":" & ADDRESS(1048576, MATCH($D$2 & " " & Q$3, rawv3!$1:$1, 0), 4)), Q$4, INDIRECT("rawv3!" & ADDRESS(1, MATCH($B$4 & " " & $B30, rawv3!$1:$1, 0), 4) & ":" & ADDRESS(1048576, MATCH($B$4 & " " & $B30, rawv3!$1:$1, 0), 4)), $C32 )} -> 1415 | R32: {=COUNTIFS( rawv3!$F:$F, "<>Ongoing", INDIRECT("rawv3!" & ADDRESS(1, MATCH($D$2 & " " & Q$3, rawv3!$1:$1, 0), 4) & ":" & ADDRESS(1048576, MATCH($D$2 & " " & Q$3, rawv3!$1:$1, 0), 4)), R$4, INDIRECT("rawv3!" & ADDRESS(1, MATCH($B$4 & " " & $B30, rawv3!$1:$1, 0), 4) & ":" & ADDRESS(1048576, MATCH($B$4 & " " & $B30, rawv3!$1:$1, 0), 4)), $C32 )} -> 562 | T32: {=COUNTIFS( rawv3!$F:$F, "<>Ongoing", INDIRECT("rawv3!" & ADDRESS(1, MATCH($D$2 & " " & T$3, rawv3!$1:$1, 0), 4) & ":" & ADDRESS(1048576, MATCH($D$2 & " " & T$3, rawv3!$1:$1, 0), 4)), T$4, INDIRECT("rawv3!" & ADDRESS(1, MATCH($B$4 & " " & $B30, rawv3!$1:$1, 0), 4) & ":" & ADDRESS(1048576, MATCH($B$4 & " " & $B30, rawv3!$1:$1, 0), 4)), $C32 )} -> 1460 | U32: {=COUNTIFS( rawv3!$F:$F, "<>Ongoing", INDIRECT("rawv3!" & ADDRESS(1, MATCH($D$2 & " " & T$3, rawv3!$1:$1, 0), 4) & ":" & ADDRESS(1048576, MATCH($D$2 & " " & T$3, rawv3!$1:$1, 0), 4)), U$4, INDIRECT("rawv3!" & ADDRESS(1, MATCH($B$4 & " " & $B30, rawv3!$1:$1, 0), 4) & ":" & ADDRESS(1048576, MATCH($B$4 & " " & $B30, rawv3!$1:$1, 0), 4)), $C32 )} -> 517 | W32: {=COUNTIFS( rawv3!$F:$F, "<>Ongoing", INDIRECT("rawv3!" & ADDRESS(1, MATCH($D$2 & " " & W$3, rawv3!$1:$1, 0), 4) & ":" & ADDRESS(1048576, MATCH($D$2 & " " & W$3, rawv3!$1:$1, 0), 4)), W$4, INDIRECT("rawv3!" & ADDRESS(1, MATCH($B$4 & " " & $B30, rawv3!$1:$1, 0), 4) & ":" & ADDRESS(1048576, MATCH($B$4 & " " & $B30, rawv3!$1:$1, 0), 4)), $C32 )} -> 861 | X32: {=COUNTIFS( rawv3!$F:$F, "<>Ongoing", INDIRECT("rawv3!" & ADDRESS(1, MATCH($D$2 & " " & W$3, rawv3!$1:$1, 0), 4) & ":" & ADDRESS(1048576, MATCH($D$2 & " " & W$3, rawv3!$1:$1, 0), 4)), X$4, INDIRECT("rawv3!" & ADDRESS(1, MATCH($B$4 & " " & $B30, rawv3!$1:$1, 0), 4) & ":" & ADDRESS(1048576, MATCH($B$4 & " " & $B30, rawv3!$1:$1, 0), 4)), $C32 )} -> 1117 | Z32: {=COUNTIFS( rawv3!$F:$F, "<>Ongoing", INDIRECT("rawv3!" & ADDRESS(1, MATCH($B$4 & " " & $B30, rawv3!$1:$1, 0), 4) & ":" & ADDRESS(1048576, MATCH($B$4 & " " & $B30, rawv3!$1:$1, 0), 4)), $C32)} -> 1978
D33: F90D % | E33: {=COUNTIFS( rawv3!$F:$F, "Success", INDIRECT("rawv3!" & ADDRESS(1, MATCH($D$2 & " " & E$3, rawv3!$1:$1, 0), 4) & ":" & ADDRESS(1048576, MATCH($D$2 & " " & E$3, rawv3!$1:$1, 0), 4)), E$4, INDIRECT("rawv3!" & ADDRESS(1, MATCH($B$4 & " " & $B30, rawv3!$1:$1, 0), 4) & ":" & ADDRESS(1048576, MATCH($B$4 & " " & $B30, rawv3!$1:$1, 0), 4)), $C32 )/E32} -> 0.78326613 | F33: {=COUNTIFS( rawv3!$F:$F, "Success", INDIRECT("rawv3!" & ADDRESS(1, MATCH($D$2 & " " & E$3, rawv3!$1:$1, 0), 4) & ":" & ADDRESS(1048576, MATCH($D$2 & " " & E$3, rawv3!$1:$1, 0), 4)), F$4, INDIRECT("rawv3!" & ADDRESS(1, MATCH($B$4 & " " & $B30, rawv3!$1:$1, 0), 4) & ":" & ADDRESS(1048576, MATCH($B$4 & " " & $B30, rawv3!$1:$1, 0), 4)), $C32 )/F32} -> 0.79429735 | H33: {=COUNTIFS( rawv3!$F:$F, "Success", INDIRECT("rawv3!" & ADDRESS(1, MATCH($D$2 & " " & H$3, rawv3!$1:$1, 0), 4) & ":" & ADDRESS(1048576, MATCH($D$2 & " " & H$3, rawv3!$1:$1, 0), 4)), H$4, INDIRECT("rawv3!" & ADDRESS(1, MATCH($B$4 & " " & $B30, rawv3!$1:$1, 0), 4) & ":" & ADDRESS(1048576, MATCH($B$4 & " " & $B30, rawv3!$1:$1, 0), 4)), $C32 )/H32} -> 0.80377668 | I33: {=COUNTIFS( rawv3!$F:$F, "Success", INDIRECT("rawv3!" & ADDRESS(1, MATCH($D$2 & " " & H$3, rawv3!$1:$1, 0), 4) & ":" & ADDRESS(1048576, MATCH($D$2 & " " & H$3, rawv3!$1:$1, 0), 4)), I$4, INDIRECT("rawv3!" & ADDRESS(1, MATCH($B$4 & " " & $B30, rawv3!$1:$1, 0), 4) & ":" & ADDRESS(1048576, MATCH($B$4 & " " & $B30, rawv3!$1:$1, 0), 4)), $C32 )/I32} -> 0.76578947 | K33: {=COUNTIFS( rawv3!$F:$F, "Success", INDIRECT("rawv3!" & ADDRESS(1, MATCH($D$2 & " " & K$3, rawv3!$1:$1, 0), 4) & ":" & ADDRESS(1048576, MATCH($D$2 & " " & K$3, rawv3!$1:$1, 0), 4)), K$4, INDIRECT("rawv3!" & ADDRESS(1, MATCH($B$4 & " " & $B30, rawv3!$1:$1, 0), 4) & ":" & ADDRESS(1048576, MATCH($B$4 & " " & $B30, rawv3!$1:$1, 0), 4)), $C32 )/K32} -> 0.78243105 | L33: {=COUNTIFS( rawv3!$F:$F, "Success", INDIRECT("rawv3!" & ADDRESS(1, MATCH($D$2 & " " & K$3, rawv3!$1:$1, 0), 4) & ":" & ADDRESS(1048576, MATCH($D$2 & " " & K$3, rawv3!$1:$1, 0), 4)), L$4, INDIRECT("rawv3!" & ADDRESS(1, MATCH($B$4 & " " & $B30, rawv3!$1:$1, 0), 4) & ":" & ADDRESS(1048576, MATCH($B$4 & " " & $B30, rawv3!$1:$1, 0), 4)), $C32 )/L32} -> 0.7957958 | N33: {=COUNTIFS( rawv3!$F:$F, "Success", INDIRECT("rawv3!" & ADDRESS(1, MATCH($D$2 & " " & N$3, rawv3!$1:$1, 0), 4) & ":" & ADDRESS(1048576, MATCH($D$2 & " " & N$3, rawv3!$1:$1, 0), 4)), N$4, INDIRECT("rawv3!" & ADDRESS(1, MATCH($B$4 & " " & $B30, rawv3!$1:$1, 0), 4) & ":" & ADDRESS(1048576, MATCH($B$4 & " " & $B30, rawv3!$1:$1, 0), 4)), $C32 )/N32} -> 0.79982818 | O33: {=COUNTIFS( rawv3!$F:$F, "Success", INDIRECT("rawv3!" & ADDRESS(1, MATCH($D$2 & " " & N$3, rawv3!$1:$1, 0), 4) & ":" & ADDRESS(1048576, MATCH($D$2 & " " & N$3, rawv3!$1:$1, 0), 4)), O$4, INDIRECT("rawv3!" & ADDRESS(1, MATCH($B$4 & " " & $B30, rawv3!$1:$1, 0), 4) & ":" & ADDRESS(1048576, MATCH($B$4 & " " & $B30, rawv3!$1:$1, 0), 4)), $C32 )/O32} -> 0.77395577 | Q33: {=COUNTIFS( rawv3!$F:$F, "Success", INDIRECT("rawv3!" & ADDRESS(1, MATCH($D$2 & " " & Q$3, rawv3!$1:$1, 0), 4) & ":" & ADDRESS(1048576, MATCH($D$2 & " " & Q$3, rawv3!$1:$1, 0), 4)), Q$4, INDIRECT("rawv3!" & ADDRESS(1, MATCH($B$4 & " " & $B30, rawv3!$1:$1, 0), 4) & ":" & ADDRESS(1048576, MATCH($B$4 & " " & $B30, rawv3!$1:$1, 0), 4)), $C32 )/Q32} -> 0.79646643 | R33: {=COUNTIFS( rawv3!$F:$F, "Success", INDIRECT("rawv3!" & ADDRESS(1, MATCH($D$2 & " " & Q$3, rawv3!$1:$1, 0), 4) & ":" & ADDRESS(1048576, MATCH($D$2 & " " & Q$3, rawv3!$1:$1, 0), 4)), R$4, INDIRECT("rawv3!" & ADDRESS(1, MATCH($B$4 & " " & $B30, rawv3!$1:$1, 0), 4) & ":" & ADDRESS(1048576, MATCH($B$4 & " " & $B30, rawv3!$1:$1, 0), 4)), $C32 )/R32} -> 0.77046263 | T33: {=COUNTIFS( rawv3!$F:$F, "Success", INDIRECT("rawv3!" & ADDRESS(1, MATCH($D$2 & " " & T$3, rawv3!$1:$1, 0), 4) & ":" & ADDRESS(1048576, MATCH($D$2 & " " & T$3, rawv3!$1:$1, 0), 4)), T$4, INDIRECT("rawv3!" & ADDRESS(1, MATCH($B$4 & " " & $B30, rawv3!$1:$1, 0), 4) & ":" & ADDRESS(1048576, MATCH($B$4 & " " & $B30, rawv3!$1:$1, 0), 4)), $C32 )/T32} -> 0.79109589 | U33: {=COUNTIFS( rawv3!$F:$F, "Success", INDIRECT("rawv3!" & ADDRESS(1, MATCH($D$2 & " " & T$3, rawv3!$1:$1, 0), 4) & ":" & ADDRESS(1048576, MATCH($D$2 & " " & T$3, rawv3!$1:$1, 0), 4)), U$4, INDIRECT("rawv3!" & ADDRESS(1, MATCH($B$4 & " " & $B30, rawv3!$1:$1, 0), 4) & ":" & ADDRESS(1048576, MATCH($B$4 & " " & $B30, rawv3!$1:$1, 0), 4)), $C32 )/U32} -> 0.78336557 | W33: {=COUNTIFS( rawv3!$F:$F, "Success", INDIRECT("rawv3!" & ADDRESS(1, MATCH($D$2 & " " & W$3, rawv3!$1:$1, 0), 4) & ":" & ADDRESS(1048576, MATCH($D$2 & " " & W$3, rawv3!$1:$1, 0), 4)), W$4, INDIRECT("rawv3!" & ADDRESS(1, MATCH($B$4 & " " & $B30, rawv3!$1:$1, 0), 4) & ":" & ADDRESS(1048576, MATCH($B$4 & " " & $B30, rawv3!$1:$1, 0), 4)), $C32 )/W32} -> 0.77119628 | X33: {=COUNTIFS( rawv3!$F:$F, "Success", INDIRECT("rawv3!" & ADDRESS(1, MATCH($D$2 & " " & W$3, rawv3!$1:$1, 0), 4) & ":" & ADDRESS(1048576, MATCH($D$2 & " " & W$3, rawv3!$1:$1, 0), 4)), X$4, INDIRECT("rawv3!" & ADDRESS(1, MATCH($B$4 & " " & $B30, rawv3!$1:$1, 0), 4) & ":" & ADDRESS(1048576, MATCH($B$4 & " " & $B30, rawv3!$1:$1, 0), 4)), $C32 )/X32} -> 0.80304387 | Z33: {=COUNTIFS( rawv3!$F:$F, "Success", INDIRECT("rawv3!" & ADDRESS(1, MATCH($B$4 & " " & $B30, rawv3!$1:$1, 0), 4) & ":" & ADDRESS(1048576, MATCH($B$4 & " " & $B30, rawv3!$1:$1, 0), 4)), $C32)/Z32} -> 0.78918099 | AA33: {=COUNTIFS( rawv3!$F:$F, "Success", INDIRECT("rawv3!" & ADDRESS(1, MATCH($B$4 & " " & $B30, rawv3!$1:$1, 0), 4) & ":" & ADDRESS(1048576, MATCH($B$4 & " " & $B30, rawv3!$1:$1, 0), 4)), $C32)} -> 1561
B35: Priority | C35: Speed of execution | D35: # | E35: {=COUNTIFS( rawv3!$F:$F, "<>Ongoing", INDIRECT("rawv3!" & ADDRESS(1, MATCH($D$2 & " " & E$3, rawv3!$1:$1, 0), 4) & ":" & ADDRESS(1048576, MATCH($D$2 & " " & E$3, rawv3!$1:$1, 0), 4)), E$4, INDIRECT("rawv3!" & ADDRESS(1, MATCH($B$4 & " " & $B35, rawv3!$1:$1, 0), 4) & ":" & ADDRESS(1048576, MATCH($B$4 & " " & $B35, rawv3!$1:$1, 0), 4)), $C35 )} -> 48 | F35: {=COUNTIFS( rawv3!$F:$F, "<>Ongoing", INDIRECT("rawv3!" & ADDRESS(1, MATCH($D$2 & " " & E$3, rawv3!$1:$1, 0), 4) & ":" & ADDRESS(1048576, MATCH($D$2 & " " & E$3, rawv3!$1:$1, 0), 4)), F$4, INDIRECT("rawv3!" & ADDRESS(1, MATCH($B$4 & " " & $B35, rawv3!$1:$1, 0), 4) & ":" & ADDRESS(1048576, MATCH($B$4 & " " & $B35, rawv3!$1:$1, 0), 4)), $C35 )} -> 60 | H35: {=COUNTIFS( rawv3!$F:$F, "<>Ongoing", INDIRECT("rawv3!" & ADDRESS(1, MATCH($D$2 & " " & H$3, rawv3!$1:$1, 0), 4) & ":" & ADDRESS(1048576, MATCH($D$2 & " " & H$3, rawv3!$1:$1, 0), 4)), H$4, INDIRECT("rawv3!" & ADDRESS(1, MATCH($B$4 & " " & $B35, rawv3!$1:$1, 0), 4) & ":" & ADDRESS(1048576, MATCH($B$4 & " " & $B35, rawv3!$1:$1, 0), 4)), $C35 )} -> 73 | I35: {=COUNTIFS( rawv3!$F:$F, "<>Ongoing", INDIRECT("rawv3!" & ADDRESS(1, MATCH($D$2 & " " & H$3, rawv3!$1:$1, 0), 4) & ":" & ADDRESS(1048576, MATCH($D$2 & " " & H$3, rawv3!$1:$1, 0), 4)), I$4, INDIRECT("rawv3!" & ADDRESS(1, MATCH($B$4 & " " & $B35, rawv3!$1:$1, 0), 4) & ":" & ADDRESS(1048576, MATCH($B$4 & " " & $B35, rawv3!$1:$1, 0), 4)), $C35 )} -> 35 | K35: {=COUNTIFS( rawv3!$F:$F, "<>Ongoing", INDIRECT("rawv3!" & ADDRESS(1, MATCH($D$2 & " " & K$3, rawv3!$1:$1, 0), 4) & ":" & ADDRESS(1048576, MATCH($D$2 & " " & K$3, rawv3!$1:$1, 0), 4)), K$4, INDIRECT("rawv3!" & ADDRESS(1, MATCH($B$4 & " " & $B35, rawv3!$1:$1, 0), 4) & ":" & ADDRESS(1048576, MATCH($B$4 & " " & $B35, rawv3!$1:$1, 0), 4)), $C35 )} -> 66 | L35: {=COUNTIFS( rawv3!$F:$F, "<>Ongoing", INDIRECT("rawv3!" & ADDRESS(1, MATCH($D$2 & " " & K$3, rawv3!$1:$1, 0), 4) & ":" & ADDRESS(1048576, MATCH($D$2 & " " & K$3, rawv3!$1:$1, 0), 4)), L$4, INDIRECT("rawv3!" & ADDRESS(1, MATCH($B$4 & " " & $B35, rawv3!$1:$1, 0), 4) & ":" & ADDRESS(1048576, MATCH($B$4 & " " & $B35, rawv3!$1:$1, 0), 4)), $C35 )} -> 42 | N35: {=COUNTIFS( rawv3!$F:$F, "<>Ongoing", INDIRECT("rawv3!" & ADDRESS(1, MATCH($D$2 & " " & N$3, rawv3!$1:$1, 0), 4) & ":" & ADDRESS(1048576, MATCH($D$2 & " " & N$3, rawv3!$1:$1, 0), 4)), N$4, INDIRECT("rawv3!" & ADDRESS(1, MATCH($B$4 & " " & $B35, rawv3!$1:$1, 0), 4) & ":" & ADDRESS(1048576, MATCH($B$4 & " " & $B35, rawv3!$1:$1, 0), 4)), $C35 )} -> 67 | O35: {=COUNTIFS( rawv3!$F:$F, "<>Ongoing", INDIRECT("rawv3!" & ADDRESS(1, MATCH($D$2 & " " & N$3, rawv3!$1:$1, 0), 4) & ":" & ADDRESS(1048576, MATCH($D$2 & " " & N$3, rawv3!$1:$1, 0), 4)), O$4, INDIRECT("rawv3!" & ADDRESS(1, MATCH($B$4 & " " & $B35, rawv3!$1:$1, 0), 4) & ":" & ADDRESS(1048576, MATCH($B$4 & " " & $B35, rawv3!$1:$1, 0), 4)), $C35 )} -> 41 | Q35: {=COUNTIFS( rawv3!$F:$F, "<>Ongoing", INDIRECT("rawv3!" & ADDRESS(1, MATCH($D$2 & " " & Q$3, rawv3!$1:$1, 0), 4) & ":" & ADDRESS(1048576, MATCH($D$2 & " " & Q$3, rawv3!$1:$1, 0), 4)), Q$4, INDIRECT("rawv3!" & ADDRESS(1, MATCH($B$4 & " " & $B35, rawv3!$1:$1, 0), 4) & ":" & ADDRESS(1048576, MATCH($B$4 & " " & $B35, rawv3!$1:$1, 0), 4)), $C35 )} -> 77 | R35: {=COUNTIFS( rawv3!$F:$F, "<>Ongoing", INDIRECT("rawv3!" & ADDRESS(1, MATCH($D$2 & " " & Q$3, rawv3!$1:$1, 0), 4) & ":" & ADDRESS(1048576, MATCH($D$2 & " " & Q$3, rawv3!$1:$1, 0), 4)), R$4, INDIRECT("rawv3!" & ADDRESS(1, MATCH($B$4 & " " & $B35, rawv3!$1:$1, 0), 4) & ":" & ADDRESS(1048576, MATCH($B$4 & " " & $B35, rawv3!$1:$1, 0), 4)), $C35 )} -> 31 | T35: {=COUNTIFS( rawv3!$F:$F, "<>Ongoing", INDIRECT("rawv3!" & ADDRESS(1, MATCH($D$2 & " " & T$3, rawv3!$1:$1, 0), 4) & ":" & ADDRESS(1048576, MATCH($D$2 & " " & T$3, rawv3!$1:$1, 0), 4)), T$4, INDIRECT("rawv3!" & ADDRESS(1, MATCH($B$4 & " " & $B35, rawv3!$1:$1, 0), 4) & ":" & ADDRESS(1048576, MATCH($B$4 & " " & $B35, rawv3!$1:$1, 0), 4)), $C35 )} -> 81 | U35: {=COUNTIFS( rawv3!$F:$F, "<>Ongoing", INDIRECT("rawv3!" & ADDRESS(1, MATCH($D$2 & " " & T$3, rawv3!$1:$1, 0), 4) & ":" & ADDRESS(1048576, MATCH($D$2 & " " & T$3, rawv3!$1:$1, 0), 4)), U$4, INDIRECT("rawv3!" & ADDRESS(1, MATCH($B$4 & " " & $B35, rawv3!$1:$1, 0), 4) & ":" & ADDRESS(1048576, MATCH($B$4 & " " & $B35, rawv3!$1:$1, 0), 4)), $C35 )} -> 27 | W35: {=COUNTIFS( rawv3!$F:$F, "<>Ongoing", INDIRECT("rawv3!" & ADDRESS(1, MATCH($D$2 & " " & W$3, rawv3!$1:$1, 0), 4) & ":" & ADDRESS(1048576, MATCH($D$2 & " " & W$3, rawv3!$1:$1, 0), 4)), W$4, INDIRECT("rawv3!" & ADDRESS(1, MATCH($B$4 & " " & $B35, rawv3!$1:$1, 0), 4) & ":" & ADDRESS(1048576, MATCH($B$4 & " " & $B35, rawv3!$1:$1, 0), 4)), $C35 )} -> 69 | X35: {=COUNTIFS( rawv3!$F:$F, "<>Ongoing", INDIRECT("rawv3!" & ADDRESS(1, MATCH($D$2 & " " & W$3, rawv3!$1:$1, 0), 4) & ":" & ADDRESS(1048576, MATCH($D$2 & " " & W$3, rawv3!$1:$1, 0), 4)), X$4, INDIRECT("rawv3!" & ADDRESS(1, MATCH($B$4 & " " & $B35, rawv3!$1:$1, 0), 4) & ":" & ADDRESS(1048576, MATCH($B$4 & " " & $B35, rawv3!$1:$1, 0), 4)), $C35 )} -> 39 | Z35: {=COUNTIFS( rawv3!$F:$F, "<>Ongoing", INDIRECT("rawv3!" & ADDRESS(1, MATCH($B$4 & " " & $B35, rawv3!$1:$1, 0), 4) & ":" & ADDRESS(1048576, MATCH($B$4 & " " & $B35, rawv3!$1:$1, 0), 4)), $C35)} -> 108
D36: F90D % | E36: {=COUNTIFS( rawv3!$F:$F, "Success", INDIRECT("rawv3!" & ADDRESS(1, MATCH($D$2 & " " & E$3, rawv3!$1:$1, 0), 4) & ":" & ADDRESS(1048576, MATCH($D$2 & " " & E$3, rawv3!$1:$1, 0), 4)), E$4, INDIRECT("rawv3!" & ADDRESS(1, MATCH($B$4 & " " & $B35, rawv3!$1:$1, 0), 4) & ":" & ADDRESS(1048576, MATCH($B$4 & " " & $B35, rawv3!$1:$1, 0), 4)), $C35 )/E35} -> 0.79166667 | F36: {=COUNTIFS( rawv3!$F:$F, "Success", INDIRECT("rawv3!" & ADDRESS(1, MATCH($D$2 & " " & E$3, rawv3!$1:$1, 0), 4) & ":" & ADDRESS(1048576, MATCH($D$2 & " " & E$3, rawv3!$1:$1, 0), 4)), F$4, INDIRECT("rawv3!" & ADDRESS(1, MATCH($B$4 & " " & $B35, rawv3!$1:$1, 0), 4) & ":" & ADDRESS(1048576, MATCH($B$4 & " " & $B35, rawv3!$1:$1, 0), 4)), $C35 )/F35} -> 0.76666667 | H36: {=COUNTIFS( rawv3!$F:$F, "Success", INDIRECT("rawv3!" & ADDRESS(1, MATCH($D$2 & " " & H$3, rawv3!$1:$1, 0), 4) & ":" & ADDRESS(1048576, MATCH($D$2 & " " & H$3, rawv3!$1:$1, 0), 4)), H$4, INDIRECT("rawv3!" & ADDRESS(1, MATCH($B$4 & " " & $B35, rawv3!$1:$1, 0), 4) & ":" & ADDRESS(1048576, MATCH($B$4 & " " & $B35, rawv3!$1:$1, 0), 4)), $C35 )/H35} -> 0.76712329 | I36: {=COUNTIFS( rawv3!$F:$F, "Success", INDIRECT("rawv3!" & ADDRESS(1, MATCH($D$2 & " " & H$3, rawv3!$1:$1, 0), 4) & ":" & ADDRESS(1048576, MATCH($D$2 & " " & H$3, rawv3!$1:$1, 0), 4)), I$4, INDIRECT("rawv3!" & ADDRESS(1, MATCH($B$4 & " " & $B35, rawv3!$1:$1, 0), 4) & ":" & ADDRESS(1048576, MATCH($B$4 & " " & $B35, rawv3!$1:$1, 0), 4)), $C35 )/I35} -> 0.8 | K36: {=COUNTIFS( rawv3!$F:$F, "Success", INDIRECT("rawv3!" & ADDRESS(1, MATCH($D$2 & " " & K$3, rawv3!$1:$1, 0), 4) & ":" & ADDRESS(1048576, MATCH($D$2 & " " & K$3, rawv3!$1:$1, 0), 4)), K$4, INDIRECT("rawv3!" & ADDRESS(1, MATCH($B$4 & " " & $B35, rawv3!$1:$1, 0), 4) & ":" & ADDRESS(1048576, MATCH($B$4 & " " & $B35, rawv3!$1:$1, 0), 4)), $C35 )/K35} -> 0.75757576 | L36: {=COUNTIFS( rawv3!$F:$F, "Success", INDIRECT("rawv3!" & ADDRESS(1, MATCH($D$2 & " " & K$3, rawv3!$1:$1, 0), 4) & ":" & ADDRESS(1048576, MATCH($D$2 & " " & K$3, rawv3!$1:$1, 0), 4)), L$4, INDIRECT("rawv3!" & ADDRESS(1, MATCH($B$4 & " " & $B35, rawv3!$1:$1, 0), 4) & ":" & ADDRESS(1048576, MATCH($B$4 & " " & $B35, rawv3!$1:$1, 0), 4)), $C35 )/L35} -> 0.80952381 | N36: {=COUNTIFS( rawv3!$F:$F, "Success", INDIRECT("rawv3!" & ADDRESS(1, MATCH($D$2 & " " & N$3, rawv3!$1:$1, 0), 4) & ":" & ADDRESS(1048576, MATCH($D$2 & " " & N$3, rawv3!$1:$1, 0), 4)), N$4, INDIRECT("rawv3!" & ADDRESS(1, MATCH($B$4 & " " & $B35, rawv3!$1:$1, 0), 4) & ":" & ADDRESS(1048576, MATCH($B$4 & " " & $B35, rawv3!$1:$1, 0), 4)), $C35 )/N35} -> 0.74626866 | O36: {=COUNTIFS( rawv3!$F:$F, "Success", INDIRECT("rawv3!" & ADDRESS(1, MATCH($D$2 & " " & N$3, rawv3!$1:$1, 0), 4) & ":" & ADDRESS(1048576, MATCH($D$2 & " " & N$3, rawv3!$1:$1, 0), 4)), O$4, INDIRECT("rawv3!" & ADDRESS(1, MATCH($B$4 & " " & $B35, rawv3!$1:$1, 0), 4) & ":" & ADDRESS(1048576, MATCH($B$4 & " " & $B35, rawv3!$1:$1, 0), 4)), $C35 )/O35} -> 0.82926829 | Q36: {=COUNTIFS( rawv3!$F:$F, "Success", INDIRECT("rawv3!" & ADDRESS(1, MATCH($D$2 & " " & Q$3, rawv3!$1:$1, 0), 4) & ":" & ADDRESS(1048576, MATCH($D$2 & " " & Q$3, rawv3!$1:$1, 0), 4)), Q$4, INDIRECT("rawv3!" & ADDRESS(1, MATCH($B$4 & " " & $B35, rawv3!$1:$1, 0), 4) & ":" & ADDRESS(1048576, MATCH($B$4 & " " & $B35, rawv3!$1:$1, 0), 4)), $C35 )/Q35} -> 0.75324675 | R36: {=COUNTIFS( rawv3!$F:$F, "Success", INDIRECT("rawv3!" & ADDRESS(1, MATCH($D$2 & " " & Q$3, rawv3!$1:$1, 0), 4) & ":" & ADDRESS(1048576, MATCH($D$2 & " " & Q$3, rawv3!$1:$1, 0), 4)), R$4, INDIRECT("rawv3!" & ADDRESS(1, MATCH($B$4 & " " & $B35, rawv3!$1:$1, 0), 4) & ":" & ADDRESS(1048576, MATCH($B$4 & " " & $B35, rawv3!$1:$1, 0), 4)), $C35 )/R35} -> 0.83870968 | T36: {=COUNTIFS( rawv3!$F:$F, "Success", INDIRECT("rawv3!" & ADDRESS(1, MATCH($D$2 & " " & T$3, rawv3!$1:$1, 0), 4) & ":" & ADDRESS(1048576, MATCH($D$2 & " " & T$3, rawv3!$1:$1, 0), 4)), T$4, INDIRECT("rawv3!" & ADDRESS(1, MATCH($B$4 & " " & $B35, rawv3!$1:$1, 0), 4) & ":" & ADDRESS(1048576, MATCH($B$4 & " " & $B35, rawv3!$1:$1, 0), 4)), $C35 )/T35} -> 0.7654321 | U36: {=COUNTIFS( rawv3!$F:$F, "Success", INDIRECT("rawv3!" & ADDRESS(1, MATCH($D$2 & " " & T$3, rawv3!$1:$1, 0), 4) & ":" & ADDRESS(1048576, MATCH($D$2 & " " & T$3, rawv3!$1:$1, 0), 4)), U$4, INDIRECT("rawv3!" & ADDRESS(1, MATCH($B$4 & " " & $B35, rawv3!$1:$1, 0), 4) & ":" & ADDRESS(1048576, MATCH($B$4 & " " & $B35, rawv3!$1:$1, 0), 4)), $C35 )/U35} -> 0.81481481 | W36: {=COUNTIFS( rawv3!$F:$F, "Success", INDIRECT("rawv3!" & ADDRESS(1, MATCH($D$2 & " " & W$3, rawv3!$1:$1, 0), 4) & ":" & ADDRESS(1048576, MATCH($D$2 & " " & W$3, rawv3!$1:$1, 0), 4)), W$4, INDIRECT("rawv3!" & ADDRESS(1, MATCH($B$4 & " " & $B35, rawv3!$1:$1, 0), 4) & ":" & ADDRESS(1048576, MATCH($B$4 & " " & $B35, rawv3!$1:$1, 0), 4)), $C35 )/W35} -> 0.75362319 | X36: {=COUNTIFS( rawv3!$F:$F, "Success", INDIRECT("rawv3!" & ADDRESS(1, MATCH($D$2 & " " & W$3, rawv3!$1:$1, 0), 4) & ":" & ADDRESS(1048576, MATCH($D$2 & " " & W$3, rawv3!$1:$1, 0), 4)), X$4, INDIRECT("rawv3!" & ADDRESS(1, MATCH($B$4 & " " & $B35, rawv3!$1:$1, 0), 4) & ":" & ADDRESS(1048576, MATCH($B$4 & " " & $B35, rawv3!$1:$1, 0), 4)), $C35 )/X35} -> 0.82051282 | Z36: {=COUNTIFS( rawv3!$F:$F, "Success", INDIRECT("rawv3!" & ADDRESS(1, MATCH($B$4 & " " & $B35, rawv3!$1:$1, 0), 4) & ":" & ADDRESS(1048576, MATCH($B$4 & " " & $B35, rawv3!$1:$1, 0), 4)), $C35)/Z35} -> 0.77777778 | AA36: {=COUNTIFS( rawv3!$F:$F, "Success", INDIRECT("rawv3!" & ADDRESS(1, MATCH($B$4 & " " & $B35, rawv3!$1:$1, 0), 4) & ":" & ADDRESS(1048576, MATCH($B$4 & " " & $B35, rawv3!$1:$1, 0), 4)), $C35)} -> 84
C37: Accuracy of decisions | D37: # | E37: {=COUNTIFS( rawv3!$F:$F, "<>Ongoing", INDIRECT("rawv3!" & ADDRESS(1, MATCH($D$2 & " " & E$3, rawv3!$1:$1, 0), 4) & ":" & ADDRESS(1048576, MATCH($D$2 & " " & E$3, rawv3!$1:$1, 0), 4)), E$4, INDIRECT("rawv3!" & ADDRESS(1, MATCH($B$4 & " " & $B35, rawv3!$1:$1, 0), 4) & ":" & ADDRESS(1048576, MATCH($B$4 & " " & $B35, rawv3!$1:$1, 0), 4)), $C37 )} -> 1235 | F37: {=COUNTIFS( rawv3!$F:$F, "<>Ongoing", INDIRECT("rawv3!" & ADDRESS(1, MATCH($D$2 & " " & E$3, rawv3!$1:$1, 0), 4) & ":" & ADDRESS(1048576, MATCH($D$2 & " " & E$3, rawv3!$1:$1, 0), 4)), F$4, INDIRECT("rawv3!" & ADDRESS(1, MATCH($B$4 & " " & $B35, rawv3!$1:$1, 0), 4) & ":" & ADDRESS(1048576, MATCH($B$4 & " " & $B35, rawv3!$1:$1, 0), 4)), $C37 )} -> 1190 | H37: {=COUNTIFS( rawv3!$F:$F, "<>Ongoing", INDIRECT("rawv3!" & ADDRESS(1, MATCH($D$2 & " " & H$3, rawv3!$1:$1, 0), 4) & ":" & ADDRESS(1048576, MATCH($D$2 & " " & H$3, rawv3!$1:$1, 0), 4)), H$4, INDIRECT("rawv3!" & ADDRESS(1, MATCH($B$4 & " " & $B35, rawv3!$1:$1, 0), 4) & ":" & ADDRESS(1048576, MATCH($B$4 & " " & $B35, rawv3!$1:$1, 0), 4)), $C37 )} -> 1471 | I37: {=COUNTIFS( rawv3!$F:$F, "<>Ongoing", INDIRECT("rawv3!" & ADDRESS(1, MATCH($D$2 & " " & H$3, rawv3!$1:$1, 0), 4) & ":" & ADDRESS(1048576, MATCH($D$2 & " " & H$3, rawv3!$1:$1, 0), 4)), I$4, INDIRECT("rawv3!" & ADDRESS(1, MATCH($B$4 & " " & $B35, rawv3!$1:$1, 0), 4) & ":" & ADDRESS(1048576, MATCH($B$4 & " " & $B35, rawv3!$1:$1, 0), 4)), $C37 )} -> 959 | K37: {=COUNTIFS( rawv3!$F:$F, "<>Ongoing", INDIRECT("rawv3!" & ADDRESS(1, MATCH($D$2 & " " & K$3, rawv3!$1:$1, 0), 4) & ":" & ADDRESS(1048576, MATCH($D$2 & " " & K$3, rawv3!$1:$1, 0), 4)), K$4, INDIRECT("rawv3!" & ADDRESS(1, MATCH($B$4 & " " & $B35, rawv3!$1:$1, 0), 4) & ":" & ADDRESS(1048576, MATCH($B$4 & " " & $B35, rawv3!$1:$1, 0), 4)), $C37 )} -> 1156 | L37: {=COUNTIFS( rawv3!$F:$F, "<>Ongoing", INDIRECT("rawv3!" & ADDRESS(1, MATCH($D$2 & " " & K$3, rawv3!$1:$1, 0), 4) & ":" & ADDRESS(1048576, MATCH($D$2 & " " & K$3, rawv3!$1:$1, 0), 4)), L$4, INDIRECT("rawv3!" & ADDRESS(1, MATCH($B$4 & " " & $B35, rawv3!$1:$1, 0), 4) & ":" & ADDRESS(1048576, MATCH($B$4 & " " & $B35, rawv3!$1:$1, 0), 4)), $C37 )} -> 1273 | N37: {=COUNTIFS( rawv3!$F:$F, "<>Ongoing", INDIRECT("rawv3!" & ADDRESS(1, MATCH($D$2 & " " & N$3, rawv3!$1:$1, 0), 4) & ":" & ADDRESS(1048576, MATCH($D$2 & " " & N$3, rawv3!$1:$1, 0), 4)), N$4, INDIRECT("rawv3!" & ADDRESS(1, MATCH($B$4 & " " & $B35, rawv3!$1:$1, 0), 4) & ":" & ADDRESS(1048576, MATCH($B$4 & " " & $B35, rawv3!$1:$1, 0), 4)), $C37 )} -> 1454 | O37: {=COUNTIFS( rawv3!$F:$F, "<>Ongoing", INDIRECT("rawv3!" & ADDRESS(1, MATCH($D$2 & " " & N$3, rawv3!$1:$1, 0), 4) & ":" & ADDRESS(1048576, MATCH($D$2 & " " & N$3, rawv3!$1:$1, 0), 4)), O$4, INDIRECT("rawv3!" & ADDRESS(1, MATCH($B$4 & " " & $B35, rawv3!$1:$1, 0), 4) & ":" & ADDRESS(1048576, MATCH($B$4 & " " & $B35, rawv3!$1:$1, 0), 4)), $C37 )} -> 976 | Q37: {=COUNTIFS( rawv3!$F:$F, "<>Ongoing", INDIRECT("rawv3!" & ADDRESS(1, MATCH($D$2 & " " & Q$3, rawv3!$1:$1, 0), 4) & ":" & ADDRESS(1048576, MATCH($D$2 & " " & Q$3, rawv3!$1:$1, 0), 4)), Q$4, INDIRECT("rawv3!" & ADDRESS(1, MATCH($B$4 & " " & $B35, rawv3!$1:$1, 0), 4) & ":" & ADDRESS(1048576, MATCH($B$4 & " " & $B35, rawv3!$1:$1, 0), 4)), $C37 )} -> 1763 | R37: {=COUNTIFS( rawv3!$F:$F, "<>Ongoing", INDIRECT("rawv3!" & ADDRESS(1, MATCH($D$2 & " " & Q$3, rawv3!$1:$1, 0), 4) & ":" & ADDRESS(1048576, MATCH($D$2 & " " & Q$3, rawv3!$1:$1, 0), 4)), R$4, INDIRECT("rawv3!" & ADDRESS(1, MATCH($B$4 & " " & $B35, rawv3!$1:$1, 0), 4) & ":" & ADDRESS(1048576, MATCH($B$4 & " " & $B35, rawv3!$1:$1, 0), 4)), $C37 )} -> 665 | T37: {=COUNTIFS( rawv3!$F:$F, "<>Ongoing", INDIRECT("rawv3!" & ADDRESS(1, MATCH($D$2 & " " & T$3, rawv3!$1:$1, 0), 4) & ":" & ADDRESS(1048576, MATCH($D$2 & " " & T$3, rawv3!$1:$1, 0), 4)), T$4, INDIRECT("rawv3!" & ADDRESS(1, MATCH($B$4 & " " & $B35, rawv3!$1:$1, 0), 4) & ":" & ADDRESS(1048576, MATCH($B$4 & " " & $B35, rawv3!$1:$1, 0), 4)), $C37 )} -> 1840 | U37: {=COUNTIFS( rawv3!$F:$F, "<>Ongoing", INDIRECT("rawv3!" & ADDRESS(1, MATCH($D$2 & " " & T$3, rawv3!$1:$1, 0), 4) & ":" & ADDRESS(1048576, MATCH($D$2 & " " & T$3, rawv3!$1:$1, 0), 4)), U$4, INDIRECT("rawv3!" & ADDRESS(1, MATCH($B$4 & " " & $B35, rawv3!$1:$1, 0), 4) & ":" & ADDRESS(1048576, MATCH($B$4 & " " & $B35, rawv3!$1:$1, 0), 4)), $C37 )} -> 589 | W37: {=COUNTIFS( rawv3!$F:$F, "<>Ongoing", INDIRECT("rawv3!" & ADDRESS(1, MATCH($D$2 & " " & W$3, rawv3!$1:$1, 0), 4) & ":" & ADDRESS(1048576, MATCH($D$2 & " " & W$3, rawv3!$1:$1, 0), 4)), W$4, INDIRECT("rawv3!" & ADDRESS(1, MATCH($B$4 & " " & $B35, rawv3!$1:$1, 0), 4) & ":" & ADDRESS(1048576, MATCH($B$4 & " " & $B35, rawv3!$1:$1, 0), 4)), $C37 )} -> 1058 | X37: {=COUNTIFS( rawv3!$F:$F, "<>Ongoing", INDIRECT("rawv3!" & ADDRESS(1, MATCH($D$2 & " " & W$3, rawv3!$1:$1, 0), 4) & ":" & ADDRESS(1048576, MATCH($D$2 & " " & W$3, rawv3!$1:$1, 0), 4)), X$4, INDIRECT("rawv3!" & ADDRESS(1, MATCH($B$4 & " " & $B35, rawv3!$1:$1, 0), 4) & ":" & ADDRESS(1048576, MATCH($B$4 & " " & $B35, rawv3!$1:$1, 0), 4)), $C37 )} -> 1372 | Z37: {=COUNTIFS( rawv3!$F:$F, "<>Ongoing", INDIRECT("rawv3!" & ADDRESS(1, MATCH($B$4 & " " & $B35, rawv3!$1:$1, 0), 4) & ":" & ADDRESS(1048576, MATCH($B$4 & " " & $B35, rawv3!$1:$1, 0), 4)), $C37)} -> 2430
D38: F90D % | E38: {=COUNTIFS( rawv3!$F:$F, "Success", INDIRECT("rawv3!" & ADDRESS(1, MATCH($D$2 & " " & E$3, rawv3!$1:$1, 0), 4) & ":" & ADDRESS(1048576, MATCH($D$2 & " " & E$3, rawv3!$1:$1, 0), 4)), E$4, INDIRECT("rawv3!" & ADDRESS(1, MATCH($B$4 & " " & $B35, rawv3!$1:$1, 0), 4) & ":" & ADDRESS(1048576, MATCH($B$4 & " " & $B35, rawv3!$1:$1, 0), 4)), $C37 )/E37} -> 0.77894737 | F38: {=COUNTIFS( rawv3!$F:$F, "Success", INDIRECT("rawv3!" & ADDRESS(1, MATCH($D$2 & " " & E$3, rawv3!$1:$1, 0), 4) & ":" & ADDRESS(1048576, MATCH($D$2 & " " & E$3, rawv3!$1:$1, 0), 4)), F$4, INDIRECT("rawv3!" & ADDRESS(1, MATCH($B$4 & " " & $B35, rawv3!$1:$1, 0), 4) & ":" & ADDRESS(1048576, MATCH($B$4 & " " & $B35, rawv3!$1:$1, 0), 4)), $C37 )/F37} -> 0.8 | H38: {=COUNTIFS( rawv3!$F:$F, "Success", INDIRECT("rawv3!" & ADDRESS(1, MATCH($D$2 & " " & H$3, rawv3!$1:$1, 0), 4) & ":" & ADDRESS(1048576, MATCH($D$2 & " " & H$3, rawv3!$1:$1, 0), 4)), H$4, INDIRECT("rawv3!" & ADDRESS(1, MATCH($B$4 & " " & $B35, rawv3!$1:$1, 0), 4) & ":" & ADDRESS(1048576, MATCH($B$4 & " " & $B35, rawv3!$1:$1, 0), 4)), $C37 )/H37} -> 0.79741672 | I38: {=COUNTIFS( rawv3!$F:$F, "Success", INDIRECT("rawv3!" & ADDRESS(1, MATCH($D$2 & " " & H$3, rawv3!$1:$1, 0), 4) & ":" & ADDRESS(1048576, MATCH($D$2 & " " & H$3, rawv3!$1:$1, 0), 4)), I$4, INDIRECT("rawv3!" & ADDRESS(1, MATCH($B$4 & " " & $B35, rawv3!$1:$1, 0), 4) & ":" & ADDRESS(1048576, MATCH($B$4 & " " & $B35, rawv3!$1:$1, 0), 4)), $C37 )/I37} -> 0.77789364 | K38: {=COUNTIFS( rawv3!$F:$F, "Success", INDIRECT("rawv3!" & ADDRESS(1, MATCH($D$2 & " " & K$3, rawv3!$1:$1, 0), 4) & ":" & ADDRESS(1048576, MATCH($D$2 & " " & K$3, rawv3!$1:$1, 0), 4)), K$4, INDIRECT("rawv3!" & ADDRESS(1, MATCH($B$4 & " " & $B35, rawv3!$1:$1, 0), 4) & ":" & ADDRESS(1048576, MATCH($B$4 & " " & $B35, rawv3!$1:$1, 0), 4)), $C37 )/K37} -> 0.78892734 | L38: {=COUNTIFS( rawv3!$F:$F, "Success", INDIRECT("rawv3!" & ADDRESS(1, MATCH($D$2 & " " & K$3, rawv3!$1:$1, 0), 4) & ":" & ADDRESS(1048576, MATCH($D$2 & " " & K$3, rawv3!$1:$1, 0), 4)), L$4, INDIRECT("rawv3!" & ADDRESS(1, MATCH($B$4 & " " & $B35, rawv3!$1:$1, 0), 4) & ":" & ADDRESS(1048576, MATCH($B$4 & " " & $B35, rawv3!$1:$1, 0), 4)), $C37 )/L37} -> 0.79104478 | N38: {=COUNTIFS( rawv3!$F:$F, "Success", INDIRECT("rawv3!" & ADDRESS(1, MATCH($D$2 & " " & N$3, rawv3!$1:$1, 0), 4) & ":" & ADDRESS(1048576, MATCH($D$2 & " " & N$3, rawv3!$1:$1, 0), 4)), N$4, INDIRECT("rawv3!" & ADDRESS(1, MATCH($B$4 & " " & $B35, rawv3!$1:$1, 0), 4) & ":" & ADDRESS(1048576, MATCH($B$4 & " " & $B35, rawv3!$1:$1, 0), 4)), $C37 )/N37} -> 0.7957359 | O38: {=COUNTIFS( rawv3!$F:$F, "Success", INDIRECT("rawv3!" & ADDRESS(1, MATCH($D$2 & " " & N$3, rawv3!$1:$1, 0), 4) & ":" & ADDRESS(1048576, MATCH($D$2 & " " & N$3, rawv3!$1:$1, 0), 4)), O$4, INDIRECT("rawv3!" & ADDRESS(1, MATCH($B$4 & " " & $B35, rawv3!$1:$1, 0), 4) & ":" & ADDRESS(1048576, MATCH($B$4 & " " & $B35, rawv3!$1:$1, 0), 4)), $C37 )/O37} -> 0.7807377 | Q38: {=COUNTIFS( rawv3!$F:$F, "Success", INDIRECT("rawv3!" & ADDRESS(1, MATCH($D$2 & " " & Q$3, rawv3!$1:$1, 0), 4) & ":" & ADDRESS(1048576, MATCH($D$2 & " " & Q$3, rawv3!$1:$1, 0), 4)), Q$4, INDIRECT("rawv3!" & ADDRESS(1, MATCH($B$4 & " " & $B35, rawv3!$1:$1, 0), 4) & ":" & ADDRESS(1048576, MATCH($B$4 & " " & $B35, rawv3!$1:$1, 0), 4)), $C37 )/Q37} -> 0.79693704 | R38: {=COUNTIFS( rawv3!$F:$F, "Success", INDIRECT("rawv3!" & ADDRESS(1, MATCH($D$2 & " " & Q$3, rawv3!$1:$1, 0), 4) & ":" & ADDRESS(1048576, MATCH($D$2 & " " & Q$3, rawv3!$1:$1, 0), 4)), R$4, INDIRECT("rawv3!" & ADDRESS(1, MATCH($B$4 & " " & $B35, rawv3!$1:$1, 0), 4) & ":" & ADDRESS(1048576, MATCH($B$4 & " " & $B35, rawv3!$1:$1, 0), 4)), $C37 )/R37} -> 0.77142857 | T38: {=COUNTIFS( rawv3!$F:$F, "Success", INDIRECT("rawv3!" & ADDRESS(1, MATCH($D$2 & " " & T$3, rawv3!$1:$1, 0), 4) & ":" & ADDRESS(1048576, MATCH($D$2 & " " & T$3, rawv3!$1:$1, 0), 4)), T$4, INDIRECT("rawv3!" & ADDRESS(1, MATCH($B$4 & " " & $B35, rawv3!$1:$1, 0), 4) & ":" & ADDRESS(1048576, MATCH($B$4 & " " & $B35, rawv3!$1:$1, 0), 4)), $C37 )/T37} -> 0.7923913 | U38: {=COUNTIFS( rawv3!$F:$F, "Success", INDIRECT("rawv3!" & ADDRESS(1, MATCH($D$2 & " " & T$3, rawv3!$1:$1, 0), 4) & ":" & ADDRESS(1048576, MATCH($D$2 & " " & T$3, rawv3!$1:$1, 0), 4)), U$4, INDIRECT("rawv3!" & ADDRESS(1, MATCH($B$4 & " " & $B35, rawv3!$1:$1, 0), 4) & ":" & ADDRESS(1048576, MATCH($B$4 & " " & $B35, rawv3!$1:$1, 0), 4)), $C37 )/U37} -> 0.78098472 | W38: {=COUNTIFS( rawv3!$F:$F, "Success", INDIRECT("rawv3!" & ADDRESS(1, MATCH($D$2 & " " & W$3, rawv3!$1:$1, 0), 4) & ":" & ADDRESS(1048576, MATCH($D$2 & " " & W$3, rawv3!$1:$1, 0), 4)), W$4, INDIRECT("rawv3!" & ADDRESS(1, MATCH($B$4 & " " & $B35, rawv3!$1:$1, 0), 4) & ":" & ADDRESS(1048576, MATCH($B$4 & " " & $B35, rawv3!$1:$1, 0), 4)), $C37 )/W37} -> 0.78071834 | X38: {=COUNTIFS( rawv3!$F:$F, "Success", INDIRECT("rawv3!" & ADDRESS(1, MATCH($D$2 & " " & W$3, rawv3!$1:$1, 0), 4) & ":" & ADDRESS(1048576, MATCH($D$2 & " " & W$3, rawv3!$1:$1, 0), 4)), X$4, INDIRECT("rawv3!" & ADDRESS(1, MATCH($B$4 & " " & $B35, rawv3!$1:$1, 0), 4) & ":" & ADDRESS(1048576, MATCH($B$4 & " " & $B35, rawv3!$1:$1, 0), 4)), $C37 )/X37} -> 0.79664723 | Z38: {=COUNTIFS( rawv3!$F:$F, "Success", INDIRECT("rawv3!" & ADDRESS(1, MATCH($B$4 & " " & $B35, rawv3!$1:$1, 0), 4) & ":" & ADDRESS(1048576, MATCH($B$4 & " " & $B35, rawv3!$1:$1, 0), 4)), $C37)/Z37} -> 0.78971193 | AA38: {=COUNTIFS( rawv3!$F:$F, "Success", INDIRECT("rawv3!" & ADDRESS(1, MATCH($B$4 & " " & $B35, rawv3!$1:$1, 0), 4) & ":" & ADDRESS(1048576, MATCH($B$4 & " " & $B35, rawv3!$1:$1, 0), 4)), $C37)} -> 1919
B40: TOTAL | D40: # | E40: {=COUNTIFS( rawv3!$F:$F, "<>Ongoing", INDIRECT("rawv3!" & ADDRESS(1, MATCH($D$2& " " & E$3 , rawv3!$1:$1, 0), 4) & ":" & ADDRESS(1048576, MATCH($D$2& " " & E$3 , rawv3!$1:$1, 0), 4)), E$4)} -> 1283 | F40: {=COUNTIFS( rawv3!$F:$F, "<>Ongoing", INDIRECT("rawv3!" & ADDRESS(1, MATCH($D$2& " " & E$3 , rawv3!$1:$1, 0), 4) & ":" & ADDRESS(1048576, MATCH($D$2& " " & E$3 , rawv3!$1:$1, 0), 4)), F$4)} -> 1250 | H40: {=COUNTIFS( rawv3!$F:$F, "<>Ongoing", INDIRECT("rawv3!" & ADDRESS(1, MATCH($D$2& " " & H$3 , rawv3!$1:$1, 0), 4) & ":" & ADDRESS(1048576, MATCH($D$2& " " & H$3 , rawv3!$1:$1, 0), 4)), H$4)} -> 1544 | I40: {=COUNTIFS( rawv3!$F:$F, "<>Ongoing", INDIRECT("rawv3!" & ADDRESS(1, MATCH($D$2& " " & H$3 , rawv3!$1:$1, 0), 4) & ":" & ADDRESS(1048576, MATCH($D$2& " " & H$3 , rawv3!$1:$1, 0), 4)), I$4)} -> 994 | K40: {=COUNTIFS( rawv3!$F:$F, "<>Ongoing", INDIRECT("rawv3!" & ADDRESS(1, MATCH($D$2& " " & K$3 , rawv3!$1:$1, 0), 4) & ":" & ADDRESS(1048576, MATCH($D$2& " " & K$3 , rawv3!$1:$1, 0), 4)), K$4)} -> 1222 | L40: {=COUNTIFS( rawv3!$F:$F, "<>Ongoing", INDIRECT("rawv3!" & ADDRESS(1, MATCH($D$2& " " & K$3 , rawv3!$1:$1, 0), 4) & ":" & ADDRESS(1048576, MATCH($D$2& " " & K$3 , rawv3!$1:$1, 0), 4)), L$4)} -> 1315 | N40: {=COUNTIFS( rawv3!$F:$F, "<>Ongoing", INDIRECT("rawv3!" & ADDRESS(1, MATCH($D$2& " " & N$3 , rawv3!$1:$1, 0), 4) & ":" & ADDRESS(1048576, MATCH($D$2& " " & N$3 , rawv3!$1:$1, 0), 4)), N$4)} -> 1521 | O40: {=COUNTIFS( rawv3!$F:$F, "<>Ongoing", INDIRECT("rawv3!" & ADDRESS(1, MATCH($D$2& " " & N$3 , rawv3!$1:$1, 0), 4) & ":" & ADDRESS(1048576, MATCH($D$2& " " & N$3 , rawv3!$1:$1, 0), 4)), O$4)} -> 1017 | Q40: {=COUNTIFS( rawv3!$F:$F, "<>Ongoing", INDIRECT("rawv3!" & ADDRESS(1, MATCH($D$2& " " & Q$3 , rawv3!$1:$1, 0), 4) & ":" & ADDRESS(1048576, MATCH($D$2& " " & Q$3 , rawv3!$1:$1, 0), 4)), Q$4)} -> 1840 | R40: {=COUNTIFS( rawv3!$F:$F, "<>Ongoing", INDIRECT("rawv3!" & ADDRESS(1, MATCH($D$2& " " & Q$3 , rawv3!$1:$1, 0), 4) & ":" & ADDRESS(1048576, MATCH($D$2& " " & Q$3 , rawv3!$1:$1, 0), 4)), R$4)} -> 696 | T40: {=COUNTIFS( rawv3!$F:$F, "<>Ongoing", INDIRECT("rawv3!" & ADDRESS(1, MATCH($D$2& " " & T$3 , rawv3!$1:$1, 0), 4) & ":" & ADDRESS(1048576, MATCH($D$2& " " & T$3 , rawv3!$1:$1, 0), 4)), T$4)} -> 1921 | U40: {=COUNTIFS( rawv3!$F:$F, "<>Ongoing", INDIRECT("rawv3!" & ADDRESS(1, MATCH($D$2& " " & T$3 , rawv3!$1:$1, 0), 4) & ":" & ADDRESS(1048576, MATCH($D$2& " " & T$3 , rawv3!$1:$1, 0), 4)), U$4)} -> 616 | W40: {=COUNTIFS( rawv3!$F:$F, "<>Ongoing", INDIRECT("rawv3!" & ADDRESS(1, MATCH($D$2& " " & W$3 , rawv3!$1:$1, 0), 4) & ":" & ADDRESS(1048576, MATCH($D$2& " " & W$3 , rawv3!$1:$1, 0), 4)), W$4)} -> 1127 | X40: {=COUNTIFS( rawv3!$F:$F, "<>Ongoing", INDIRECT("rawv3!" & ADDRESS(1, MATCH($D$2& " " & W$3 , rawv3!$1:$1, 0), 4) & ":" & ADDRESS(1048576, MATCH($D$2& " " & W$3 , rawv3!$1:$1, 0), 4)), X$4)} -> 1411 | Z40: =COUNTIFS(rawv3!$F:$F, "Success") + COUNTIFS(rawv3!$F:$F, "Failed") -> 2538
D41: F90D % | E41: {=COUNTIFS( rawv3!$F:$F, "Success", INDIRECT("rawv3!" & ADDRESS(1, MATCH($D$2& " " & E$3 , rawv3!$1:$1, 0), 4) & ":" & ADDRESS(1048576, MATCH($D$2& " " & E$3 , rawv3!$1:$1, 0), 4)), E$4)/E40} -> 0.77942323 | F41: {=COUNTIFS( rawv3!$F:$F, "Success", INDIRECT("rawv3!" & ADDRESS(1, MATCH($D$2& " " & E$3 , rawv3!$1:$1, 0), 4) & ":" & ADDRESS(1048576, MATCH($D$2& " " & E$3 , rawv3!$1:$1, 0), 4)), F$4)/F40} -> 0.7984 | H41: {=COUNTIFS( rawv3!$F:$F, "Success", INDIRECT("rawv3!" & ADDRESS(1, MATCH($D$2& " " & H$3 , rawv3!$1:$1, 0), 4) & ":" & ADDRESS(1048576, MATCH($D$2& " " & H$3 , rawv3!$1:$1, 0), 4)), H$4)/H40} -> 0.79598446 | I41: {=COUNTIFS( rawv3!$F:$F, "Success", INDIRECT("rawv3!" & ADDRESS(1, MATCH($D$2& " " & H$3 , rawv3!$1:$1, 0), 4) & ":" & ADDRESS(1048576, MATCH($D$2& " " & H$3 , rawv3!$1:$1, 0), 4)), I$4)/I40} -> 0.77867203 | K41: {=COUNTIFS( rawv3!$F:$F, "Success", INDIRECT("rawv3!" & ADDRESS(1, MATCH($D$2& " " & K$3 , rawv3!$1:$1, 0), 4) & ":" & ADDRESS(1048576, MATCH($D$2& " " & K$3 , rawv3!$1:$1, 0), 4)), K$4)/K40} -> 0.78723404 | L41: {=COUNTIFS( rawv3!$F:$F, "Success", INDIRECT("rawv3!" & ADDRESS(1, MATCH($D$2& " " & K$3 , rawv3!$1:$1, 0), 4) & ":" & ADDRESS(1048576, MATCH($D$2& " " & K$3 , rawv3!$1:$1, 0), 4)), L$4)/L40} -> 0.79163498 | N41: {=COUNTIFS( rawv3!$F:$F, "Success", INDIRECT("rawv3!" & ADDRESS(1, MATCH($D$2& " " & N$3 , rawv3!$1:$1, 0), 4) & ":" & ADDRESS(1048576, MATCH($D$2& " " & N$3 , rawv3!$1:$1, 0), 4)), N$4)/N40} -> 0.79355687 | O41: {=COUNTIFS( rawv3!$F:$F, "Success", INDIRECT("rawv3!" & ADDRESS(1, MATCH($D$2& " " & N$3 , rawv3!$1:$1, 0), 4) & ":" & ADDRESS(1048576, MATCH($D$2& " " & N$3 , rawv3!$1:$1, 0), 4)), O$4)/O40} -> 0.7826942 | Q41: {=COUNTIFS( rawv3!$F:$F, "Success", INDIRECT("rawv3!" & ADDRESS(1, MATCH($D$2& " " & Q$3 , rawv3!$1:$1, 0), 4) & ":" & ADDRESS(1048576, MATCH($D$2& " " & Q$3 , rawv3!$1:$1, 0), 4)), Q$4)/Q40} -> 0.7951087 | R41: {=COUNTIFS( rawv3!$F:$F, "Success", INDIRECT("rawv3!" & ADDRESS(1, MATCH($D$2& " " & Q$3 , rawv3!$1:$1, 0), 4) & ":" & ADDRESS(1048576, MATCH($D$2& " " & Q$3 , rawv3!$1:$1, 0), 4)), R$4)/R40} -> 0.77442529 | T41: {=COUNTIFS( rawv3!$F:$F, "Success", INDIRECT("rawv3!" & ADDRESS(1, MATCH($D$2& " " & T$3 , rawv3!$1:$1, 0), 4) & ":" & ADDRESS(1048576, MATCH($D$2& " " & T$3 , rawv3!$1:$1, 0), 4)), T$4)/T40} -> 0.79125455 | U41: {=COUNTIFS( rawv3!$F:$F, "Success", INDIRECT("rawv3!" & ADDRESS(1, MATCH($D$2& " " & T$3 , rawv3!$1:$1, 0), 4) & ":" & ADDRESS(1048576, MATCH($D$2& " " & T$3 , rawv3!$1:$1, 0), 4)), U$4)/U40} -> 0.78246753 | W41: {=COUNTIFS( rawv3!$F:$F, "Success", INDIRECT("rawv3!" & ADDRESS(1, MATCH($D$2& " " & W$3 , rawv3!$1:$1, 0), 4) & ":" & ADDRESS(1048576, MATCH($D$2& " " & W$3 , rawv3!$1:$1, 0), 4)), W$4)/W40} -> 0.77905945 | X41: {=COUNTIFS( rawv3!$F:$F, "Success", INDIRECT("rawv3!" & ADDRESS(1, MATCH($D$2& " " & W$3 , rawv3!$1:$1, 0), 4) & ":" & ADDRESS(1048576, MATCH($D$2& " " & W$3 , rawv3!$1:$1, 0), 4)), X$4)/X40} -> 0.79730687 | Z41: =COUNTIFS( rawv3!$F:$F, "Success" )/Z40 -> 0.7892041 | AA41: =COUNTIFS( rawv3!$F:$F, "Success" ) -> 2003

Sheet Matrix - % Difference
B1: Not enough data
B2: Data as of July 3, 2024 | D2: Client
E3: Communication | H3: Decision | K3: Drive | N3: Emotion | Q3: Environment | T3: Preference | W3: Priority | Z3: TOTAL
B4: XP | E4: Synchronous | F4: Asynchronous | H4: Data-Driven | I4: Intuition | K4: Small tangible goals | L4: Towards visionary ideas | N4: Investment | O4: Separation | Q4: Flexibility | R4: Structure | T4: One goal in mind | U4: With detailed instructions | W4: Speed of execution | X4: Accuracy of decisions
B5: Communication | C5: Synchronous | D5: # | E5: {=COUNTIFS( rawv3!$F:$F, "<>Ongoing", INDIRECT("rawv3!" & ADDRESS(1, MATCH($D$2 & " " & E$3, rawv3!$1:$1, 0), 4) & ":" & ADDRESS(1048576, MATCH($D$2 & " " & E$3, rawv3!$1:$1, 0), 4)), E$4, INDIRECT("rawv3!" & ADDRESS(1, MATCH($B$4 & " " & $B5, rawv3!$1:$1, 0), 4) & ":" & ADDRESS(1048576, MATCH($B$4 & " " & $B5, rawv3!$1:$1, 0), 4)), $C5 )} -> 595 | F5: {=COUNTIFS( rawv3!$F:$F, "<>Ongoing", INDIRECT("rawv3!" & ADDRESS(1, MATCH($D$2 & " " & E$3, rawv3!$1:$1, 0), 4) & ":" & ADDRESS(1048576, MATCH($D$2 & " " & E$3, rawv3!$1:$1, 0), 4)), F$4, INDIRECT("rawv3!" & ADDRESS(1, MATCH($B$4 & " " & $B5, rawv3!$1:$1, 0), 4) & ":" & ADDRESS(1048576, MATCH($B$4 & " " & $B5, rawv3!$1:$1, 0), 4)), $C5 )} -> 379 | H5: {=COUNTIFS( rawv3!$F:$F, "<>Ongoing", INDIRECT("rawv3!" & ADDRESS(1, MATCH($D$2 & " " & H$3, rawv3!$1:$1, 0), 4) & ":" & ADDRESS(1048576, MATCH($D$2 & " " & H$3, rawv3!$1:$1, 0), 4)), H$4, INDIRECT("rawv3!" & ADDRESS(1, MATCH($B$4 & " " & $B5, rawv3!$1:$1, 0), 4) & ":" & ADDRESS(1048576, MATCH($B$4 & " " & $B5, rawv3!$1:$1, 0), 4)), $C5 )} -> 591 | I5: {=COUNTIFS( rawv3!$F:$F, "<>Ongoing", INDIRECT("rawv3!" & ADDRESS(1, MATCH($D$2 & " " & H$3, rawv3!$1:$1, 0), 4) & ":" & ADDRESS(1048576, MATCH($D$2 & " " & H$3, rawv3!$1:$1, 0), 4)), I$4, INDIRECT("rawv3!" & ADDRESS(1, MATCH($B$4 & " " & $B5, rawv3!$1:$1, 0), 4) & ":" & ADDRESS(1048576, MATCH($B$4 & " " & $B5, rawv3!$1:$1, 0), 4)), $C5 )} -> 385 | K5: {=COUNTIFS( rawv3!$F:$F, "<>Ongoing", INDIRECT("rawv3!" & ADDRESS(1, MATCH($D$2 & " " & K$3, rawv3!$1:$1, 0), 4) & ":" & ADDRESS(1048576, MATCH($D$2 & " " & K$3, rawv3!$1:$1, 0), 4)), K$4, INDIRECT("rawv3!" & ADDRESS(1, MATCH($B$4 & " " & $B5, rawv3!$1:$1, 0), 4) & ":" & ADDRESS(1048576, MATCH($B$4 & " " & $B5, rawv3!$1:$1, 0), 4)), $C5 )} -> 445 | L5: {=COUNTIFS( rawv3!$F:$F, "<>Ongoing", INDIRECT("rawv3!" & ADDRESS(1, MATCH($D$2 & " " & K$3, rawv3!$1:$1, 0), 4) & ":" & ADDRESS(1048576, MATCH($D$2 & " " & K$3, rawv3!$1:$1, 0), 4)), L$4, INDIRECT("rawv3!" & ADDRESS(1, MATCH($B$4 & " " & $B5, rawv3!$1:$1, 0), 4) & ":" & ADDRESS(1048576, MATCH($B$4 & " " & $B5, rawv3!$1:$1, 0), 4)), $C5 )} -> 530 | N5: {=COUNTIFS( rawv3!$F:$F, "<>Ongoing", INDIRECT("rawv3!" & ADDRESS(1, MATCH($D$2 & " " & N$3, rawv3!$1:$1, 0), 4) & ":" & ADDRESS(1048576, MATCH($D$2 & " " & N$3, rawv3!$1:$1, 0), 4)), N$4, INDIRECT("rawv3!" & ADDRESS(1, MATCH($B$4 & " " & $B5, rawv3!$1:$1, 0), 4) & ":" & ADDRESS(1048576, MATCH($B$4 & " " & $B5, rawv3!$1:$1, 0), 4)), $C5 )} -> 595 | O5: {=COUNTIFS( rawv3!$F:$F, "<>Ongoing", INDIRECT("rawv3!" & ADDRESS(1, MATCH($D$2 & " " & N$3, rawv3!$1:$1, 0), 4) & ":" & ADDRESS(1048576, MATCH($D$2 & " " & N$3, rawv3!$1:$1, 0), 4)), O$4, INDIRECT("rawv3!" & ADDRESS(1, MATCH($B$4 & " " & $B5, rawv3!$1:$1, 0), 4) & ":" & ADDRESS(1048576, MATCH($B$4 & " " & $B5, rawv3!$1:$1, 0), 4)), $C5 )} -> 381 | Q5: {=COUNTIFS( rawv3!$F:$F, "<>Ongoing", INDIRECT("rawv3!" & ADDRESS(1, MATCH($D$2 & " " & Q$3, rawv3!$1:$1, 0), 4) & ":" & ADDRESS(1048576, MATCH($D$2 & " " & Q$3, rawv3!$1:$1, 0), 4)), Q$4, INDIRECT("rawv3!" & ADDRESS(1, MATCH($B$4 & " " & $B5, rawv3!$1:$1, 0), 4) & ":" & ADDRESS(1048576, MATCH($B$4 & " " & $B5, rawv3!$1:$1, 0), 4)), $C5 )} -> 690 | R5: {=COUNTIFS( rawv3!$F:$F, "<>Ongoing", INDIRECT("rawv3!" & ADDRESS(1, MATCH($D$2 & " " & Q$3, rawv3!$1:$1, 0), 4) & ":" & ADDRESS(1048576, MATCH($D$2 & " " & Q$3, rawv3!$1:$1, 0), 4)), R$4, INDIRECT("rawv3!" & ADDRESS(1, MATCH($B$4 & " " & $B5, rawv3!$1:$1, 0), 4) & ":" & ADDRESS(1048576, MATCH($B$4 & " " & $B5, rawv3!$1:$1, 0), 4)), $C5 )} -> 285 | T5: {=COUNTIFS( rawv3!$F:$F, "<>Ongoing", INDIRECT("rawv3!" & ADDRESS(1, MATCH($D$2 & " " & T$3, rawv3!$1:$1, 0), 4) & ":" & ADDRESS(1048576, MATCH($D$2 & " " & T$3, rawv3!$1:$1, 0), 4)), T$4, INDIRECT("rawv3!" & ADDRESS(1, MATCH($B$4 & " " & $B5, rawv3!$1:$1, 0), 4) & ":" & ADDRESS(1048576, MATCH($B$4 & " " & $B5, rawv3!$1:$1, 0), 4)), $C5 )} -> 743 | U5: {=COUNTIFS( rawv3!$F:$F, "<>Ongoing", INDIRECT("rawv3!" & ADDRESS(1, MATCH($D$2 & " " & T$3, rawv3!$1:$1, 0), 4) & ":" & ADDRESS(1048576, MATCH($D$2 & " " & T$3, rawv3!$1:$1, 0), 4)), U$4, INDIRECT("rawv3!" & ADDRESS(1, MATCH($B$4 & " " & $B5, rawv3!$1:$1, 0), 4) & ":" & ADDRESS(1048576, MATCH($B$4 & " " & $B5, rawv3!$1:$1, 0), 4)), $C5 )} -> 232 | W5: {=COUNTIFS( rawv3!$F:$F, "<>Ongoing", INDIRECT("rawv3!" & ADDRESS(1, MATCH($D$2 & " " & W$3, rawv3!$1:$1, 0), 4) & ":" & ADDRESS(1048576, MATCH($D$2 & " " & W$3, rawv3!$1:$1, 0), 4)), W$4, INDIRECT("rawv3!" & ADDRESS(1, MATCH($B$4 & " " & $B5, rawv3!$1:$1, 0), 4) & ":" & ADDRESS(1048576, MATCH($B$4 & " " & $B5, rawv3!$1:$1, 0), 4)), $C5 )} -> 436 | X5: {=COUNTIFS( rawv3!$F:$F, "<>Ongoing", INDIRECT("rawv3!" & ADDRESS(1, MATCH($D$2 & " " & W$3, rawv3!$1:$1, 0), 4) & ":" & ADDRESS(1048576, MATCH($D$2 & " " & W$3, rawv3!$1:$1, 0), 4)), X$4, INDIRECT("rawv3!" & ADDRESS(1, MATCH($B$4 & " " & $B5, rawv3!$1:$1, 0), 4) & ":" & ADDRESS(1048576, MATCH($B$4 & " " & $B5, rawv3!$1:$1, 0), 4)), $C5 )} -> 540 | Z5: {=COUNTIFS( rawv3!$F:$F, "<>Ongoing", INDIRECT("rawv3!" & ADDRESS(1, MATCH($B$4 & " " & $B5, rawv3!$1:$1, 0), 4) & ":" & ADDRESS(1048576, MATCH($B$4 & " " & $B5, rawv3!$1:$1, 0), 4)), $C5)} -> 976
D6: F90D % | E6: =(Matrix!E6-Matrix!$Z$41)/Matrix!$Z$41 -> -0.022523358 | F6: =(Matrix!F6-Matrix!$Z$41)/Matrix!$Z$41 -> -0.020421874 | H6: =(Matrix!H6-Matrix!$Z$41)/Matrix!$Z$41 -> -0.013763619 | I6: =(Matrix!I6-Matrix!$Z$41)/Matrix!$Z$41 -> -0.032396859 | K6: =(Matrix!K6-Matrix!$Z$41)/Matrix!$Z$41 -> -0.06035329 | L6: =(Matrix!L6-Matrix!$Z$41)/Matrix!$Z$41 -> 0.013679481 | N6: =(Matrix!N6-Matrix!$Z$41)/Matrix!$Z$41 -> -0.020393779 | O6: =(Matrix!O6-Matrix!$Z$41)/Matrix!$Z$41 -> -0.022238296 | Q6: =(Matrix!Q6-Matrix!$Z$41)/Matrix!$Z$41 -> -0.015702533 | R6: =(Matrix!R6-Matrix!$Z$41)/Matrix!$Z$41 -> -0.030780146 | T6: =(Matrix!T6-Matrix!$Z$41)/Matrix!$Z$41 -> -0.0057618821 | U6: =(Matrix!U6-Matrix!$Z$41)/Matrix!$Z$41 -> -0.071522027 | W6: =(Matrix!W6-Matrix!$Z$41)/Matrix!$Z$41 -> -0.035144531 | X6: =(Matrix!X6-Matrix!$Z$41)/Matrix!$Z$41 -> -0.009785322 | Z6: =(Matrix!Z6-Matrix!$Z$41)/Matrix!$Z$41 -> -0.021113821
C7: Asynchronous | D7: # | E7: {=COUNTIFS( rawv3!$F:$F, "<>Ongoing", INDIRECT("rawv3!" & ADDRESS(1, MATCH($D$2 & " " & E$3, rawv3!$1:$1, 0), 4) & ":" & ADDRESS(1048576, MATCH($D$2 & " " & E$3, rawv3!$1:$1, 0), 4)), E$4, INDIRECT("rawv3!" & ADDRESS(1, MATCH($B$4 & " " & $B5, rawv3!$1:$1, 0), 4) & ":" & ADDRESS(1048576, MATCH($B$4 & " " & $B5, rawv3!$1:$1, 0), 4)), $C7 )} -> 688 | F7: {=COUNTIFS( rawv3!$F:$F, "<>Ongoing", INDIRECT("rawv3!" & ADDRESS(1, MATCH($D$2 & " " & E$3, rawv3!$1:$1, 0), 4) & ":" & ADDRESS(1048576, MATCH($D$2 & " " & E$3, rawv3!$1:$1, 0), 4)), F$4, INDIRECT("rawv3!" & ADDRESS(1, MATCH($B$4 & " " & $B5, rawv3!$1:$1, 0), 4) & ":" & ADDRESS(1048576, MATCH($B$4 & " " & $B5, rawv3!$1:$1, 0), 4)), $C7 )} -> 871 | H7: {=COUNTIFS( rawv3!$F:$F, "<>Ongoing", INDIRECT("rawv3!" & ADDRESS(1, MATCH($D$2 & " " & H$3, rawv3!$1:$1, 0), 4) & ":" & ADDRESS(1048576, MATCH($D$2 & " " & H$3, rawv3!$1:$1, 0), 4)), H$4, INDIRECT("rawv3!" & ADDRESS(1, MATCH($B$4 & " " & $B5, rawv3!$1:$1, 0), 4) & ":" & ADDRESS(1048576, MATCH($B$4 & " " & $B5, rawv3!$1:$1, 0), 4)), $C7 )} -> 953 | I7: {=COUNTIFS( rawv3!$F:$F, "<>Ongoing", INDIRECT("rawv3!" & ADDRESS(1, MATCH($D$2 & " " & H$3, rawv3!$1:$1, 0), 4) & ":" & ADDRESS(1048576, MATCH($D$2 & " " & H$3, rawv3!$1:$1, 0), 4)), I$4, INDIRECT("rawv3!" & ADDRESS(1, MATCH($B$4 & " " & $B5, rawv3!$1:$1, 0), 4) & ":" & ADDRESS(1048576, MATCH($B$4 & " " & $B5, rawv3!$1:$1, 0), 4)), $C7 )} -> 609 | K7: {=COUNTIFS( rawv3!$F:$F, "<>Ongoing", INDIRECT("rawv3!" & ADDRESS(1, MATCH($D$2 & " " & K$3, rawv3!$1:$1, 0), 4) & ":" & ADDRESS(1048576, MATCH($D$2 & " " & K$3, rawv3!$1:$1, 0), 4)), K$4, INDIRECT("rawv3!" & ADDRESS(1, MATCH($B$4 & " " & $B5, rawv3!$1:$1, 0), 4) & ":" & ADDRESS(1048576, MATCH($B$4 & " " & $B5, rawv3!$1:$1, 0), 4)), $C7 )} -> 777 | L7: {=COUNTIFS( rawv3!$F:$F, "<>Ongoing", INDIRECT("rawv3!" & ADDRESS(1, MATCH($D$2 & " " & K$3, rawv3!$1:$1, 0), 4) & ":" & ADDRESS(1048576, MATCH($D$2 & " " & K$3, rawv3!$1:$1, 0), 4)), L$4, INDIRECT("rawv3!" & ADDRESS(1, MATCH($B$4 & " " & $B5, rawv3!$1:$1, 0), 4) & ":" & ADDRESS(1048576, MATCH($B$4 & " " & $B5, rawv3!$1:$1, 0), 4)), $C7 )} -> 785 | N7: {=COUNTIFS( rawv3!$F:$F, "<>Ongoing", INDIRECT("rawv3!" & ADDRESS(1, MATCH($D$2 & " " & N$3, rawv3!$1:$1, 0), 4) & ":" & ADDRESS(1048576, MATCH($D$2 & " " & N$3, rawv3!$1:$1, 0), 4)), N$4, INDIRECT("rawv3!" & ADDRESS(1, MATCH($B$4 & " " & $B5, rawv3!$1:$1, 0), 4) & ":" & ADDRESS(1048576, MATCH($B$4 & " " & $B5, rawv3!$1:$1, 0), 4)), $C7 )} -> 926 | O7: {=COUNTIFS( rawv3!$F:$F, "<>Ongoing", INDIRECT("rawv3!" & ADDRESS(1, MATCH($D$2 & " " & N$3, rawv3!$1:$1, 0), 4) & ":" & ADDRESS(1048576, MATCH($D$2 & " " & N$3, rawv3!$1:$1, 0), 4)), O$4, INDIRECT("rawv3!" & ADDRESS(1, MATCH($B$4 & " " & $B5, rawv3!$1:$1, 0), 4) & ":" & ADDRESS(1048576, MATCH($B$4 & " " & $B5, rawv3!$1:$1, 0), 4)), $C7 )} -> 636 | Q7: {=COUNTIFS( rawv3!$F:$F, "<>Ongoing", INDIRECT("rawv3!" & ADDRESS(1, MATCH($D$2 & " " & Q$3, rawv3!$1:$1, 0), 4) & ":" & ADDRESS(1048576, MATCH($D$2 & " " & Q$3, rawv3!$1:$1, 0), 4)), Q$4, INDIRECT("rawv3!" & ADDRESS(1, MATCH($B$4 & " " & $B5, rawv3!$1:$1, 0), 4) & ":" & ADDRESS(1048576, MATCH($B$4 & " " & $B5, rawv3!$1:$1, 0), 4)), $C7 )} -> 1150 | R7: {=COUNTIFS( rawv3!$F:$F, "<>Ongoing", INDIRECT("rawv3!" & ADDRESS(1, MATCH($D$2 & " " & Q$3, rawv3!$1:$1, 0), 4) & ":" & ADDRESS(1048576, MATCH($D$2 & " " & Q$3, rawv3!$1:$1, 0), 4)), R$4, INDIRECT("rawv3!" & ADDRESS(1, MATCH($B$4 & " " & $B5, rawv3!$1:$1, 0), 4) & ":" & ADDRESS(1048576, MATCH($B$4 & " " & $B5, rawv3!$1:$1, 0), 4)), $C7 )} -> 411 | T7: {=COUNTIFS( rawv3!$F:$F, "<>Ongoing", INDIRECT("rawv3!" & ADDRESS(1, MATCH($D$2 & " " & T$3, rawv3!$1:$1, 0), 4) & ":" & ADDRESS(1048576, MATCH($D$2 & " " & T$3, rawv3!$1:$1, 0), 4)), T$4, INDIRECT("rawv3!" & ADDRESS(1, MATCH($B$4 & " " & $B5, rawv3!$1:$1, 0), 4) & ":" & ADDRESS(1048576, MATCH($B$4 & " " & $B5, rawv3!$1:$1, 0), 4)), $C7 )} -> 1178 | U7: {=COUNTIFS( rawv3!$F:$F, "<>Ongoing", INDIRECT("rawv3!" & ADDRESS(1, MATCH($D$2 & " " & T$3, rawv3!$1:$1, 0), 4) & ":" & ADDRESS(1048576, MATCH($D$2 & " " & T$3, rawv3!$1:$1, 0), 4)), U$4, INDIRECT("rawv3!" & ADDRESS(1, MATCH($B$4 & " " & $B5, rawv3!$1:$1, 0), 4) & ":" & ADDRESS(1048576, MATCH($B$4 & " " & $B5, rawv3!$1:$1, 0), 4)), $C7 )} -> 384 | W7: {=COUNTIFS( rawv3!$F:$F, "<>Ongoing", INDIRECT("rawv3!" & ADDRESS(1, MATCH($D$2 & " " & W$3, rawv3!$1:$1, 0), 4) & ":" & ADDRESS(1048576, MATCH($D$2 & " " & W$3, rawv3!$1:$1, 0), 4)), W$4, INDIRECT("rawv3!" & ADDRESS(1, MATCH($B$4 & " " & $B5, rawv3!$1:$1, 0), 4) & ":" & ADDRESS(1048576, MATCH($B$4 & " " & $B5, rawv3!$1:$1, 0), 4)), $C7 )} -> 691 | X7: {=COUNTIFS( rawv3!$F:$F, "<>Ongoing", INDIRECT("rawv3!" & ADDRESS(1, MATCH($D$2 & " " & W$3, rawv3!$1:$1, 0), 4) & ":" & ADDRESS(1048576, MATCH($D$2 & " " & W$3, rawv3!$1:$1, 0), 4)), X$4, INDIRECT("rawv3!" & ADDRESS(1, MATCH($B$4 & " " & $B5, rawv3!$1:$1, 0), 4) & ":" & ADDRESS(1048576, MATCH($B$4 & " " & $B5, rawv3!$1:$1, 0), 4)), $C7 )} -> 871 | Z7: {=COUNTIFS( rawv3!$F:$F, "<>Ongoing", INDIRECT("rawv3!" & ADDRESS(1, MATCH($B$4 & " " & $B5, rawv3!$1:$1, 0), 4) & ":" & ADDRESS(1048576, MATCH($B$4 & " " & $B5, rawv3!$1:$1, 0), 4)), $C7)} -> 1562
D8: F90D % | E8: =(Matrix!E8-Matrix!$Z$41)/Matrix!$Z$41 -> -0.0036326324 | F8: =(Matrix!F8-Matrix!$Z$41)/Matrix!$Z$41 -> 0.025608545 | H8: =(Matrix!H8-Matrix!$Z$41)/Matrix!$Z$41 -> 0.022454775 | I8: =(Matrix!I8-Matrix!$Z$41)/Matrix!$Z$41 -> -0.0013010042 | K8: =(Matrix!K8-Matrix!$Z$41)/Matrix!$Z$41 -> 0.030639369 | L8: =(Matrix!L8-Matrix!$Z$41)/Matrix!$Z$41 -> -0.0040760515 | N8: =(Matrix!N8-Matrix!$Z$41)/Matrix!$Z$41 -> 0.022163299 | O8: =(Matrix!O8-Matrix!$Z$41)/Matrix!$Z$41 -> 0.00013187766 | Q8: =(Matrix!Q8-Matrix!$Z$41)/Matrix!$Z$41 -> 0.021392259 | R8: =(Matrix!R8-Matrix!$Z$41)/Matrix!$Z$41 -> -0.01036766 | T8: =(Matrix!T8-Matrix!$Z$41)/Matrix!$Z$41 -> 0.0078710457 | U8: =(Matrix!U8-Matrix!$Z$41)/Matrix!$Z$41 -> 0.029518223 | W8: =(Matrix!W8-Matrix!$Z$41)/Matrix!$Z$41 -> 0.0012101963 | X8: =(Matrix!X8-Matrix!$Z$41)/Matrix!$Z$41 -> 0.022699017 | Z8: =(Matrix!Z8-Matrix!$Z$41)/Matrix!$Z$41 -> 0.013192759
B10: Decision | C10: Data-Driven | D10: # | E10: {=COUNTIFS( rawv3!$F:$F, "<>Ongoing", INDIRECT("rawv3!" & ADDRESS(1, MATCH($D$2 & " " & E$3, rawv3!$1:$1, 0), 4) & ":" & ADDRESS(1048576, MATCH($D$2 & " " & E$3, rawv3!$1:$1, 0), 4)), E$4, INDIRECT("rawv3!" & ADDRESS(1, MATCH($B$4 & " " & $B10, rawv3!$1:$1, 0), 4) & ":" & ADDRESS(1048576, MATCH($B$4 & " " & $B10, rawv3!$1:$1, 0), 4)), $C10 )} -> 1196 | F10: {=COUNTIFS( rawv3!$F:$F, "<>Ongoing", INDIRECT("rawv3!" & ADDRESS(1, MATCH($D$2 & " " & E$3, rawv3!$1:$1, 0), 4) & ":" & ADDRESS(1048576, MATCH($D$2 & " " & E$3, rawv3!$1:$1, 0), 4)), F$4, INDIRECT("rawv3!" & ADDRESS(1, MATCH($B$4 & " " & $B10, rawv3!$1:$1, 0), 4) & ":" & ADDRESS(1048576, MATCH($B$4 & " " & $B10, rawv3!$1:$1, 0), 4)), $C10 )} -> 1163 | H10: {=COUNTIFS( rawv3!$F:$F, "<>Ongoing", INDIRECT("rawv3!" & ADDRESS(1, MATCH($D$2 & " " & H$3, rawv3!$1:$1, 0), 4) & ":" & ADDRESS(1048576, MATCH($D$2 & " " & H$3, rawv3!$1:$1, 0), 4)), H$4, INDIRECT("rawv3!" & ADDRESS(1, MATCH($B$4 & " " & $B10, rawv3!$1:$1, 0), 4) & ":" & ADDRESS(1048576, MATCH($B$4 & " " & $B10, rawv3!$1:$1, 0), 4)), $C10 )} -> 1460 | I10: {=COUNTIFS( rawv3!$F:$F, "<>Ongoing", INDIRECT("rawv3!" & ADDRESS(1, MATCH($D$2 & " " & H$3, rawv3!$1:$1, 0), 4) & ":" & ADDRESS(1048576, MATCH($D$2 & " " & H$3, rawv3!$1:$1, 0), 4)), I$4, INDIRECT("rawv3!" & ADDRESS(1, MATCH($B$4 & " " & $B10, rawv3!$1:$1, 0), 4) & ":" & ADDRESS(1048576, MATCH($B$4 & " " & $B10, rawv3!$1:$1, 0), 4)), $C10 )} -> 904 | K10: {=COUNTIFS( rawv3!$F:$F, "<>Ongoing", INDIRECT("rawv3!" & ADDRESS(1, MATCH($D$2 & " " & K$3, rawv3!$1:$1, 0), 4) & ":" & ADDRESS(1048576, MATCH($D$2 & " " & K$3, rawv3!$1:$1, 0), 4)), K$4, INDIRECT("rawv3!" & ADDRESS(1, MATCH($B$4 & " " & $B10, rawv3!$1:$1, 0), 4) & ":" & ADDRESS(1048576, MATCH($B$4 & " " & $B10, rawv3!$1:$1, 0), 4)), $C10 )} -> 1145 | L10: {=COUNTIFS( rawv3!$F:$F, "<>Ongoing", INDIRECT("rawv3!" & ADDRESS(1, MATCH($D$2 & " " & K$3, rawv3!$1:$1, 0), 4) & ":" & ADDRESS(1048576, MATCH($D$2 & " " & K$3, rawv3!$1:$1, 0), 4)), L$4, INDIRECT("rawv3!" & ADDRESS(1, MATCH($B$4 & " " & $B10, rawv3!$1:$1, 0), 4) & ":" & ADDRESS(1048576, MATCH($B$4 & " " & $B10, rawv3!$1:$1, 0), 4)), $C10 )} -> 1218 | N10: {=COUNTIFS( rawv3!$F:$F, "<>Ongoing", INDIRECT("rawv3!" & ADDRESS(1, MATCH($D$2 & " " & N$3, rawv3!$1:$1, 0), 4) & ":" & ADDRESS(1048576, MATCH($D$2 & " " & N$3, rawv3!$1:$1, 0), 4)), N$4, INDIRECT("rawv3!" & ADDRESS(1, MATCH($B$4 & " " & $B10, rawv3!$1:$1, 0), 4) & ":" & ADDRESS(1048576, MATCH($B$4 & " " & $B10, rawv3!$1:$1, 0), 4)), $C10 )} -> 1408 | O10: {=COUNTIFS( rawv3!$F:$F, "<>Ongoing", INDIRECT("rawv3!" & ADDRESS(1, MATCH($D$2 & " " & N$3, rawv3!$1:$1, 0), 4) & ":" & ADDRESS(1048576, MATCH($D$2 & " " & N$3, rawv3!$1:$1, 0), 4)), O$4, INDIRECT("rawv3!" & ADDRESS(1, MATCH($B$4 & " " & $B10, rawv3!$1:$1, 0), 4) & ":" & ADDRESS(1048576, MATCH($B$4 & " " & $B10, rawv3!$1:$1, 0), 4)), $C10 )} -> 956 | Q10: {=COUNTIFS( rawv3!$F:$F, "<>Ongoing", INDIRECT("rawv3!" & ADDRESS(1, MATCH($D$2 & " " & Q$3, rawv3!$1:$1, 0), 4) & ":" & ADDRESS(1048576, MATCH($D$2 & " " & Q$3, rawv3!$1:$1, 0), 4)), Q$4, INDIRECT("rawv3!" & ADDRESS(1, MATCH($B$4 & " " & $B10, rawv3!$1:$1, 0), 4) & ":" & ADDRESS(1048576, MATCH($B$4 & " " & $B10, rawv3!$1:$1, 0), 4)), $C10 )} -> 1719 | R10: {=COUNTIFS( rawv3!$F:$F, "<>Ongoing", INDIRECT("rawv3!" & ADDRESS(1, MATCH($D$2 & " " & Q$3, rawv3!$1:$1, 0), 4) & ":" & ADDRESS(1048576, MATCH($D$2 & " " & Q$3, rawv3!$1:$1, 0), 4)), R$4, INDIRECT("rawv3!" & ADDRESS(1, MATCH($B$4 & " " & $B10, rawv3!$1:$1, 0), 4) & ":" & ADDRESS(1048576, MATCH($B$4 & " " & $B10, rawv3!$1:$1, 0), 4)), $C10 )} -> 643 | T10: {=COUNTIFS( rawv3!$F:$F, "<>Ongoing", INDIRECT("rawv3!" & ADDRESS(1, MATCH($D$2 & " " & T$3, rawv3!$1:$1, 0), 4) & ":" & ADDRESS(1048576, MATCH($D$2 & " " & T$3, rawv3!$1:$1, 0), 4)), T$4, INDIRECT("rawv3!" & ADDRESS(1, MATCH($B$4 & " " & $B10, rawv3!$1:$1, 0), 4) & ":" & ADDRESS(1048576, MATCH($B$4 & " " & $B10, rawv3!$1:$1, 0), 4)), $C10 )} -> 1793 | U10: {=COUNTIFS( rawv3!$F:$F, "<>Ongoing", INDIRECT("rawv3!" & ADDRESS(1, MATCH($D$2 & " " & T$3, rawv3!$1:$1, 0), 4) & ":" & ADDRESS(1048576, MATCH($D$2 & " " & T$3, rawv3!$1:$1, 0), 4)), U$4, INDIRECT("rawv3!" & ADDRESS(1, MATCH($B$4 & " " & $B10, rawv3!$1:$1, 0), 4) & ":" & ADDRESS(1048576, MATCH($B$4 & " " & $B10, rawv3!$1:$1, 0), 4)), $C10 )} -> 570 | W10: {=COUNTIFS( rawv3!$F:$F, "<>Ongoing", INDIRECT("rawv3!" & ADDRESS(1, MATCH($D$2 & " " & W$3, rawv3!$1:$1, 0), 4) & ":" & ADDRESS(1048576, MATCH($D$2 & " " & W$3, rawv3!$1:$1, 0), 4)), W$4, INDIRECT("rawv3!" & ADDRESS(1, MATCH($B$4 & " " & $B10, rawv3!$1:$1, 0), 4) & ":" & ADDRESS(1048576, MATCH($B$4 & " " & $B10, rawv3!$1:$1, 0), 4)), $C10 )} -> 1045 | X10: {=COUNTIFS( rawv3!$F:$F, "<>Ongoing", INDIRECT("rawv3!" & ADDRESS(1, MATCH($D$2 & " " & W$3, rawv3!$1:$1, 0), 4) & ":" & ADDRESS(1048576, MATCH($D$2 & " " & W$3, rawv3!$1:$1, 0), 4)), X$4, INDIRECT("rawv3!" & ADDRESS(1, MATCH($B$4 & " " & $B10, rawv3!$1:$1, 0), 4) & ":" & ADDRESS(1048576, MATCH($B$4 & " " & $B10, rawv3!$1:$1, 0), 4)), $C10 )} -> 1319 | Z10: {=COUNTIFS( rawv3!$F:$F, "<>Ongoing", INDIRECT("rawv3!" & ADDRESS(1, MATCH($B$4 & " " & $B10, rawv3!$1:$1, 0), 4) & ":" & ADDRESS(1048576, MATCH($B$4 & " " & $B10, rawv3!$1:$1, 0), 4)), $C10)} -> 2364
D11: F90D % | E11: =(Matrix!E11-Matrix!$Z$41)/Matrix!$Z$41 -> -0.015773163 | F11: =(Matrix!F11-Matrix!$Z$41)/Matrix!$Z$41 -> 0.016512205 | H11: =(Matrix!H11-Matrix!$Z$41)/Matrix!$Z$41 -> 0.0093400994 | I11: =(Matrix!I11-Matrix!$Z$41)/Matrix!$Z$41 -> -0.013232364 | K11: =(Matrix!K11-Matrix!$Z$41)/Matrix!$Z$41 -> -0.002920074 | L11: =(Matrix!L11-Matrix!$Z$41)/Matrix!$Z$41 -> 0.0049408646 | N11: =(Matrix!N11-Matrix!$Z$41)/Matrix!$Z$41 -> 0.0052201527 | O11: =(Matrix!O11-Matrix!$Z$41)/Matrix!$Z$41 -> -0.0059367016 | Q11: =(Matrix!Q11-Matrix!$Z$41)/Matrix!$Z$41 -> 0.0054238015 | R11: =(Matrix!R11-Matrix!$Z$41)/Matrix!$Z$41 -> -0.010756028 | T11: =(Matrix!T11-Matrix!$Z$41)/Matrix!$Z$41 -> 0.0020897265 | U11: =(Matrix!U11-Matrix!$Z$41)/Matrix!$Z$41 -> -0.0041043698 | W11: =(Matrix!W11-Matrix!$Z$41)/Matrix!$Z$41 -> -0.01178376 | X11: =(Matrix!X11-Matrix!$Z$41)/Matrix!$Z$41 -> 0.010605396 | Z11: =(Matrix!Z11-Matrix!$Z$41)/Matrix!$Z$41 -> 0.00070832837
C12: Intuition | D12: # | E12: {=COUNTIFS( rawv3!$F:$F, "<>Ongoing", INDIRECT("rawv3!" & ADDRESS(1, MATCH($D$2 & " " & E$3, rawv3!$1:$1, 0), 4) & ":" & ADDRESS(1048576, MATCH($D$2 & " " & E$3, rawv3!$1:$1, 0), 4)), E$4, INDIRECT("rawv3!" & ADDRESS(1, MATCH($B$4 & " " & $B10, rawv3!$1:$1, 0), 4) & ":" & ADDRESS(1048576, MATCH($B$4 & " " & $B10, rawv3!$1:$1, 0), 4)), $C12 )} -> 87 | F12: {=COUNTIFS( rawv3!$F:$F, "<>Ongoing", INDIRECT("rawv3!" & ADDRESS(1, MATCH($D$2 & " " & E$3, rawv3!$1:$1, 0), 4) & ":" & ADDRESS(1048576, MATCH($D$2 & " " & E$3, rawv3!$1:$1, 0), 4)), F$4, INDIRECT("rawv3!" & ADDRESS(1, MATCH($B$4 & " " & $B10, rawv3!$1:$1, 0), 4) & ":" & ADDRESS(1048576, MATCH($B$4 & " " & $B10, rawv3!$1:$1, 0), 4)), $C12 )} -> 87 | H12: {=COUNTIFS( rawv3!$F:$F, "<>Ongoing", INDIRECT("rawv3!" & ADDRESS(1, MATCH($D$2 & " " & H$3, rawv3!$1:$1, 0), 4) & ":" & ADDRESS(1048576, MATCH($D$2 & " " & H$3, rawv3!$1:$1, 0), 4)), H$4, INDIRECT("rawv3!" & ADDRESS(1, MATCH($B$4 & " " & $B10, rawv3!$1:$1, 0), 4) & ":" & ADDRESS(1048576, MATCH($B$4 & " " & $B10, rawv3!$1:$1, 0), 4)), $C12 )} -> 84 | I12: {=COUNTIFS( rawv3!$F:$F, "<>Ongoing", INDIRECT("rawv3!" & ADDRESS(1, MATCH($D$2 & " " & H$3, rawv3!$1:$1, 0), 4) & ":" & ADDRESS(1048576, MATCH($D$2 & " " & H$3, rawv3!$1:$1, 0), 4)), I$4, INDIRECT("rawv3!" & ADDRESS(1, MATCH($B$4 & " " & $B10, rawv3!$1:$1, 0), 4) & ":" & ADDRESS(1048576, MATCH($B$4 & " " & $B10, rawv3!$1:$1, 0), 4)), $C12 )} -> 90 | K12: {=COUNTIFS( rawv3!$F:$F, "<>Ongoing", INDIRECT("rawv3!" & ADDRESS(1, MATCH($D$2 & " " & K$3, rawv3!$1:$1, 0), 4) & ":" & ADDRESS(1048576, MATCH($D$2 & " " & K$3, rawv3!$1:$1, 0), 4)), K$4, INDIRECT("rawv3!" & ADDRESS(1, MATCH($B$4 & " " & $B10, rawv3!$1:$1, 0), 4) & ":" & ADDRESS(1048576, MATCH($B$4 & " " & $B10, rawv3!$1:$1, 0), 4)), $C12 )} -> 77 | L12: {=COUNTIFS( rawv3!$F:$F, "<>Ongoing", INDIRECT("rawv3!" & ADDRESS(1, MATCH($D$2 & " " & K$3, rawv3!$1:$1, 0), 4) & ":" & ADDRESS(1048576, MATCH($D$2 & " " & K$3, rawv3!$1:$1, 0), 4)), L$4, INDIRECT("rawv3!" & ADDRESS(1, MATCH($B$4 & " " & $B10, rawv3!$1:$1, 0), 4) & ":" & ADDRESS(1048576, MATCH($B$4 & " " & $B10, rawv3!$1:$1, 0), 4)), $C12 )} -> 97 | N12: {=COUNTIFS( rawv3!$F:$F, "<>Ongoing", INDIRECT("rawv3!" & ADDRESS(1, MATCH($D$2 & " " & N$3, rawv3!$1:$1, 0), 4) & ":" & ADDRESS(1048576, MATCH($D$2 & " " & N$3, rawv3!$1:$1, 0), 4)), N$4, INDIRECT("rawv3!" & ADDRESS(1, MATCH($B$4 & " " & $B10, rawv3!$1:$1, 0), 4) & ":" & ADDRESS(1048576, MATCH($B$4 & " " & $B10, rawv3!$1:$1, 0), 4)), $C12 )} -> 113 | O12: {=COUNTIFS( rawv3!$F:$F, "<>Ongoing", INDIRECT("rawv3!" & ADDRESS(1, MATCH($D$2 & " " & N$3, rawv3!$1:$1, 0), 4) & ":" & ADDRESS(1048576, MATCH($D$2 & " " & N$3, rawv3!$1:$1, 0), 4)), O$4, INDIRECT("rawv3!" & ADDRESS(1, MATCH($B$4 & " " & $B10, rawv3!$1:$1, 0), 4) & ":" & ADDRESS(1048576, MATCH($B$4 & " " & $B10, rawv3!$1:$1, 0), 4)), $C12 )} -> 61 | Q12: {=COUNTIFS( rawv3!$F:$F, "<>Ongoing", INDIRECT("rawv3!" & ADDRESS(1, MATCH($D$2 & " " & Q$3, rawv3!$1:$1, 0), 4) & ":" & ADDRESS(1048576, MATCH($D$2 & " " & Q$3, rawv3!$1:$1, 0), 4)), Q$4, INDIRECT("rawv3!" & ADDRESS(1, MATCH($B$4 & " " & $B10, rawv3!$1:$1, 0), 4) & ":" & ADDRESS(1048576, MATCH($B$4 & " " & $B10, rawv3!$1:$1, 0), 4)), $C12 )} -> 121 | R12: {=COUNTIFS( rawv3!$F:$F, "<>Ongoing", INDIRECT("rawv3!" & ADDRESS(1, MATCH($D$2 & " " & Q$3, rawv3!$1:$1, 0), 4) & ":" & ADDRESS(1048576, MATCH($D$2 & " " & Q$3, rawv3!$1:$1, 0), 4)), R$4, INDIRECT("rawv3!" & ADDRESS(1, MATCH($B$4 & " " & $B10, rawv3!$1:$1, 0), 4) & ":" & ADDRESS(1048576, MATCH($B$4 & " " & $B10, rawv3!$1:$1, 0), 4)), $C12 )} -> 53 | T12: {=COUNTIFS( rawv3!$F:$F, "<>Ongoing", INDIRECT("rawv3!" & ADDRESS(1, MATCH($D$2 & " " & T$3, rawv3!$1:$1, 0), 4) & ":" & ADDRESS(1048576, MATCH($D$2 & " " & T$3, rawv3!$1:$1, 0), 4)), T$4, INDIRECT("rawv3!" & ADDRESS(1, MATCH($B$4 & " " & $B10, rawv3!$1:$1, 0), 4) & ":" & ADDRESS(1048576, MATCH($B$4 & " " & $B10, rawv3!$1:$1, 0), 4)), $C12 )} -> 128 | U12: {=COUNTIFS( rawv3!$F:$F, "<>Ongoing", INDIRECT("rawv3!" & ADDRESS(1, MATCH($D$2 & " " & T$3, rawv3!$1:$1, 0), 4) & ":" & ADDRESS(1048576, MATCH($D$2 & " " & T$3, rawv3!$1:$1, 0), 4)), U$4, INDIRECT("rawv3!" & ADDRESS(1, MATCH($B$4 & " " & $B10, rawv3!$1:$1, 0), 4) & ":" & ADDRESS(1048576, MATCH($B$4 & " " & $B10, rawv3!$1:$1, 0), 4)), $C12 )} -> 46 | W12: {=COUNTIFS( rawv3!$F:$F, "<>Ongoing", INDIRECT("rawv3!" & ADDRESS(1, MATCH($D$2 & " " & W$3, rawv3!$1:$1, 0), 4) & ":" & ADDRESS(1048576, MATCH($D$2 & " " & W$3, rawv3!$1:$1, 0), 4)), W$4, INDIRECT("rawv3!" & ADDRESS(1, MATCH($B$4 & " " & $B10, rawv3!$1:$1, 0), 4) & ":" & ADDRESS(1048576, MATCH($B$4 & " " & $B10, rawv3!$1:$1, 0), 4)), $C12 )} -> 82 | X12: {=COUNTIFS( rawv3!$F:$F, "<>Ongoing", INDIRECT("rawv3!" & ADDRESS(1, MATCH($D$2 & " " & W$3, rawv3!$1:$1, 0), 4) & ":" & ADDRESS(1048576, MATCH($D$2 & " " & W$3, rawv3!$1:$1, 0), 4)), X$4, INDIRECT("rawv3!" & ADDRESS(1, MATCH($B$4 & " " & $B10, rawv3!$1:$1, 0), 4) & ":" & ADDRESS(1048576, MATCH($B$4 & " " & $B10, rawv3!$1:$1, 0), 4)), $C12 )} -> 92 | Z12: {=COUNTIFS( rawv3!$F:$F, "<>Ongoing", INDIRECT("rawv3!" & ADDRESS(1, MATCH($B$4 & " " & $B10, rawv3!$1:$1, 0), 4) & ":" & ADDRESS(1048576, MATCH($B$4 & " " & $B10, rawv3!$1:$1, 0), 4)), $C12)} -> 174
D13: F90D % | E13: =(Matrix!E13-Matrix!$Z$41)/Matrix!$Z$41 -> 0.034069585 | F13: =(Matrix!F13-Matrix!$Z$41)/Matrix!$Z$41 -> -0.053316577 | H13: =(Matrix!H13-Matrix!$Z$41)/Matrix!$Z$41 -> -0.0044219385 | I13: =(Matrix!I13-Matrix!$Z$41)/Matrix!$Z$41 -> -0.014478283 | K13: =(Matrix!K13-Matrix!$Z$41)/Matrix!$Z$41 -> 0.0038059793 | L13: =(Matrix!L13-Matrix!$Z$41)/Matrix!$Z$41 -> -0.020284007 | N13: =(Matrix!N13-Matrix!$Z$41)/Matrix!$Z$41 -> 0.0091941733 | O13: =(Matrix!O13-Matrix!$Z$41)/Matrix!$Z$41 -> -0.044482457 | Q13: =(Matrix!Q13-Matrix!$Z$41)/Matrix!$Z$41 -> 0.036717651 | R13: =(Matrix!R13-Matrix!$Z$41)/Matrix!$Z$41 -> -0.11542121 | T13: =(Matrix!T13-Matrix!$Z$41)/Matrix!$Z$41 -> 0.0097197953 | U13: =(Matrix!U13-Matrix!$Z$41)/Matrix!$Z$41 -> -0.063448306 | W13: =(Matrix!W13-Matrix!$Z$41)/Matrix!$Z$41 -> -0.02649684 | X13: =(Matrix!X13-Matrix!$Z$41)/Matrix!$Z$41 -> 0.0054157894 | Z13: =(Matrix!Z13-Matrix!$Z$41)/Matrix!$Z$41 -> -0.0096234958
B15: Drive | C15: Small tangible goals | D15: # | E15: {=COUNTIFS( rawv3!$F:$F, "<>Ongoing", INDIRECT("rawv3!" & ADDRESS(1, MATCH($D$2 & " " & E$3, rawv3!$1:$1, 0), 4) & ":" & ADDRESS(1048576, MATCH($D$2 & " " & E$3, rawv3!$1:$1, 0), 4)), E$4, INDIRECT("rawv3!" & ADDRESS(1, MATCH($B$4 & " " & $B15, rawv3!$1:$1, 0), 4) & ":" & ADDRESS(1048576, MATCH($B$4 & " " & $B15, rawv3!$1:$1, 0), 4)), $C15 )} -> 689 | F15: {=COUNTIFS( rawv3!$F:$F, "<>Ongoing", INDIRECT("rawv3!" & ADDRESS(1, MATCH($D$2 & " " & E$3, rawv3!$1:$1, 0), 4) & ":" & ADDRESS(1048576, MATCH($D$2 & " " & E$3, rawv3!$1:$1, 0), 4)), F$4, INDIRECT("rawv3!" & ADDRESS(1, MATCH($B$4 & " " & $B15, rawv3!$1:$1, 0), 4) & ":" & ADDRESS(1048576, MATCH($B$4 & " " & $B15, rawv3!$1:$1, 0), 4)), $C15 )} -> 708 | H15: {=COUNTIFS( rawv3!$F:$F, "<>Ongoing", INDIRECT("rawv3!" & ADDRESS(1, MATCH($D$2 & " " & H$3, rawv3!$1:$1, 0), 4) & ":" & ADDRESS(1048576, MATCH($D$2 & " " & H$3, rawv3!$1:$1, 0), 4)), H$4, INDIRECT("rawv3!" & ADDRESS(1, MATCH($B$4 & " " & $B15, rawv3!$1:$1, 0), 4) & ":" & ADDRESS(1048576, MATCH($B$4 & " " & $B15, rawv3!$1:$1, 0), 4)), $C15 )} -> 844 | I15: {=COUNTIFS( rawv3!$F:$F, "<>Ongoing", INDIRECT("rawv3!" & ADDRESS(1, MATCH($D$2 & " " & H$3, rawv3!$1:$1, 0), 4) & ":" & ADDRESS(1048576, MATCH($D$2 & " " & H$3, rawv3!$1:$1, 0), 4)), I$4, INDIRECT("rawv3!" & ADDRESS(1, MATCH($B$4 & " " & $B15, rawv3!$1:$1, 0), 4) & ":" & ADDRESS(1048576, MATCH($B$4 & " " & $B15, rawv3!$1:$1, 0), 4)), $C15 )} -> 557 | K15: {=COUNTIFS( rawv3!$F:$F, "<>Ongoing", INDIRECT("rawv3!" & ADDRESS(1, MATCH($D$2 & " " & K$3, rawv3!$1:$1, 0), 4) & ":" & ADDRESS(1048576, MATCH($D$2 & " " & K$3, rawv3!$1:$1, 0), 4)), K$4, INDIRECT("rawv3!" & ADDRESS(1, MATCH($B$4 & " " & $B15, rawv3!$1:$1, 0), 4) & ":" & ADDRESS(1048576, MATCH($B$4 & " " & $B15, rawv3!$1:$1, 0), 4)), $C15 )} -> 790 | L15: {=COUNTIFS( rawv3!$F:$F, "<>Ongoing", INDIRECT("rawv3!" & ADDRESS(1, MATCH($D$2 & " " & K$3, rawv3!$1:$1, 0), 4) & ":" & ADDRESS(1048576, MATCH($D$2 & " " & K$3, rawv3!$1:$1, 0), 4)), L$4, INDIRECT("rawv3!" & ADDRESS(1, MATCH($B$4 & " " & $B15, rawv3!$1:$1, 0), 4) & ":" & ADDRESS(1048576, MATCH($B$4 & " " & $B15, rawv3!$1:$1, 0), 4)), $C15 )} -> 611 | N15: {=COUNTIFS( rawv3!$F:$F, "<>Ongoing", INDIRECT("rawv3!" & ADDRESS(1, MATCH($D$2 & " " & N$3, rawv3!$1:$1, 0), 4) & ":" & ADDRESS(1048576, MATCH($D$2 & " " & N$3, rawv3!$1:$1, 0), 4)), N$4, INDIRECT("rawv3!" & ADDRESS(1, MATCH($B$4 & " " & $B15, rawv3!$1:$1, 0), 4) & ":" & ADDRESS(1048576, MATCH($B$4 & " " & $B15, rawv3!$1:$1, 0), 4)), $C15 )} -> 833 | O15: {=COUNTIFS( rawv3!$F:$F, "<>Ongoing", INDIRECT("rawv3!" & ADDRESS(1, MATCH($D$2 & " " & N$3, rawv3!$1:$1, 0), 4) & ":" & ADDRESS(1048576, MATCH($D$2 & " " & N$3, rawv3!$1:$1, 0), 4)), O$4, INDIRECT("rawv3!" & ADDRESS(1, MATCH($B$4 & " " & $B15, rawv3!$1:$1, 0), 4) & ":" & ADDRESS(1048576, MATCH($B$4 & " " & $B15, rawv3!$1:$1, 0), 4)), $C15 )} -> 568 | Q15: {=COUNTIFS( rawv3!$F:$F, "<>Ongoing", INDIRECT("rawv3!" & ADDRESS(1, MATCH($D$2 & " " & Q$3, rawv3!$1:$1, 0), 4) & ":" & ADDRESS(1048576, MATCH($D$2 & " " & Q$3, rawv3!$1:$1, 0), 4)), Q$4, INDIRECT("rawv3!" & ADDRESS(1, MATCH($B$4 & " " & $B15, rawv3!$1:$1, 0), 4) & ":" & ADDRESS(1048576, MATCH($B$4 & " " & $B15, rawv3!$1:$1, 0), 4)), $C15 )} -> 1006 | R15: {=COUNTIFS( rawv3!$F:$F, "<>Ongoing", INDIRECT("rawv3!" & ADDRESS(1, MATCH($D$2 & " " & Q$3, rawv3!$1:$1, 0), 4) & ":" & ADDRESS(1048576, MATCH($D$2 & " " & Q$3, rawv3!$1:$1, 0), 4)), R$4, INDIRECT("rawv3!" & ADDRESS(1, MATCH($B$4 & " " & $B15, rawv3!$1:$1, 0), 4) & ":" & ADDRESS(1048576, MATCH($B$4 & " " & $B15, rawv3!$1:$1, 0), 4)), $C15 )} -> 394 | T15: {=COUNTIFS( rawv3!$F:$F, "<>Ongoing", INDIRECT("rawv3!" & ADDRESS(1, MATCH($D$2 & " " & T$3, rawv3!$1:$1, 0), 4) & ":" & ADDRESS(1048576, MATCH($D$2 & " " & T$3, rawv3!$1:$1, 0), 4)), T$4, INDIRECT("rawv3!" & ADDRESS(1, MATCH($B$4 & " " & $B15, rawv3!$1:$1, 0), 4) & ":" & ADDRESS(1048576, MATCH($B$4 & " " & $B15, rawv3!$1:$1, 0), 4)), $C15 )} -> 1055 | U15: {=COUNTIFS( rawv3!$F:$F, "<>Ongoing", INDIRECT("rawv3!" & ADDRESS(1, MATCH($D$2 & " " & T$3, rawv3!$1:$1, 0), 4) & ":" & ADDRESS(1048576, MATCH($D$2 & " " & T$3, rawv3!$1:$1, 0), 4)), U$4, INDIRECT("rawv3!" & ADDRESS(1, MATCH($B$4 & " " & $B15, rawv3!$1:$1, 0), 4) & ":" & ADDRESS(1048576, MATCH($B$4 & " " & $B15, rawv3!$1:$1, 0), 4)), $C15 )} -> 345 | W15: {=COUNTIFS( rawv3!$F:$F, "<>Ongoing", INDIRECT("rawv3!" & ADDRESS(1, MATCH($D$2 & " " & W$3, rawv3!$1:$1, 0), 4) & ":" & ADDRESS(1048576, MATCH($D$2 & " " & W$3, rawv3!$1:$1, 0), 4)), W$4, INDIRECT("rawv3!" & ADDRESS(1, MATCH($B$4 & " " & $B15, rawv3!$1:$1, 0), 4) & ":" & ADDRESS(1048576, MATCH($B$4 & " " & $B15, rawv3!$1:$1, 0), 4)), $C15 )} -> 632 | X15: {=COUNTIFS( rawv3!$F:$F, "<>Ongoing", INDIRECT("rawv3!" & ADDRESS(1, MATCH($D$2 & " " & W$3, rawv3!$1:$1, 0), 4) & ":" & ADDRESS(1048576, MATCH($D$2 & " " & W$3, rawv3!$1:$1, 0), 4)), X$4, INDIRECT("rawv3!" & ADDRESS(1, MATCH($B$4 & " " & $B15, rawv3!$1:$1, 0), 4) & ":" & ADDRESS(1048576, MATCH($B$4 & " " & $B15, rawv3!$1:$1, 0), 4)), $C15 )} -> 769 | Z15: {=COUNTIFS( rawv3!$F:$F, "<>Ongoing", INDIRECT("rawv3!" & ADDRESS(1, MATCH($B$4 & " " & $B15, rawv3!$1:$1, 0), 4) & ":" & ADDRESS(1048576, MATCH($B$4 & " " & $B15, rawv3!$1:$1, 0), 4)), $C15)} -> 1401
D16: F90D % | E16: =(Matrix!E16-Matrix!$Z$41)/Matrix!$Z$41 -> -0.028986274 | F16: =(Matrix!F16-Matrix!$Z$41)/Matrix!$Z$41 -> 0.025491424 | H16: =(Matrix!H16-Matrix!$Z$41)/Matrix!$Z$41 -> 0.004371405 | I16: =(Matrix!I16-Matrix!$Z$41)/Matrix!$Z$41 -> -0.0081592154 | K16: =(Matrix!K16-Matrix!$Z$41)/Matrix!$Z$41 -> 0.010471634 | L16: =(Matrix!L16-Matrix!$Z$41)/Matrix!$Z$41 -> -0.01493913 | N16: =(Matrix!N16-Matrix!$Z$41)/Matrix!$Z$41 -> 0.020676668 | O16: =(Matrix!O16-Matrix!$Z$41)/Matrix!$Z$41 -> -0.031829017 | Q16: =(Matrix!Q16-Matrix!$Z$41)/Matrix!$Z$41 -> 0.0076336787 | R16: =(Matrix!R16-Matrix!$Z$41)/Matrix!$Z$41 -> -0.022339587 | T16: =(Matrix!T16-Matrix!$Z$41)/Matrix!$Z$41 -> 0.011277397 | U16: =(Matrix!U16-Matrix!$Z$41)/Matrix!$Z$41 -> -0.037739044 | W16: =(Matrix!W16-Matrix!$Z$41)/Matrix!$Z$41 -> -0.01158231 | X16: =(Matrix!X16-Matrix!$Z$41)/Matrix!$Z$41 -> 0.0084067657 | Z16: =(Matrix!Z16-Matrix!$Z$41)/Matrix!$Z$41 -> -0.00061043339
C17: Towards visionary ideas | D17: # | E17: {=COUNTIFS( rawv3!$F:$F, "<>Ongoing", INDIRECT("rawv3!" & ADDRESS(1, MATCH($D$2 & " " & E$3, rawv3!$1:$1, 0), 4) & ":" & ADDRESS(1048576, MATCH($D$2 & " " & E$3, rawv3!$1:$1, 0), 4)), E$4, INDIRECT("rawv3!" & ADDRESS(1, MATCH($B$4 & " " & $B15, rawv3!$1:$1, 0), 4) & ":" & ADDRESS(1048576, MATCH($B$4 & " " & $B15, rawv3!$1:$1, 0), 4)), $C17 )} -> 594 | F17: {=COUNTIFS( rawv3!$F:$F, "<>Ongoing", INDIRECT("rawv3!" & ADDRESS(1, MATCH($D$2 & " " & E$3, rawv3!$1:$1, 0), 4) & ":" & ADDRESS(1048576, MATCH($D$2 & " " & E$3, rawv3!$1:$1, 0), 4)), F$4, INDIRECT("rawv3!" & ADDRESS(1, MATCH($B$4 & " " & $B15, rawv3!$1:$1, 0), 4) & ":" & ADDRESS(1048576, MATCH($B$4 & " " & $B15, rawv3!$1:$1, 0), 4)), $C17 )} -> 542 | H17: {=COUNTIFS( rawv3!$F:$F, "<>Ongoing", INDIRECT("rawv3!" & ADDRESS(1, MATCH($D$2 & " " & H$3, rawv3!$1:$1, 0), 4) & ":" & ADDRESS(1048576, MATCH($D$2 & " " & H$3, rawv3!$1:$1, 0), 4)), H$4, INDIRECT("rawv3!" & ADDRESS(1, MATCH($B$4 & " " & $B15, rawv3!$1:$1, 0), 4) & ":" & ADDRESS(1048576, MATCH($B$4 & " " & $B15, rawv3!$1:$1, 0), 4)), $C17 )} -> 700 | I17: {=COUNTIFS( rawv3!$F:$F, "<>Ongoing", INDIRECT("rawv3!" & ADDRESS(1, MATCH($D$2 & " " & H$3, rawv3!$1:$1, 0), 4) & ":" & ADDRESS(1048576, MATCH($D$2 & " " & H$3, rawv3!$1:$1, 0), 4)), I$4, INDIRECT("rawv3!" & ADDRESS(1, MATCH($B$4 & " " & $B15, rawv3!$1:$1, 0), 4) & ":" & ADDRESS(1048576, MATCH($B$4 & " " & $B15, rawv3!$1:$1, 0), 4)), $C17 )} -> 437 | K17: {=COUNTIFS( rawv3!$F:$F, "<>Ongoing", INDIRECT("rawv3!" & ADDRESS(1, MATCH($D$2 & " " & K$3, rawv3!$1:$1, 0), 4) & ":" & ADDRESS(1048576, MATCH($D$2 & " " & K$3, rawv3!$1:$1, 0), 4)), K$4, INDIRECT("rawv3!" & ADDRESS(1, MATCH($B$4 & " " & $B15, rawv3!$1:$1, 0), 4) & ":" & ADDRESS(1048576, MATCH($B$4 & " " & $B15, rawv3!$1:$1, 0), 4)), $C17 )} -> 432 | L17: {=COUNTIFS( rawv3!$F:$F, "<>Ongoing", INDIRECT("rawv3!" & ADDRESS(1, MATCH($D$2 & " " & K$3, rawv3!$1:$1, 0), 4) & ":" & ADDRESS(1048576, MATCH($D$2 & " " & K$3, rawv3!$1:$1, 0), 4)), L$4, INDIRECT("rawv3!" & ADDRESS(1, MATCH($B$4 & " " & $B15, rawv3!$1:$1, 0), 4) & ":" & ADDRESS(1048576, MATCH($B$4 & " " & $B15, rawv3!$1:$1, 0), 4)), $C17 )} -> 704 | N17: {=COUNTIFS( rawv3!$F:$F, "<>Ongoing", INDIRECT("rawv3!" & ADDRESS(1, MATCH($D$2 & " " & N$3, rawv3!$1:$1, 0), 4) & ":" & ADDRESS(1048576, MATCH($D$2 & " " & N$3, rawv3!$1:$1, 0), 4)), N$4, INDIRECT("rawv3!" & ADDRESS(1, MATCH($B$4 & " " & $B15, rawv3!$1:$1, 0), 4) & ":" & ADDRESS(1048576, MATCH($B$4 & " " & $B15, rawv3!$1:$1, 0), 4)), $C17 )} -> 688 | O17: {=COUNTIFS( rawv3!$F:$F, "<>Ongoing", INDIRECT("rawv3!" & ADDRESS(1, MATCH($D$2 & " " & N$3, rawv3!$1:$1, 0), 4) & ":" & ADDRESS(1048576, MATCH($D$2 & " " & N$3, rawv3!$1:$1, 0), 4)), O$4, INDIRECT("rawv3!" & ADDRESS(1, MATCH($B$4 & " " & $B15, rawv3!$1:$1, 0), 4) & ":" & ADDRESS(1048576, MATCH($B$4 & " " & $B15, rawv3!$1:$1, 0), 4)), $C17 )} -> 449 | Q17: {=COUNTIFS( rawv3!$F:$F, "<>Ongoing", INDIRECT("rawv3!" & ADDRESS(1, MATCH($D$2 & " " & Q$3, rawv3!$1:$1, 0), 4) & ":" & ADDRESS(1048576, MATCH($D$2 & " " & Q$3, rawv3!$1:$1, 0), 4)), Q$4, INDIRECT("rawv3!" & ADDRESS(1, MATCH($B$4 & " " & $B15, rawv3!$1:$1, 0), 4) & ":" & ADDRESS(1048576, MATCH($B$4 & " " & $B15, rawv3!$1:$1, 0), 4)), $C17 )} -> 834 | R17: {=COUNTIFS( rawv3!$F:$F, "<>Ongoing", INDIRECT("rawv3!" & ADDRESS(1, MATCH($D$2 & " " & Q$3, rawv3!$1:$1, 0), 4) & ":" & ADDRESS(1048576, MATCH($D$2 & " " & Q$3, rawv3!$1:$1, 0), 4)), R$4, INDIRECT("rawv3!" & ADDRESS(1, MATCH($B$4 & " " & $B15, rawv3!$1:$1, 0), 4) & ":" & ADDRESS(1048576, MATCH($B$4 & " " & $B15, rawv3!$1:$1, 0), 4)), $C17 )} -> 302 | T17: {=COUNTIFS( rawv3!$F:$F, "<>Ongoing", INDIRECT("rawv3!" & ADDRESS(1, MATCH($D$2 & " " & T$3, rawv3!$1:$1, 0), 4) & ":" & ADDRESS(1048576, MATCH($D$2 & " " & T$3, rawv3!$1:$1, 0), 4)), T$4, INDIRECT("rawv3!" & ADDRESS(1, MATCH($B$4 & " " & $B15, rawv3!$1:$1, 0), 4) & ":" & ADDRESS(1048576, MATCH($B$4 & " " & $B15, rawv3!$1:$1, 0), 4)), $C17 )} -> 866 | U17: {=COUNTIFS( rawv3!$F:$F, "<>Ongoing", INDIRECT("rawv3!" & ADDRESS(1, MATCH($D$2 & " " & T$3, rawv3!$1:$1, 0), 4) & ":" & ADDRESS(1048576, MATCH($D$2 & " " & T$3, rawv3!$1:$1, 0), 4)), U$4, INDIRECT("rawv3!" & ADDRESS(1, MATCH($B$4 & " " & $B15, rawv3!$1:$1, 0), 4) & ":" & ADDRESS(1048576, MATCH($B$4 & " " & $B15, rawv3!$1:$1, 0), 4)), $C17 )} -> 271 | W17: {=COUNTIFS( rawv3!$F:$F, "<>Ongoing", INDIRECT("rawv3!" & ADDRESS(1, MATCH($D$2 & " " & W$3, rawv3!$1:$1, 0), 4) & ":" & ADDRESS(1048576, MATCH($D$2 & " " & W$3, rawv3!$1:$1, 0), 4)), W$4, INDIRECT("rawv3!" & ADDRESS(1, MATCH($B$4 & " " & $B15, rawv3!$1:$1, 0), 4) & ":" & ADDRESS(1048576, MATCH($B$4 & " " & $B15, rawv3!$1:$1, 0), 4)), $C17 )} -> 495 | X17: {=COUNTIFS( rawv3!$F:$F, "<>Ongoing", INDIRECT("rawv3!" & ADDRESS(1, MATCH($D$2 & " " & W$3, rawv3!$1:$1, 0), 4) & ":" & ADDRESS(1048576, MATCH($D$2 & " " & W$3, rawv3!$1:$1, 0), 4)), X$4, INDIRECT("rawv3!" & ADDRESS(1, MATCH($B$4 & " " & $B15, rawv3!$1:$1, 0), 4) & ":" & ADDRESS(1048576, MATCH($B$4 & " " & $B15, rawv3!$1:$1, 0), 4)), $C17 )} -> 642 | Z17: {=COUNTIFS( rawv3!$F:$F, "<>Ongoing", INDIRECT("rawv3!" & ADDRESS(1, MATCH($B$4 & " " & $B15, rawv3!$1:$1, 0), 4) & ":" & ADDRESS(1048576, MATCH($B$4 & " " & $B15, rawv3!$1:$1, 0), 4)), $C17)} -> 1137
D18: F90D % | E18: =(Matrix!E18-Matrix!$Z$41)/Matrix!$Z$41 -> 0.0068533563 | F18: =(Matrix!F18-Matrix!$Z$41)/Matrix!$Z$41 -> -0.0064257857 | H18: =(Matrix!H18-Matrix!$Z$41)/Matrix!$Z$41 -> 0.013679481 | I18: =(Matrix!I18-Matrix!$Z$41)/Matrix!$Z$41 -> -0.019955193 | K18: =(Matrix!K18-Matrix!$Z$41)/Matrix!$Z$41 -> -0.026210684 | L18: =(Matrix!L18-Matrix!$Z$41)/Matrix!$Z$41 -> 0.01871908 | N18: =(Matrix!N18-Matrix!$Z$41)/Matrix!$Z$41 -> -0.012841203 | O18: =(Matrix!O18-Matrix!$Z$41)/Matrix!$Z$41 -> 0.021581214 | Q18: =(Matrix!Q18-Matrix!$Z$41)/Matrix!$Z$41 -> 0.0072984049 | R18: =(Matrix!R18-Matrix!$Z$41)/Matrix!$Z$41 -> -0.014012094 | T18: =(Matrix!T18-Matrix!$Z$41)/Matrix!$Z$41 -> -0.0079753349 | U18: =(Matrix!U18-Matrix!$Z$41)/Matrix!$Z$41 -> 0.02864154 | W18: =(Matrix!W18-Matrix!$Z$41)/Matrix!$Z$41 -> -0.014478283 | X18: =(Matrix!X18-Matrix!$Z$41)/Matrix!$Z$41 -> 0.012495276 | Z18: =(Matrix!Z18-Matrix!$Z$41)/Matrix!$Z$41 -> 0.0007521699
